Workbook

Sheet GRÁFICO

Sheet BALANÇO
B2: Balanço
B3: MÊS | C3: FATURADO | D3: LUCRO | E3: CUSTO | F3: RECEBERÁ | G3: PAGARÁ | H3: PAGO | I3: RECEBIDO
B4: JANEIRO | C4: =JANEIRO!D64 -> 9265.25 | D4: =JANEIRO!D65 -> 6404.25 | E4: =JANEIRO!D66 -> 2861 | F4: =JANEIRO!D67 -> 0 | G4: =JANEIRO!D68 -> 0 | H4: =JANEIRO!D69 -> 2861 | I4: =JANEIRO!D70 -> 6404.25
B5: FEVEREIRO | C5: =FEVEREIRO!D112 -> 21209.25 | D5: =FEVEREIRO!D113 -> 12807.48 | E5: =FEVEREIRO!D114 -> 8401.77 | F5: =FEVEREIRO!D115 -> 0 | G5: =FEVEREIRO!D116 -> 0 | H5: =FEVEREIRO!D117 -> 8401.77 | I5: =FEVEREIRO!D118 -> 12807.48
B6: MARÇO | C6: =MARÇO!D112 -> 21608.56 | D6: =MARÇO!D113 -> 12704.9 | E6: =MARÇO!D114 -> 8903.66 | F6: =MARÇO!D115 -> 0 | G6: =MARÇO!D116 -> 0 | H6: =MARÇO!D117 -> 8903.66 | I6: =MARÇO!D118 -> 12704.9
B7: ABRIL | C7: =ABRIL!D118 -> 27399.38 | D7: =ABRIL!D119 -> 16233 | E7: =ABRIL!D120 -> 11166.38 | F7: =ABRIL!D121 -> 0 | G7: =ABRIL!D122 -> 0 | H7: =ABRIL!D123 -> 11166.38 | I7: =ABRIL!D124 -> 16233
B8: MAIO | C8: =MAIO!D121 -> 24879.47 | D8: =MAIO!D122 -> 15081.64 | E8: =MAIO!D123 -> 9797.83 | F8: =MAIO!D124 -> 0 | G8: =MAIO!D125 -> 0 | H8: =MAIO!D126 -> 9797.83 | I8: =MAIO!D127 -> 15081.64
B9: JUNHO | C9: =JUNHO!D182 -> 37820.12 | D9: =JUNHO!D183 -> 22316.3 | E9: =JUNHO!D184 -> 15503.82 | F9: =JUNHO!D185 -> 0 | G9: =JUNHO!D186 -> 0 | H9: =JUNHO!D187 -> 15503.82 | I9: =JUNHO!D188 -> 22316.3
B10: JULHO | C10: =JULHO!D198 -> 39452.25 | D10: =JULHO!D199 -> 23719.95 | E10: =JULHO!D200 -> 15732.3 | F10: =JULHO!D201 -> 0 | G10: =JULHO!D202 -> 0 | H10: =JULHO!D203 -> 15732.3 | I10: =JULHO!D204 -> 23719.95
B11: AGOSTO | C11: =AGOSTO!D161 -> 26653.54 | D11: =AGOSTO!D162 -> 15493 | E11: =AGOSTO!D163 -> 11160.54 | F11: =AGOSTO!D164 -> 0 | G11: =AGOSTO!D165 -> 0 | H11: =AGOSTO!D166 -> 11160.54 | I11: =AGOSTO!D167 -> 15493
B12: SETEMBRO | C12: =SETEMBRO!D165 -> 28175.57 | D12: =SETEMBRO!D166 -> 15790 | E12: =SETEMBRO!D167 -> 12385.57 | F12: =SETEMBRO!D168 -> 0 | G12: =SETEMBRO!D169 -> 0 | H12: =SETEMBRO!D170 -> 12385.57 | I12: =SETEMBRO!D171 -> 15830
B13: OUTUBRO | C13: =OUTUBRO!D114 -> 24788 | D13: =OUTUBRO!D115 -> 14820.1 | E13: =OUTUBRO!D116 -> 9967.9 | F13: =OUTUBRO!D117 -> 0 | G13: =OUTUBRO!D118 -> 0 | H13: =OUTUBRO!D119 -> 9967.9 | I13: =OUTUBRO!D120 -> 14820.1
B14: NOVEMBRO | C14: =NOVEMBRO!D148 -> 27363.64 | D14: =NOVEMBRO!D149 -> 12294.57 | E14: =NOVEMBRO!D150 -> 15069.07 | F14: =NOVEMBRO!D151 -> 3310 | G14: =NOVEMBRO!D152 -> 6180.95 | H14: =NOVEMBRO!D153 -> 8888.12 | I14: =NOVEMBRO!D154 -> 8984.57
B15: DEZEMBRO | C15: =DEZEMBRO!D75 -> 1950 | D15: =DEZEMBRO!D76 -> 1200 | E15: =DEZEMBRO!D77 -> 750 | F15: =DEZEMBRO!D78 -> 1200 | G15: =DEZEMBRO!D79 -> 750 | H15: =DEZEMBRO!D80 -> 0 | I15: =DEZEMBRO!D81 -> 0
B16: TOTAL | C16: =SUM(C4:C15) -> 290565.03 | D16: =SUM(D4:D15) -> 168865.19 | E16: =SUM(E4:E15) -> 121699.84 | F16: =SUM(F4:F15) -> 4510 | G16: =SUM(G4:G15) -> 6930.95 | H16: =SUM(H4:H15) -> 114768.89 | I16: =SUM(I4:I15) -> 164395.19

Sheet JANEIRO
B2: CONTROLE DE DILIGÊNCIAS
B4: SOLICITAÇÃO | C4: Nº. DOC9 | D4: SOLICITANTE | E4: TEL. | F4: TIPO DE DILIGÊNCIA | G4: Processo | H4: DATA | I4: HORA | J4: LOCAL | K4: Cidade - UF | L4: VALOR | M4: DATA PAG | N4: PAGAM. | O4: CONTRATADO | P4: TEL. 2 | Q4: CUSTO | R4: PRAZO | S4: PAGO | T4: STATUS | U4: LUCRO
B5: 45665 | D5: Ana Flavia Tanimoto | E5: 16 99783-4544 | F5: Procotolo | H5: 45666 | L5: 150 | N5: CUMPRIDO | S5: SIM | T5: CUMPRIDO | U5: =Table_2[[#This Row],[VALOR]]-Table_2[[#This Row],[ CUSTO]] -> 150
B6: 45672 | D6: Letícia | E6: 11 94925-2506 | F6: Procotolo | H6: 45672 | J6: Prefeitura Municipal | K6: Canarana/MT | L6: 300 | N6: CUMPRIDO | O6: Geiciany Alencar | P6: 65 9207-4899 | Q6: 150 | S6: SIM | T6: CUMPRIDO | U6: =Table_2[[#This Row],[VALOR]]-Table_2[[#This Row],[ CUSTO]] -> 150
B7: 45673 | D7: Jessica | E7: 41 9685-0539 | F7: Acompanhamento | H7: 45677 | I7: 0.41666667 | J7: Marques de São Vicente | K7: São Paulo - SP | L7: 400 | N7: CUMPRIDO | O7: Diligência Própria | S7: SIM | T7: CUMPRIDO | U7: =Table_2[[#This Row],[VALOR]]-Table_2[[#This Row],[ CUSTO]] -> 400
B8: 45663 | D8: Cláudia Maxxi | E8: 11 99113-8935 | F8: Instrução - Presencial | G8: 0011051.24.2024.5.15.0131 | H8: 45678 | I8: 0.49305556 | J8: 12ª | K8: CAMPINAS - SP | N8: CUMPRIDO | O8: Patricia Von Ah | P8: 19 99155-8565 | Q8: 50 | S8: SIM | T8: CUMPRIDO | U8: =Table_2[[#This Row],[VALOR]]-Table_2[[#This Row],[ CUSTO]] -> -50
B9: 45663 | D9: Cláudia Maxxi | E9: 11 99113-8935 | F9: Una - Presencial | G9: 1000765-56.2024.5.02.0381 | H9: 45678 | I9: 0.35416667 | J9: 1ª | K9: OSASCO - SP | L9: 200 | N9: CUMPRIDO | O9: Joao Tomaz da Silva | P9: 11 97377-8980 | Q9: 70 | S9: SIM | T9: CUMPRIDO | U9: =Table_2[[#This Row],[VALOR]]-Table_2[[#This Row],[ CUSTO]] -> 130
B10: 45672 | D10: Vivian Barbosa | E10: 11 94569-1656 | F10: Audiência UNA | H10: 45678 | I10: 0.58680556 | J10: 10ª Vara do Trabalho | K10: CAMPINAS - SP | L10: 150 | M10: 45726 | N10: CUMPRIDO | O10: Miriam Pinatto Gehring | P10: 19 99220-3513 | Q10: 70 | S10: SIM | T10: CUMPRIDO | U10: =Table_2[[#This Row],[VALOR]]-Table_2[[#This Row],[ CUSTO]] -> 80
B11: 45677 | D11: Mayara | E11: 12 98170-8541 | F11: Procotolo | H11: 45678 | J11: Prefeitura Municipal | K11: Balneário Piçarras - SP | U11: =Table_2[[#This Row],[VALOR]]-Table_2[[#This Row],[ CUSTO]] -> 0
B12: 45663 | D12: Cláudia Maxxi | E12: 11 99113-8935 | F12: Una - Presencial | G12: 0010932-51.2024.5.15.0038 | H12: 45679 | I12: 0.44444444 | J12: Única | K12: BRAGANÇA PAULISTA - SP | L12: 200 | N12: CUMPRIDO | O12: Patricia Von Ah | P12: 19 99155-8565 | Q12: 70 | R12: ok | S12: SIM | T12: CUMPRIDO | U12: =Table_2[[#This Row],[VALOR]]-Table_2[[#This Row],[ CUSTO]] -> 130
B13: 45673 | D13: Andrezza | E13: 62 8268-9720 | F13: Audiência de Conciliação | H13: 45679 | I13: 0.375 | J13: Departamento de Defesa do Consumidor | K13: Atibaia - SP | L13: 150 | N13: CUMPRIDO | O13: Patricia Von Ah | P13: 19 99155-8565 | Q13: 50 | S13: SIM | T13: CUMPRIDO | U13: =Table_2[[#This Row],[VALOR]]-Table_2[[#This Row],[ CUSTO]] -> 100
B14: 45677 | D14: Dalila Passos | E14: 11 94535-7095 | F14: Audiência | G14: 1001623-52.2024.5.02.0231 | H14: 45679 | I14: 0.38541667 | J14: 1ª | K14: Carapicuíba - SP | L14: 150 | N14: CUMPRIDO | O14: Camila Roncalle | P14: 11 98992-0599 | Q14: 70 | S14: SIM | T14: CUMPRIDO | U14: =Table_2[[#This Row],[VALOR]]-Table_2[[#This Row],[ CUSTO]] -> 80
B15: 45678 | D15: Henriette Brigagão | E15: 35 9215-0702 | F15: Audiência | H15: 45679 | I15: 0.57638889 | J15: 2ª | K15: Suzano - SP | L15: 200 | N15: CUMPRIDO | O15: Fernando Santos | P15: 11 98307-2224 | Q15: 70 | S15: SIM | T15: CUMPRIDO | U15: =Table_2[[#This Row],[VALOR]]-Table_2[[#This Row],[ CUSTO]] -> 130
B16: 45679 | D16: Thiago Coriolano | E16: 11 98775-8123 | F16: Audiência | H16: 45679 | I16: 0.40625 | J16: 9ª | K16: Guarulhos - SP | L16: 200 | N16: CUMPRIDO | O16: Andréia Marques | P16: 11 98815-9490 | Q16: 80 | S16: SIM | T16: CUMPRIDO | U16: =Table_2[[#This Row],[VALOR]]-Table_2[[#This Row],[ CUSTO]] -> 120
B17: 45666 | D17: MTO ADVOGADOS | E17: 31 8107-6333 | F17: Audiência Cível | H17: 45680 | I17: 0.64583333 | J17: Juizado Especial Cível | K17: Santo André - SP | L17: 200 | N17: CUMPRIDO | O17: Raquel Farias Amaral | P17: 11 91914-1798 | Q17: 70 | S17: SIM | T17: CUMPRIDO | U17: =Table_2[[#This Row],[VALOR]]-Table_2[[#This Row],[ CUSTO]] -> 130
B18: 45678 | D18: Jessica | E18: 41 9685-0539 | F18: Acompanhamento | H18: 45680 | I18: 0.58333333 | J18: Marques de São Vicente | K18: São Paulo - SP | L18: =300+36.8 -> 336.8 | N18: CUMPRIDO | O18: Diligência Própria | Q18: 36.8 | S18: SIM | T18: CUMPRIDO | U18: =Table_2[[#This Row],[VALOR]]-Table_2[[#This Row],[ CUSTO]] -> 300
B19: 45678 | D19: Lucas Mançano | E19: 61 9143-8757 | F19: Una - Presencial | G19: 1001852-71.2024.5.02.0373 | H19: 45680 | I19: 0.59375 | J19: 3ª | K19: Mogi das Cruzes - SP | L19: 400 | N19: CUMPRIDO | O19: Tamara Batiston Ferreira | P19: 11 97638-4161 | Q19: 120 | S19: SIM | T19: CUMPRIDO | U19: =Table_2[[#This Row],[VALOR]]-Table_2[[#This Row],[ CUSTO]] -> 280
B20: 45644 | D20: LACOSTA ADVOGADOS | E20: 21 95922-4000 / 11 91039-6920 | F20: Audiência | H20: 45681 | I20: 0.35416667 | J20: 34ª Vara do Trabalho da Barra Funda | K20: São Paulo - SP | L20: 150 | N20: CUMPRIDO | O20: Joao Tomaz da Silva | P20: 11 97377-8980 | Q20: 70 | S20: SIM | T20: CUMPRIDO | U20: =Table_2[[#This Row],[VALOR]]-Table_2[[#This Row],[ CUSTO]] -> 80
B21: 45671 | D21: Marina Demenciano | E21: 19 99438-7420 | F21: Audiência UNA | G21: 1001889-78.2024.5.02.0024 | H21: 45681 | I21: 0.38194444 | J21: 24ª Vara do Trabalho da Barra Funda | K21: São Paulo - SP | L21: 200 | M21: 45693 | N21: CUMPRIDO | O21: Rafael Fernandes Capelas Yamakami | P21: 11 99939-8419 | Q21: 70 | S21: SIM | T21: CUMPRIDO | U21: =Table_2[[#This Row],[VALOR]]-Table_2[[#This Row],[ CUSTO]] -> 130
B22: 45681 | D22: Jessica | E22: 41 9685-0539 | F22: Coleta de Assinaturas | H22: 45682 | I22: 0.58333333 | K22: São Paulo - SP | L22: 536.8 | N22: CUMPRIDO | O22: Diligência Própria | Q22: 36.8 | S22: SIM | T22: CUMPRIDO | U22: =Table_2[[#This Row],[VALOR]]-Table_2[[#This Row],[ CUSTO]] -> 500
B23: 45644 | D23: LACOSTA ADVOGADOS | E23: 21 95922-4000 / 11 91039-6920 | F23: Audiência | H23: 45684 | I23: 0.66666667 | J23: 66ª Vara do Trabalho da Barra Funda | K23: São Paulo - SP | L23: 150 | N23: CUMPRIDO | O23: Joao Tomaz da Silva | P23: 11 97377-8980 | Q23: 70 | S23: SIM | T23: CUMPRIDO | U23: =Table_2[[#This Row],[VALOR]]-Table_2[[#This Row],[ CUSTO]] -> 80
B24: 45663 | D24: Cláudia Maxxi | E24: 11 99113-8935 | F24: Instrução - Presencial | G24: 1001604-18.2023.5.02.0381 | H24: 45684 | I24: 0.375 | J24: 1ª | K24: OSASCO - SP | L24: 200 | M24: 45688 | N24: CUMPRIDO | O24: Joao Tomaz da Silva | P24: 11 97377-8980 | Q24: 70 | S24: SIM | T24: CUMPRIDO | U24: =Table_2[[#This Row],[VALOR]]-Table_2[[#This Row],[ CUSTO]] -> 130
B25: 45671 | D25: Marina Demenciano | E25: 19 99438-7420 | F25: Audiência UNA | G25: 1001856-14.2024.5.02.0081 | H25: 45684 | I25: 0.56944444 | J25: 81ª Vara do Trabalho da Barra Funda | K25: São Paulo - SP | L25: 200 | M25: 45693 | N25: CUMPRIDO | O25: Joao Tomaz da Silva | P25: 11 97377-8980 | Q25: 70 | S25: SIM | T25: CUMPRIDO | U25: =Table_2[[#This Row],[VALOR]]-Table_2[[#This Row],[ CUSTO]] -> 130
B26: 45681 | D26: Beatriz Aragão & Bernardo | E26: 85 3252-2939 - 85 8405-1478 | F26: Audiência UNA | G26: 1001776-94.2024.5.02.0713 | H26: 45684 | I26: 0.5625 | J26: 88ª da Barra Funda | K26: São Paulo - SP | L26: 200 | N26: CUMPRIDO | O26: Amanda Pivott | P26: 11 94857-0549 | Q26: 70 | S26: SIM | T26: CUMPRIDO | U26: =Table_2[[#This Row],[VALOR]]-Table_2[[#This Row],[ CUSTO]] -> 130
B27: 45681 | C27: 4636037 | D27: DOC9 | F27: Audiência UNA | G27: 1001814-59.2024.5.02.0373 | H27: 45684 | I27: 0.63194444 | J27: 3ª | K27: Mogi das Cruzes - SP | L27: 84.25 | M27: 45703 | N27: CUMPRIDO | O27: Diligência Própria | S27: SIM | T27: CUMPRIDO | U27: =Table_2[[#This Row],[VALOR]]-Table_2[[#This Row],[ CUSTO]] -> 84.25
B28: 45681 | D28: Gabriel Belarmino | E28: 11 98863-8637 | F28: Despacho | G28: 1013171-35.2023.4.06.3803 | H28: 45684 | J28: 3ª Vara Federal | K28: Uberlândia - MG | L28: 250 | N28: CUMPRIDO | O28: Gabriela Viana | P28: 34 9135-5994 | Q28: 70 | S28: SIM | T28: CUMPRIDO | U28: =Table_2[[#This Row],[VALOR]]-Table_2[[#This Row],[ CUSTO]] -> 180
B29: 45684 | D29: Thiago Coriolano | E29: 11 98775-8123 | F29: Procotolo | H29: 45684 | K29: Taubaté - SP | L29: 180 | N29: CUMPRIDO | O29: Tamyres Fim | P29: 12 99181-8165 | Q29: 40 | S29: SIM | T29: CUMPRIDO | U29: =Table_2[[#This Row],[VALOR]]-Table_2[[#This Row],[ CUSTO]] -> 140
B30: 45660 | D30: Leticia Prado | E30: 11 94744-8723 | F30: Audiência Cível | H30: 45685 | I30: 0.64583333 | J30: Juizado Especial Cível | K30: Suzano - SP | L30: 120 | N30: CUMPRIDO | O30: Diligência Própria | S30: SIM | T30: CUMPRIDO | U30: =Table_2[[#This Row],[VALOR]]-Table_2[[#This Row],[ CUSTO]] -> 120
B31: 45663 | D31: Cláudia Maxxi | E31: 11 99113-8935 | F31: Instrução - Presencial | G31: 0011218-81.2023.5.15.0032 | H31: 45685 | I31: 0.66319444 | J31: 10ª | K31: CAMPINAS - SP | L31: 200 | M31: 45688 | N31: CUMPRIDO | O31: Patricia Von Ah | P31: 19 99155-8565 | Q31: 50 | R31: ok | S31: SIM | T31: CUMPRIDO | U31: =Table_2[[#This Row],[VALOR]]-Table_2[[#This Row],[ CUSTO]] -> 150
B32: 45671 | D32: Marina Demenciano | E32: 19 99438-7420 | F32: Audiência UNA | G32: 1001857-12.2024.5.02.0012 | H32: 45685 | I32: 0.39583333 | J32: 12ª Vara do Trabalho da Barra Funda | K32: São Paulo - SP | L32: 200 | M32: 45693 | N32: CUMPRIDO | O32: Joao Tomaz da Silva | P32: 11 97377-8980 | Q32: 70 | S32: SIM | T32: CUMPRIDO | U32: =Table_2[[#This Row],[VALOR]]-Table_2[[#This Row],[ CUSTO]] -> 130
B33: 45674 | D33: Josiane | E33: 45 9979-5193 | F33: Conciliação | G33: 1032551-94.2024.8.26.0577 | H33: 45685 | I33: 0.47916667 | J33: 1ª Vara do Juizado Especial Cível | K33: SÃO JOSE DOS CAMPOS - SP | L33: 120 | N33: CUMPRIDO | O33: Helena Do Amaral Simionelli | P33: 12 99108-0694 | Q33: 70 | S33: SIM | T33: CUMPRIDO | U33: =Table_2[[#This Row],[VALOR]]-Table_2[[#This Row],[ CUSTO]] -> 50
B34: 45681 | D34: Nathalia Fett Advogados | E34: 51 9114-0718 | F34: Audiência UNA | G34: 0020751-10.2024.5.04.0752 | H34: 45685 | I34: 0.4375 | J34: 2ª | K34: Santa Rosa - RS | L34: 200 | M34: 45688 | N34: CUMPRIDO | O34: Eliane Andréia Andreski | P34: 55 9910-8804 | Q34: 120 | S34: SIM | T34: CUMPRIDO | U34: =Table_2[[#This Row],[VALOR]]-Table_2[[#This Row],[ CUSTO]] -> 80
B35: 45684 | D35: Cláudia Maxxi | E35: 11 99113-8935 | F35: Instrução - Presencial | G35: 0011879-65.2023.5.15.0095 | H35: 45685 | I35: 0.44444444 | J35: 8ª | K35: CAMPINAS - SP | M35: perdeu | O35: Patricia Von Ah | P35: 19 99155-8565 | T35: CUMPRIDO | U35: =Table_2[[#This Row],[VALOR]]-Table_2[[#This Row],[ CUSTO]] -> 0
B36: 45685 | D36: Cláudia Maxxi | E36: 11 99113-8935 | F36: Instrução - Presencial | G36: 0010473.67.2024.5.15.0129 | H36: 45685 | I36: 0.36458333 | J36: 10ª | K36: CAMPINAS - SP | L36: 200 | M36: 45688 | N36: CUMPRIDO | O36: Patricia Von Ah | P36: 19 99155-8565 | Q36: 80 | S36: SIM | T36: CUMPRIDO | U36: =Table_2[[#This Row],[VALOR]]-Table_2[[#This Row],[ CUSTO]] -> 120
B37: 45663 | D37: Cláudia Maxxi | E37: 11 99113-8935 | F37: Instrução -Presencial | G37: 0010259-70.2024.5.15.0131 | H37: 45686 | I37: 0.53472222 | J37: 12ª | K37: CAMPINAS - SP | M37: 45688 | N37: CUMPRIDO | O37: Patricia Von Ah | P37: 19 99155-8565 | Q37: 50 | R37: ok | S37: SIM | T37: CUMPRIDO | U37: =Table_2[[#This Row],[VALOR]]-Table_2[[#This Row],[ CUSTO]] -> -50
B38: 45663 | D38: Cláudia Maxxi | E38: 11 99113-8935 | F38: Una - Presencial | G38: 0010467-98.2024.5.15.0084 | H38: 45686 | I38: 0.59722222 | J38: 4ª | K38: SÃO JOSE DOS CAMPOS - SP | L38: 200 | M38: 45688 | N38: CUMPRIDO | O38: Helena Do Amaral Simionelli | P38: 12 99108-0694 | Q38: 50 | S38: SIM | T38: CUMPRIDO | U38: =Table_2[[#This Row],[VALOR]]-Table_2[[#This Row],[ CUSTO]] -> 150
B39: 45681 | D39: Vivian Barbosa | E39: 11 94569-1656 | F39: Despacho | G39: 0011091-74.2023.5.15.0152 | H39: 45686 | J39: Vara do Trabalho | K39: Hortolândia - SP | L39: 200 | M39: 45726 | N39: CUMPRIDO | O39: Anna Asahara | P39: 19 97408-8344 | Q39: 50 | S39: SIM | T39: CUMPRIDO | U39: =Table_2[[#This Row],[VALOR]]-Table_2[[#This Row],[ CUSTO]] -> 150
B40: 45681 | D40: Vivian Barbosa | E40: 11 94569-1656 | F40: Instrução -Presencial | G40: 0001491-58.2024.5.09.0670 | H40: 45686 | I40: 0.44444444 | J40: 1ª | K40: São José dos Pinhais - PR | L40: 300 | M40: 45726 | N40: CUMPRIDO | O40: Katia Sousa | P40: 41 9155-8251 | Q40: 120 | S40: SIM | T40: CUMPRIDO | U40: =Table_2[[#This Row],[VALOR]]-Table_2[[#This Row],[ CUSTO]] -> 180
B41: 45681 | D41: Vivian Barbosa | E41: 11 94569-1656 | F41: Instrução -Presencial | G41: 0011171-07.2024.5.15.0054 | H41: 45686 | I41: 0.61458333 | J41: 1ª | K41: Sertãozinho - SP | L41: 450 | M41: 45726 | N41: CUMPRIDO | O41: Lídia Maria Nascimento Alves da Silva | P41: 16 99401-0695 | Q41: 200 | S41: SIM | T41: CUMPRIDO | U41: =Table_2[[#This Row],[VALOR]]-Table_2[[#This Row],[ CUSTO]] -> 250
B42: 45681 | D42: Vivian Barbosa | E42: 11 94569-1656 | F42: Instrução -Presencial | G42: 0010337-02.2024.5.15.0087 | H42: 45686 | I42: 0.65972222 | J42: 1ª | K42: Paulínia - SP | L42: 300 | M42: 45726 | N42: CUMPRIDO | O42: Andréia Manzini | P42: 19 99452-9159 | Q42: 80 | S42: SIM | T42: CUMPRIDO | U42: =Table_2[[#This Row],[VALOR]]-Table_2[[#This Row],[ CUSTO]] -> 220
B43: 45684 | D43: Bruno Magalhães | E43: 62 9166-2415 | F43: Una - Presencial | H43: 45687 | I43: 0.36805556 | J43: 14ª Vara do Trabalho | K43: Fortaleza - CE | L43: 400 | N43: CUMPRIDO | O43: Karla Alves | P43: 85 8698-0343 | Q43: 80 | S43: SIM | T43: CUMPRIDO | U43: =Table_2[[#This Row],[VALOR]]-Table_2[[#This Row],[ CUSTO]] -> 320
B44: 45686 | D44: Jessica | E44: 41 9685-0539 | F44: Acompanhamento | H44: 45687 | I44: 0.41666667 | K44: Vitória - ES | L44: 150 | N44: CUMPRIDO | O44: Pedro Rodrigues Gomes | P44: 27 99286-8848 | Q44: 30 | S44: SIM | T44: CUMPRIDO | U44: =Table_2[[#This Row],[VALOR]]-Table_2[[#This Row],[ CUSTO]] -> 120
B45: 45663 | D45: Cláudia Maxxi | E45: 11 99113-8935 | F45: Instrução -Presencial | G45: 0012024-98.2023.5.15.0038 | H45: 45688 | I45: 0.63194444 | J45: ÚNICA | K45: BRAGANÇA PAULISTA - SP | L45: 200 | M45: 45688 | N45: CUMPRIDO | O45: Patricia Von Ah | P45: 19 99155-8565 | Q45: 70 | R45: ok | S45: SIM | T45: CUMPRIDO | U45: =Table_2[[#This Row],[VALOR]]-Table_2[[#This Row],[ CUSTO]] -> 130
B46: 45687 | D46: Thulyo Augustto | E46: 62 9683-9870 | F46: Conciliação | H46: 45688 | I46: 0.41875 | J46: Cejusc | K46: Brasília - DF | L46: 250 | M46: 45688 | N46: CUMPRIDO | O46: Luana Amancio | P46: 61 8542-3080 | Q46: 80 | S46: SIM | T46: CUMPRIDO | U46: =Table_2[[#This Row],[VALOR]]-Table_2[[#This Row],[ CUSTO]] -> 170
B47: 45687 | D47: Rodrigo Bezerra | E47: 11 99360-4364 | F47: Conciliação | G47: 1035149-55.2024.8.26.0016 | H47: 45688 | I47: 0.6875 | J47: 2ª Vara do Juizado Especial Cível - Vergueiro | K47: São Paulo - SP | L47: 180 | M47: 45688 | N47: CUMPRIDO | O47: Elisangela ES - SOLUÇÕES JURÍDICAS | P47: 11 93067-5163 | Q47: 80 | S47: SIM | T47: CUMPRIDO | U47: =Table_2[[#This Row],[VALOR]]-Table_2[[#This Row],[ CUSTO]] -> 100
B48: 45688 | D48: Jessica | E48: 41 9685-0539 | F48: Acompanhamento | H48: 45688 | I48: 0.5 | K48: Sabara - MG | L48: =407.4 -> 407.4 | N48: CUMPRIDO | O48: Bruno Alves | P48: 31 9972-7505 | Q48: 107.4 | S48: SIM | T48: CUMPRIDO | U48: =Table_2[[#This Row],[VALOR]]-Table_2[[#This Row],[ CUSTO]] -> 300
U49: =Table_2[[#This Row],[VALOR]]-Table_2[[#This Row],[ CUSTO]] -> 0
U50: =Table_2[[#This Row],[VALOR]]-Table_2[[#This Row],[ CUSTO]] -> 0
U51: =Table_2[[#This Row],[VALOR]]-Table_2[[#This Row],[ CUSTO]] -> 0
U52: =Table_2[[#This Row],[VALOR]]-Table_2[[#This Row],[ CUSTO]] -> 0
U53: =Table_2[[#This Row],[VALOR]]-Table_2[[#This Row],[ CUSTO]] -> 0
U54: =Table_2[[#This Row],[VALOR]]-Table_2[[#This Row],[ CUSTO]] -> 0
U55: =Table_2[[#This Row],[VALOR]]-Table_2[[#This Row],[ CUSTO]] -> 0
U56: =Table_2[[#This Row],[VALOR]]-Table_2[[#This Row],[ CUSTO]] -> 0
U57: =Table_2[[#This Row],[VALOR]]-Table_2[[#This Row],[ CUSTO]] -> 0
U58: =Table_2[[#This Row],[VALOR]]-Table_2[[#This Row],[ CUSTO]] -> 0
U59: =Table_2[[#This Row],[VALOR]]-Table_2[[#This Row],[ CUSTO]] -> 0
B64: FATURADO | D64: =SUM(JANEIRO!$L$5:$L$59) -> 9265.25
B65: LUCRO | D65: =SUM(JANEIRO!$U$5:$U$59) -> 6404.25
B66: CUSTO | D66: =SUM(JANEIRO!$Q$5:$Q$59) -> 2861
B67: RECEBERÁ | D67: =SUMIF(JANEIRO!$N$5:$N$59,"PENDENTE",JANEIRO!$U$5:$U$59) -> 0
B68: PAGARÁ | D68: =SUMIF(JANEIRO!$S$5:$S$59,"NÃO",JANEIRO!$Q$5:$Q$59) -> 0
B69: PAGO | D69: =SUMIF(JANEIRO!$S$5:$S$59,"SIM",JANEIRO!$Q$5:$Q$59) -> 2861
B70: RECEBIDO: | D70: =SUMIF(JANEIRO!$N$5:$N$59,"CUMPRIDO",JANEIRO!$U$5:$U$59) -> 6404.25

Sheet FEVEREIRO
B2: CONTROLE DE DILIGÊNCIAS
B4: SOLICITAÇÃO | C4: Nº. DOC9 | D4: SOLICITANTE | E4: TEL. | F4: TIPO DE DILIGÊNCIA | G4: Processo | H4: DATA | I4: HORA | J4: LOCAL | K4: Cidade - UF | L4: VALOR | M4: DATA PAG | N4: PAGAM. | O4: CONTRATADO | P4: TEL. 2 | Q4: CUSTO | R4: PRAZO | S4: PAGO | T4: STATUS | U4: LUCRO
B5: 45685 | D5: Cláudia Maxxi | E5: 11 99113-8935 | F5: Una-Presencial | G5: 0010465-31.2024.5.15.0084 | H5: 45691 | I5: 0.5625 | J5: 4ª | K5: SÃO JOSE DOS CAMPOS | L5: 200 | N5: CUMPRIDO | O5: Helena Do Amaral Simionelli | P5: 12 99108-0694 | Q5: 50 | S5: SIM | T5: CUMPRIDO | U5: =Table_3[[#This Row],[VALOR]]-Table_3[[#This Row],[ CUSTO]] -> 150
B6: 45688 | D6: Jessica | E6: 41 9685-0539 | F6: Coleta de Assinaturas | H6: 45691 | I6: 0.72916667 | K6: Bauru - SP | L6: 175 | N6: CUMPRIDO | O6: Lara Estahl Prieto | P6: 14 3218-2500 | Q6: 50 | S6: SIM | T6: CUMPRIDO | U6: =Table_3[[#This Row],[VALOR]]-Table_3[[#This Row],[ CUSTO]] -> 125
B7: 45691 | D7: Cláudia Maxxi | E7: 11 99113-8935 | F7: Instrução - Presencial | G7: 1000426-10.2024.5.02.0701 | H7: 45691 | I7: 0.64583333 | J7: 1ª Vara do Trabalho de São Paulo - Zona Sul | K7: São Paulo - SP | L7: 200 | N7: CUMPRIDO | O7: Israel Bessa | P7: Israel Bessa | Q7: 50 | S7: SIM | T7: CUMPRIDO | U7: =Table_3[[#This Row],[VALOR]]-Table_3[[#This Row],[ CUSTO]] -> 150
B8: 45670 | D8: José Mario Paula | E8: 11 96186-8989 | F8: Acompanhamento | H8: 45692 | I8: 0.41666667 | J8: 1ª Delegacia Territorial | K8: Serrinha - BA | L8: 300 | M8: 45327 | N8: CUMPRIDO | O8: Laryssa Campos | P8: 71 9664-8462 | Q8: 150 | S8: SIM | T8: CUMPRIDO | U8: =Table_3[[#This Row],[VALOR]]-Table_3[[#This Row],[ CUSTO]] -> 150
B9: 45685 | D9: Cláudia Maxxi | E9: 11 99113-8935 | F9: Instrução - Presencial | G9: 0010567-72.2024.5.15.0013 | H9: 45692 | I9: 0.41666667 | J9: 1ª | K9: SÃO JOSÉ DOS CAMPOS | L9: 200 | N9: CUMPRIDO | O9: Helena Do Amaral Simionelli | P9: 12 99108-0694 | Q9: 50 | S9: SIM | T9: CUMPRIDO | U9: =Table_3[[#This Row],[VALOR]]-Table_3[[#This Row],[ CUSTO]] -> 150
B10: 45685 | D10: LACOSTA ADVOGADOS | E10: 21 95922-4000 / 11 91039-6920 | F10: Audiência | H10: 45692 | I10: 0.61805556 | J10: 30ª da Barra Funda | K10: São Paulo - SP | L10: 150 | N10: CUMPRIDO | O10: Joao Tomaz da Silva | P10: 11 97377-8980 | Q10: 70 | S10: SIM | T10: CUMPRIDO | U10: =Table_3[[#This Row],[VALOR]]-Table_3[[#This Row],[ CUSTO]] -> 80
B11: 45687 | D11: Marina Demenciano | E11: 19 99438-7420 | F11: Una - Presencial | H11: 45692 | I11: 0.38541667 | J11: 18ª | K11: Rio de Janeiro - RJ | L11: 280 | N11: CUMPRIDO | O11: Franciely Maciel | P11: 21 95932-7919 | Q11: 140 | S11: SIM | T11: CUMPRIDO | U11: =Table_3[[#This Row],[VALOR]]-Table_3[[#This Row],[ CUSTO]] -> 140
B12: 45687 | D12: Marina Demenciano | E12: 19 99438-7420 | F12: Una - Presencial | H12: 45692 | I12: 0.41666667 | J12: 45ª da Barra Funda | K12: São Paulo - SP | L12: 200 | N12: CUMPRIDO | O12: Joao Tomaz da Silva | P12: 11 97377-8980 | Q12: 70 | S12: SIM | T12: CUMPRIDO | U12: =Table_3[[#This Row],[VALOR]]-Table_3[[#This Row],[ CUSTO]] -> 130
B13: 45687 | D13: Marina Demenciano | E13: 19 99438-7420 | F13: Una - Presencial | H13: 45692 | I13: 0.54861111 | J13: 36ª da Barra Funda | K13: São Paulo - SP | L13: 200 | N13: CUMPRIDO | O13: Joao Tomaz da Silva | P13: 11 97377-8980 | Q13: 70 | S13: SIM | T13: CUMPRIDO | U13: =Table_3[[#This Row],[VALOR]]-Table_3[[#This Row],[ CUSTO]] -> 130
B14: 45688 | D14: Jessica | E14: 41 9685-0539 | F14: Coleta de Assinaturas | G14: Valdevino | H14: 45692 | I14: 0.41666667 | K14: Joanópolis - SP | L14: 500 | N14: CUMPRIDO | O14: Maicon Paulo | P14: 11 97266-7939 | Q14: 125 | S14: SIM | T14: CUMPRIDO | U14: =Table_3[[#This Row],[VALOR]]-Table_3[[#This Row],[ CUSTO]] -> 375
B15: 45688 | D15: Nathalia Fett Advogados | E15: 51 9114-0718 | F15: Instrução - Presencial | G15: 0020720-31.2024.5.04.0124 | H15: 45692 | I15: 0.4375 | J15: 4ª Vara do Trabalho | K15: Rio Grande - RS | L15: 200 | N15: CUMPRIDO | O15: Gabriela Machado | P15: 53 9139-9707 | Q15: 100 | S15: SIM | T15: CUMPRIDO | U15: =Table_3[[#This Row],[VALOR]]-Table_3[[#This Row],[ CUSTO]] -> 100
B16: 45691 | D16: Cláudia Maxxi | E16: 11 99113-8935 | F16: Una - Presencial | G16: 1000734-17.2024.5.02.0064 | H16: 45692 | I16: 0.5625 | J16: 64ª da Barra Funda | K16: São Paulo - SP | L16: 200 | N16: CUMPRIDO | O16: Arlindo Felipe Jr | P16: 11 99635-2611 | Q16: 40 | S16: SIM | T16: CUMPRIDO | U16: =Table_3[[#This Row],[VALOR]]-Table_3[[#This Row],[ CUSTO]] -> 160
B17: 45691 | D17: Jessica | E17: 41 9685-0539 | F17: Coleta de Assinaturas | G17: VASCO LUIZ TEODORO | H17: 45692 | I17: 0.66666667 | J17: R PARANA, 1540, AP 502, BRASIL | K17: Uberlândia - MG | L17: 300 | N17: CUMPRIDO | O17: Gabriela Viana | P17: 34 9135-5994 | Q17: 100 | S17: SIM | T17: CUMPRIDO | U17: =Table_3[[#This Row],[VALOR]]-Table_3[[#This Row],[ CUSTO]] -> 200
B18: 45685 | D18: Cláudia Maxxi | E18: 11 99113-8935 | F18: Instrução -Presencial | G18: 0011706-47.2023.5.15.0093 | H18: 45693 | I18: 0.4375 | J18: 6ª | K18: CAMPINAS - SP | N18: CUMPRIDO | O18: Patricia Von Ah | P18: 19 99155-8565 | S18: SIM | T18: CUMPRIDO | U18: =Table_3[[#This Row],[VALOR]]-Table_3[[#This Row],[ CUSTO]] -> 0
B19: 45685 | D19: Cláudia Maxxi | E19: 11 99113-8935 | F19: Instrução - Presencial | G19: 0012034-45.2023.5.15.0038 | H19: 45693 | I19: 0.61111111 | J19: ÚNICA | K19: BRAGANÇA PAULISTA | L19: 200 | N19: CUMPRIDO | O19: Patricia Von Ah | P19: 19 99155-8565 | Q19: 70 | S19: SIM | T19: CUMPRIDO | U19: =Table_3[[#This Row],[VALOR]]-Table_3[[#This Row],[ CUSTO]] -> 130
B20: 45685 | D20: Cláudia Maxxi | E20: 11 99113-8935 | F20: Instrução - Presencial | G20: 0012064-80.2023.5.15.0038 | H20: 45693 | I20: 0.63194444 | J20: ÚNICA | K20: BRAGANÇA PAULISTA | L20: 200 | N20: CUMPRIDO | O20: Patricia Von Ah | P20: 19 99155-8565 | Q20: 70 | S20: SIM | T20: CUMPRIDO | U20: =Table_3[[#This Row],[VALOR]]-Table_3[[#This Row],[ CUSTO]] -> 130
B21: 45687 | D21: Vivian Barbosa | E21: 11 94569-1656 | F21: Inicial | G21: 0001724-47.2024.5.10.0017 | H21: 45693 | I21: 0.37222222 | J21: 17ª | K21: Brasília - DF | L21: 250 | M21: 45726 | N21: CUMPRIDO | O21: Luana Amancio | P21: 61 8542-3080 | Q21: 120 | S21: SIM | T21: CUMPRIDO | U21: =Table_3[[#This Row],[VALOR]]-Table_3[[#This Row],[ CUSTO]] -> 130
B22: 45691 | D22: Nathalia Fett Advogados | E22: 51 9114-0718 | F22: Una - Presencial | G22: 0021007-42.2024.5.04.0205 | H22: 45693 | I22: 0.375 | J22: Posto da Justiça do Trabalho | K22: Capão da Canoa - RS | L22: 250 | N22: CUMPRIDO | O22: Juliana Grundler | P22: 51 9592-0101 | Q22: 100 | S22: SIM | T22: CUMPRIDO | U22: =Table_3[[#This Row],[VALOR]]-Table_3[[#This Row],[ CUSTO]] -> 150
B23: 45686 | D23: Eliana Ivano | E23: 11 99442-6135 | F23: Instrução - Presencial | G23: 0011043-23.2024.5.15.0139 | H23: 45694 | I23: 0.64583333 | J23: Vara do Trabalho | K23: Ubatuba - SP | L23: 250 | N23: CUMPRIDO | O23: Glaydson Roberto | P23: 12 99795-5162 | Q23: 100 | S23: SIM | T23: CUMPRIDO | U23: =Table_3[[#This Row],[VALOR]]-Table_3[[#This Row],[ CUSTO]] -> 150
B24: 45688 | D24: Nathalia Fett Advogados | E24: 51 9114-0718 | F24: Una - Presencial | G24: 0011416-93.2024.5.03.0040 | H24: 45694 | I24: 0.36458333 | J24: 2ª Vara do Trabalho | K24: Sete Lagoas - MG | L24: 200 | N24: CUMPRIDO | O24: Lucia Helena de Azevedo Ribeiro | P24: 61 8168-3829 | Q24: 70 | S24: SIM | T24: CUMPRIDO | U24: =Table_3[[#This Row],[VALOR]]-Table_3[[#This Row],[ CUSTO]] -> 130
B25: 45688 | D25: Nathalia Fett Advogados | E25: 51 9114-0718 | F25: Instrução - Presencial | G25: 0020530-06.2024.5.04.0662 | H25: 45694 | I25: 0.59375 | J25: 2ª Vara do Trabalho | K25: Passo Fundo - RS | L25: 280 | N25: CUMPRIDO | O25: Cristian Paniz | P25: 54 9917-5166 | Q25: 150 | S25: SIM | T25: CUMPRIDO | U25: =Table_3[[#This Row],[VALOR]]-Table_3[[#This Row],[ CUSTO]] -> 130
B26: 45691 | D26: Nathalia Fett Advogados | E26: 51 9114-0718 | F26: Una - Presencial | G26: 0011212-45.2024.5.03.0009 | H26: 45694 | I26: 0.38819444 | J26: 9ª Vara do Trabalho | K26: Belo Horizonte - MG | L26: 200 | N26: CUMPRIDO | O26: Diogo Ribeiro Cassini | P26: 31 8722-3837 | Q26: 70 | S26: SIM | T26: CUMPRIDO | U26: =Table_3[[#This Row],[VALOR]]-Table_3[[#This Row],[ CUSTO]] -> 130
B27: 45693 | D27: Jessica | E27: 41 9685-0539 | F27: Coleta de Assinaturas | G27: ALFREDO DE SOUZA ALBERTO | H27: 45694 | I27: 0.58333333 | J27: Boqueirão | K27: Santos - SP | L27: =300+36.8 -> 336.8 | N27: CUMPRIDO | O27: IRB - Isabelle | P27: 13 98804-4390 | Q27: =75+36.8 -> 111.8 | S27: SIM | T27: CUMPRIDO | U27: =Table_3[[#This Row],[VALOR]]-Table_3[[#This Row],[ CUSTO]] -> 225
B28: 45693 | D28: Julia Berton | E28: 11 95106-8588 | F28: Una - Presencial | H28: 45694 | I28: 0.54166667 | J28: 2ª Vara do Trabalho | K28: Mogi das Cruzes - SP | L28: 200 | N28: CUMPRIDO | O28: Tamara Ferreira | P28: 11 97638-4161 | Q28: 70 | S28: SIM | T28: CUMPRIDO | U28: =Table_3[[#This Row],[VALOR]]-Table_3[[#This Row],[ CUSTO]] -> 130
B29: 45694 | D29: LACOSTA ADVOGADOS | E29: 21 95922-4000 / 11 91039-6920 | F29: Audiência | H29: 45694 | I29: 0.65972222 | J29: 7ª da Barra Funda | K29: São Paulo - SP | L29: 150 | N29: CUMPRIDO | O29: Ana Paula Santos | P29: 11 96195-3023 | Q29: 70 | S29: SIM | T29: CUMPRIDO | U29: =Table_3[[#This Row],[VALOR]]-Table_3[[#This Row],[ CUSTO]] -> 80
B30: 45687 | D30: Vivian Barbosa | E30: 11 94569-1656 | F30: Inicial | G30: 0011217-32.2024.5.15.0139 | H30: 45695 | I30: 0.39236111 | J30: Vara do Trabalho | K30: Ubatuba - SP | L30: 250 | M30: 45726 | N30: CUMPRIDO | O30: Glaydson Roberto | P30: 12 99795-5162 | Q30: 120 | S30: SIM | T30: CUMPRIDO | U30: =Table_3[[#This Row],[VALOR]]-Table_3[[#This Row],[ CUSTO]] -> 130
B31: 45694 | D31: Thiago Coriolano | E31: 11 98775-8123 | F31: Una - Presencial | G31: 1001810-31.2024.5.02.0467 | H31: 45695 | I31: 0.47222222 | J31: 7ª | K31: São Bernardo do Campo - SP | L31: 200 | N31: CUMPRIDO | O31: Elisangela ES - SOLUÇÕES JURÍDICAS | P31: 11 93067-5163 | Q31: 90 | S31: SIM | T31: CUMPRIDO | U31: =Table_3[[#This Row],[VALOR]]-Table_3[[#This Row],[ CUSTO]] -> 110
B32: 45694 | D32: Cláudia Maxxi | E32: 11 99113-8935 | F32: Baixa CTPS | H32: 45695 | I32: 0.45833333 | J32: Vara do Trabalho | K32: Indaiatuba - SP | L32: 150 | N32: CUMPRIDO | O32: Patricia Von Ah | P32: 19 99155-8565 | Q32: 80 | S32: SIM | T32: CUMPRIDO | U32: =Table_3[[#This Row],[VALOR]]-Table_3[[#This Row],[ CUSTO]] -> 70
B33: 45695 | D33: Marina Demenciano | E33: 19 99438-7420 | F33: Una - Presencial | G33: 1001003-74.2024.5.02.0446 | H33: 45698 | I33: 0.40277778 | J33: 6ª Vara do Trabalho | K33: Santos - SP | L33: 280 | N33: CUMPRIDO | O33: IRB - Isabelle | P33: 13 98804-4390 | Q33: 130 | S33: SIM | T33: CUMPRIDO | U33: =Table_3[[#This Row],[VALOR]]-Table_3[[#This Row],[ CUSTO]] -> 150
B34: 45686 | D34: Rebeca | E34: 19 99416-4309 | F34: Una - Presencial | H34: 45699 | I34: 0.36805556 | J34: 17ª da Barra Funda | K34: São Paulo - SP | L34: 150 | N34: CUMPRIDO | O34: Joao Tomaz da Silva | P34: 11 97377-8980 | Q34: 70 | S34: SIM | T34: CUMPRIDO | U34: =Table_3[[#This Row],[VALOR]]-Table_3[[#This Row],[ CUSTO]] -> 80
B35: 45693 | D35: Vivian Barbosa | E35: 11 94569-1656 | F35: Instrução - Presencial | G35: 0012224-51.2023.5.15.0153 | H35: 45699 | I35: 0.54166667 | J35: 6ª | K35: Ribeirão Preto - SP | L35: 400 | N35: CUMPRIDO | O35: Mayara Belfort | P35: 16 99138-1367 | Q35: 130 | S35: SIM | T35: CUMPRIDO | U35: =Table_3[[#This Row],[VALOR]]-Table_3[[#This Row],[ CUSTO]] -> 270
B36: 45694 | D36: Lucas Mançano | E36: 61 9143-8757 | F36: Una - Presencial | G36: 1000017-20.2025.5.02.0371 | H36: 45699 | I36: 0.40972222 | J36: 1ª | K36: Mogi das Cruzes - SP | L36: 250 | N36: CUMPRIDO | O36: Tamara Ferreira | P36: 11 97638-4161 | Q36: 80 | S36: SIM | T36: CUMPRIDO | U36: =Table_3[[#This Row],[VALOR]]-Table_3[[#This Row],[ CUSTO]] -> 170
B37: 45695 | D37: Jessica | E37: 41 9685-0539 | F37: Coleta de Assinaturas | G37: Mayle Martins Moreira | H37: 45699 | I37: 0.625 | J37: Rua Antônio de Albuquerque, n°330, Sala 901, Ed. Comercial Canopus Corporate, Savassi | K37: Belo Horizonte - MG | L37: =300+12.3 -> 312.3 | N37: CUMPRIDO | O37: Diogo Ribeiro Cassini | P37: 31 8722-3837 | Q37: =120+12.3 -> 132.3 | S37: SIM | T37: CUMPRIDO | U37: =Table_3[[#This Row],[VALOR]]-Table_3[[#This Row],[ CUSTO]] -> 180
B38: 45699 | D38: Jessica | E38: 41 9685-0539 | F38: Coleta de Assinaturas | G38: RONEL MARIANO | H38: 45699 | I38: 0.6875 | J38: Rua Doutor Euridice José Bento, nº 115, Bairro Jardim do Lago | K38: CAMPINAS - SP | L38: =300+36.8 -> 336.8 | N38: CUMPRIDO | O38: Camila Rodrigues | P38: 19 98405-2277 | Q38: =100+36.8 -> 136.8 | S38: SIM | T38: CUMPRIDO | U38: =Table_3[[#This Row],[VALOR]]-Table_3[[#This Row],[ CUSTO]] -> 200
B39: 45699 | D39: Cláudia Maxxi | E39: 11 99113-8935 | F39: Una - Presencial | G39: 1001836-39.2024.5.02.0011 | H39: 45699 | I39: 0.40625 | J39: 11ª | K39: São Paulo - SP | L39: 150 | N39: CUMPRIDO | O39: Ingrid Bellem | P39: 11 97375-7309 | Q39: 50 | S39: SIM | T39: CUMPRIDO | U39: =Table_3[[#This Row],[VALOR]]-Table_3[[#This Row],[ CUSTO]] -> 100
B40: 45699 | D40: Sofia - Benjamim Advogados | E40: 22 99978-0715 | F40: Despacho | G40: 1008513-60.2025.8.26.0002 | H40: 45699 | J40: 6ª Vara Cível de Santo Amaro | K40: São Paulo - SP | L40: 180 | N40: CUMPRIDO | O40: Sandra Natale | P40: 11 91313-7104 | Q40: 70 | S40: SIM | T40: CUMPRIDO | U40: =Table_3[[#This Row],[VALOR]]-Table_3[[#This Row],[ CUSTO]] -> 110
B41: 45694 | D41: LACOSTA ADVOGADOS | E41: 21 95922-4000 / 11 91039-6920 | F41: Audiência | H41: 45700 | I41: 0.39583333 | J41: 27ª da Barra Funda | K41: São Paulo - SP | L41: 250 | N41: CUMPRIDO | O41: Ingrid Bellem | P41: 11 97375-7309 | Q41: 120 | S41: SIM | T41: CUMPRIDO | U41: =Table_3[[#This Row],[VALOR]]-Table_3[[#This Row],[ CUSTO]] -> 130
B42: 45697 | D42: Eliana Ivano | E42: 11 99442-6135 | F42: Instrução - Presencial | H42: 45700 | I42: 0.60416667 | J42: Vara do Trabalho | K42: Mogi Mirim - SP | L42: 250 | N42: CUMPRIDO | O42: Daiane Ferreira Gomes | P42: 19 98172-7578 | Q42: 150 | S42: SIM | T42: CUMPRIDO | U42: =Table_3[[#This Row],[VALOR]]-Table_3[[#This Row],[ CUSTO]] -> 100
B43: 45699 | D43: Jessica | E43: 41 9685-0539 | F43: Coleta de Assinaturas | G43: Marlon Mariano | H43: 45700 | I43: 0.45833333 | J43: Rua Alcides Tenório de Brito Guerra, 117, São Mateus | K43: Presidente Prudente - SP | L43: 380 | N43: CUMPRIDO | O43: Cibely Esquina | P43: 18 98136-1028 | Q43: 100 | S43: SIM | T43: CUMPRIDO | U43: =Table_3[[#This Row],[VALOR]]-Table_3[[#This Row],[ CUSTO]] -> 280
B44: 45685 | D44: Cláudia Maxxi | E44: 11 99113-8935 | F44: Instrução - Presencial | G44: 0011659-58.2023.5.15.0001 | H44: 45701 | I44: 0.45833333 | J44: 1ª | K44: CAMPINAS - SP | L44: 200 | N44: CUMPRIDO | O44: Patricia Von Ah | P44: 19 99155-8565 | Q44: 50 | S44: SIM | T44: CUMPRIDO | U44: =Table_3[[#This Row],[VALOR]]-Table_3[[#This Row],[ CUSTO]] -> 150
B45: 45693 | D45: Nathalia Fett Advogados | E45: 51 9114-0718 | F45: Instrução - Presencial | G45: 0020801-52.2023.5.04.0661 | H45: 45701 | I45: 0.375 | J45: Posto da Justiça do Trabalho | K45: Marau - RS | L45: 250 | N45: CUMPRIDO | O45: Jéssica Betinéli da Silva | P45: 54 9668-1805 | Q45: 200 | S45: SIM | T45: CUMPRIDO | U45: =Table_3[[#This Row],[VALOR]]-Table_3[[#This Row],[ CUSTO]] -> 50
B46: 45693 | D46: Nathalia Fett Advogados | E46: 51 9114-0718 | F46: Instrução - Presencial | G46: 0011725-75.2023.5.03.0032 | H46: 45701 | I46: 0.4375 | J46: 4ª Vara do Trabalho | K46: Contagem - MG | L46: 200 | N46: CUMPRIDO | O46: Luiz Felipe | P46: 31 7306-6348 | Q46: 120 | S46: SIM | T46: CUMPRIDO | U46: =Table_3[[#This Row],[VALOR]]-Table_3[[#This Row],[ CUSTO]] -> 80
B47: 45694 | D47: LACOSTA ADVOGADOS | E47: 21 95922-4000 / 11 91039-6920 | F47: Audiência | H47: 45701 | I47: 0.59027778 | J47: 4ª | K47: OSASCO - SP | L47: 150 | N47: CUMPRIDO | O47: Flaviane Batista | P47: 11 95370-1207 | Q47: 70 | S47: SIM | T47: CUMPRIDO | U47: =Table_3[[#This Row],[VALOR]]-Table_3[[#This Row],[ CUSTO]] -> 80
B48: 45694 | D48: Lucas Mançano | E48: 61 9143-8757 | F48: Una - Presencial | G48: 1002133-30.2024.5.02.0372 | H48: 45701 | I48: 0.40277778 | J48: 2ª | K48: Mogi das Cruzes - SP | L48: 400 | N48: CUMPRIDO | O48: Tamara Ferreira | P48: 11 97638-4161 | Q48: 130 | S48: SIM | T48: CUMPRIDO | U48: =Table_3[[#This Row],[VALOR]]-Table_3[[#This Row],[ CUSTO]] -> 270
B49: 45694 | D49: Cláudia Maxxi | E49: 11 99113-8935 | F49: Inicial - presencial | G49: 0012351-94.2024.5.15.0042 | H49: 45701 | I49: 0.56944444 | J49: 2ª | K49: Ribeirão Preto - SP | L49: 200 | N49: CUMPRIDO | O49: Mayara Belfort | P49: 16 99138-1367 | Q49: 80 | S49: SIM | T49: CUMPRIDO | U49: =Table_3[[#This Row],[VALOR]]-Table_3[[#This Row],[ CUSTO]] -> 120
B50: 45699 | D50: JH Gomes Advocacia | E50: 11 98492-3401 | F50: Instrução - Presencial | H50: 45701 | I50: 0.42708333 | J50: 3ª Vara do Trabalho da Zona Leste | K50: São Paulo - SP | L50: 150 | N50: CUMPRIDO | O50: Ronnie de Miranda Barroso | P50: 11 97976-3497 | Q50: 70 | S50: SIM | T50: CUMPRIDO | U50: =Table_3[[#This Row],[VALOR]]-Table_3[[#This Row],[ CUSTO]] -> 80
B51: 45700 | D51: Jessica | E51: 41 9685-0539 | F51: Coleta de Assinaturas | G51: MAYLE MARTINS MOREIRA VIVAS | H51: 45701 | I51: 0.625 | J51: Rua Antônio de Albuquerque N° 330 - 8° Andar. (MG/BH) | K51: Belo Horizonte - MG | L51: 300 | M51: ok | N51: CUMPRIDO | O51: Diogo Ribeiro Cassini | P51: 31 8722-3837 | Q51: 100 | S51: SIM | T51: CUMPRIDO | U51: =Table_3[[#This Row],[VALOR]]-Table_3[[#This Row],[ CUSTO]] -> 200
B52: 45700 | D52: LACOSTA ADVOGADOS | E52: 21 95922-4000 / 11 91039-6920 | F52: Audiência | H52: 45701 | I52: 0.63888889 | J52: 80ª da Barra Funda | K52: São Paulo - SP | L52: 150 | N52: CUMPRIDO | O52: Naiara Santos Nascimento | P52: 11 97123-1691 | Q52: 70 | S52: SIM | T52: CUMPRIDO | U52: =Table_3[[#This Row],[VALOR]]-Table_3[[#This Row],[ CUSTO]] -> 80
B53: 45700 | D53: Thulyo Augustto | E53: 62 9683-9870 | F53: Instrução - Presencial | G53: 0000852-53.2024.5.10.0010 | H53: 45701 | I53: 0.39583333 | J53: 10ª | K53: Brasília - DF | L53: 250 | N53: CUMPRIDO | O53: Luana Amancio | P53: 61 8542-3080 | Q53: 100 | S53: SIM | T53: CUMPRIDO | U53: =Table_3[[#This Row],[VALOR]]-Table_3[[#This Row],[ CUSTO]] -> 150
B54: 45701 | D54: Jessica | E54: 41 9685-0539 | F54: Coleta de Assinaturas | G54: NATAN BATISTA DUTRA | H54: 45701 | I54: 0.58333333 | J54: Rua: Campo Grande 909 loja D | K54: Rio de Janeiro- RJ | L54: =300+36.8 -> 336.8 | M54: ok | N54: CUMPRIDO | O54: Marta Cristina | P54: 21 97266-2211 | Q54: =100+36.8 -> 136.8 | S54: SIM | T54: CUMPRIDO | U54: =Table_3[[#This Row],[VALOR]]-Table_3[[#This Row],[ CUSTO]] -> 200
B55: 45701 | D55: Jessica | E55: 41 9685-0539 | F55: Coleta de Assinaturas | G55: NELSON INACIO MANUEL | H55: 45702 | I55: 0.4375 | J55: Filial da Barra Funda | K55: São Paulo - SP | L55: 300 | M55: ok | N55: CUMPRIDO | O55: Arlindo Felipe Jr | P55: 11 99635-2611 | Q55: 50 | S55: SIM | T55: CUMPRIDO | U55: =Table_3[[#This Row],[VALOR]]-Table_3[[#This Row],[ CUSTO]] -> 250
B56: 45701 | D56: LACOSTA ADVOGADOS | E56: 21 95922-4000 / 11 91039-6920 | F56: Audiência | H56: 45702 | I56: 0.48958333 | J56: 5ª Vara do Trabalho da Zona Leste | K56: São Paulo - SP | L56: 150 | N56: CUMPRIDO | O56: Laura Mautone | P56: 11 99305-2938 | Q56: 70 | R56: des | S56: SIM | T56: CUMPRIDO | U56: =Table_3[[#This Row],[VALOR]]-Table_3[[#This Row],[ CUSTO]] -> 80
B57: 45701 | D57: Jamile Barakat | E57: 11 99503-8130 | F57: Protocolo | H57: 45702 | I57: 0.54166667 | J57: 38ª da Barra Funda | K57: São Paulo - SP | L57: 80 | N57: CUMPRIDO | O57: Arlindo Felipe Jr | P57: 11 99635-2611 | Q57: 50 | S57: SIM | T57: CUMPRIDO | U57: =Table_3[[#This Row],[VALOR]]-Table_3[[#This Row],[ CUSTO]] -> 30
B58: 45701 | D58: Jamile Barakat | E58: 11 99503-8130 | F58: Despacho | H58: 45702 | J58: 7ª Vara Cível da Nossa Senhora do Ó | K58: São Paulo - SP | L58: 120 | N58: CUMPRIDO | O58: Arlindo Felipe Jr | P58: 11 99635-2611 | Q58: 50 | S58: SIM | T58: CUMPRIDO | U58: =Table_3[[#This Row],[VALOR]]-Table_3[[#This Row],[ CUSTO]] -> 70
B59: 45701 | D59: Jamile Barakat | E59: 11 99503-8130 | F59: Despacho | H59: 45702 | J59: 4ª Vara Cível | K59: OSASCO - SP | L59: 150 | N59: CUMPRIDO | O59: Arlindo Felipe Jr | P59: 11 99635-2611 | Q59: 50 | S59: SIM | T59: CUMPRIDO | U59: =Table_3[[#This Row],[VALOR]]-Table_3[[#This Row],[ CUSTO]] -> 100
B60: 45700 | D60: Cláudia Maxxi | E60: 11 99113-8935 | F60: Instrução - Presencial | G60: 1001042-83.2023.5.02.0421 | H60: 45705 | I60: 0.68055556 | J60: 1ª | K60: Santana de Parnaíba - SP | L60: 200 | N60: CUMPRIDO | O60: Elisangela ES - SOLUÇÕES JURÍDICAS | P60: 11 93067-5163 | Q60: 100 | S60: SIM | T60: CUMPRIDO | U60: =Table_3[[#This Row],[VALOR]]-Table_3[[#This Row],[ CUSTO]] -> 100
B61: 45701 | D61: LACOSTA ADVOGADOS | E61: 21 95922-4000 / 11 91039-6920 | F61: Audiência | H61: 45705 | I61: 0.65277778 | J61: 2ª VT da Zona Sul | K61: São Paulo - SP | L61: 150 | N61: CUMPRIDO | O61: Joao Tomaz da Silva | P61: 11 97377-8980 | Q61: 70 | S61: SIM | T61: CUMPRIDO | U61: =Table_3[[#This Row],[VALOR]]-Table_3[[#This Row],[ CUSTO]] -> 80
B62: 45702 | D62: Vivian Barbosa / Raquel Moreira | E62: 11 94569-1656 / 11 98450-5051 | F62: Inicial - presencial | G62: 0000046-91.2025.5.06.0172 | H62: 45705 | I62: 0.36111111 | J62: 2ª | K62: Cabo de Santo Agostinho - PE | L62: 500 | N62: CUMPRIDO | O62: Érica Caroline Gonzaga da Silva | P62: 81 9753-6773 | Q62: 130 | R62: adiantado | S62: SIM | T62: CUMPRIDO | U62: =Table_3[[#This Row],[VALOR]]-Table_3[[#This Row],[ CUSTO]] -> 370
B63: 45702 | D63: Rafaelly Rocha | E63: 21 98120-7772 | F63: Audiência | G63: 1002262-45.2024.5.02.0401 | H63: 45705 | I63: 0.56944444 | J63: 1ª | K63: Praia Grande - SP | L63: 120 | N63: CUMPRIDO | O63: IRB - Isabelle | P63: 13 98804-4390 | Q63: 50 | S63: SIM | T63: CUMPRIDO | U63: =Table_3[[#This Row],[VALOR]]-Table_3[[#This Row],[ CUSTO]] -> 70
B64: 45692 | D64: Jessica | E64: 41 9685-0539 | F64: Coleta de Assinaturas | G64: JOSE CARLOS SABIA | H64: 45707 | I64: 0.54166667 | J64: Rua México, n° 31/ RJ | K64: Rio de Janeiro - RJ | L64: =300 -> 300 | M64: ok | N64: CUMPRIDO | O64: Marta Cristina | P64: 21 97266-2211 | Q64: =80+8.5 -> 88.5 | S64: SIM | T64: CUMPRIDO | U64: =Table_3[[#This Row],[VALOR]]-Table_3[[#This Row],[ CUSTO]] -> 211.5
B65: 45701 | D65: Marina Demenciano | E65: 19 99438-7420 | F65: Una - Presencial | H65: 45707 | I65: 0.40277778 | J65: 83ª da Barra Funda | K65: São Paulo - SP | L65: 200 | N65: CUMPRIDO | O65: Joao Tomaz da Silva | P65: 11 97377-8980 | Q65: 70 | S65: SIM | T65: CUMPRIDO | U65: =Table_3[[#This Row],[VALOR]]-Table_3[[#This Row],[ CUSTO]] -> 130
B66: 45701 | D66: LACOSTA ADVOGADOS | E66: 21 95922-4000 / 11 91039-6920 | F66: Audiência | H66: 45707 | I66: 0.5625 | J66: 2ª | K66: Guarulhos - SP | L66: 150 | N66: CUMPRIDO | O66: Joao Tomaz da Silva | P66: 11 97377-8980 | Q66: 80 | S66: SIM | T66: CUMPRIDO | U66: =Table_3[[#This Row],[VALOR]]-Table_3[[#This Row],[ CUSTO]] -> 70
B67: 45685 | D67: LACOSTA ADVOGADOS | E67: 21 95922-4000 / 11 91039-6920 | F67: Audiência | H67: 45708 | I67: 0.38888889 | J67: 9ª Vara do Trabalho da Zona Leste | K67: São Paulo - SP | L67: 150 | N67: CUMPRIDO | O67: Joao Tomaz da Silva | P67: 11 97377-8980 | Q67: 70 | S67: SIM | T67: CUMPRIDO | U67: =Table_3[[#This Row],[VALOR]]-Table_3[[#This Row],[ CUSTO]] -> 80
B68: 45700 | D68: Josiane | E68: 45 9979-5193 | F68: Conciliação - Presencial | G68: 0800186-11.2025.8.19.0001 | H68: 45708 | I68: 0.52083333 | J68: 21ª Vara do Juizado Especial Cível | K68: Rio de Janeiro - RJ | L68: 120 | N68: CUMPRIDO | O68: Domenique Guimarães Frascino | P68: 21 99494-6801 | Q68: 50 | S68: SIM | T68: CUMPRIDO | U68: =Table_3[[#This Row],[VALOR]]-Table_3[[#This Row],[ CUSTO]] -> 70
B69: 45700 | D69: Vinícius Silvério | E69: 41 9178-7396 | F69: Instrução - Presencial | G69: 0020887-16.2021.5.04.0007 | H69: 45708 | I69: 0.41666667 | J69: 7ª Vara do Trabalho | K69: Porto Alegre - RS | L69: 400 | N69: CUMPRIDO | O69: Ernani Korbes | P69: 51 9986-1515 | Q69: 120 | S69: SIM | T69: CUMPRIDO | U69: =Table_3[[#This Row],[VALOR]]-Table_3[[#This Row],[ CUSTO]] -> 280
B70: 45705 | D70: Jessica | E70: 41 9685-0539 | F70: Coleta de Assinaturas | G70: Clovis Ascenção Pena | H70: 45708 | I70: 0.375 | J70: Rua Antônio de Albuquerque, n°330, Sala 901, Ed. Comercial Canopus Corporate, Savassi | K70: Belo Horizonte - MG | L70: =300+51.4 -> 351.4 | M70: ok | N70: CUMPRIDO | O70: Camila Simao | P70: 31 9474-0937 | Q70: =100+51.4 -> 151.4 | S70: SIM | T70: CUMPRIDO | U70: =Table_3[[#This Row],[VALOR]]-Table_3[[#This Row],[ CUSTO]] -> 200
B71: 45707 | D71: Rodrigo Bezerra | E71: 11 99360-4364 | F71: Acompanhamento | H71: 45708 | I71: 0.58333333 | J71: 7º DP | K71: São Paulo - SP | L71: 200 | N71: CUMPRIDO | O71: Caroline Lima | P71: 11 93144-5204 | Q71: 50 | S71: SIM | T71: CUMPRIDO | U71: =Table_3[[#This Row],[VALOR]]-Table_3[[#This Row],[ CUSTO]] -> 150
B72: 45708 | D72: Jessica | E72: 41 9685-0539 | F72: Coleta de Assinaturas | G72: ADIRSON HERMENEGILDO PAIVA | H72: 45708 | I72: 0.45833333 | J72: Rua Joaquim Anacleto Da Conceição, 310 Conjunto Teixeira Dias - Bairro Barreiro | K72: Belo Horizonte - MG | L72: 300 | M72: ok | N72: CUMPRIDO | O72: Camila Simao | P72: 31 9474-0937 | Q72: 49.02 | S72: SIM | T72: CUMPRIDO | U72: =Table_3[[#This Row],[VALOR]]-Table_3[[#This Row],[ CUSTO]] -> 250.98
B73: 45685 | D73: LACOSTA ADVOGADOS | E73: 21 95922-4000 / 11 91039-6920 | F73: Audiência | H73: 45709 | I73: 0.61111111 | J73: 64ª da Barra Funda | K73: São Paulo - SP | L73: 150 | N73: CUMPRIDO | O73: Joao Tomaz da Silva | P73: 11 97377-8980 | Q73: 70 | S73: SIM | T73: CUMPRIDO | U73: =Table_3[[#This Row],[VALOR]]-Table_3[[#This Row],[ CUSTO]] -> 80
B74: 45707 | D74: Sepulveda | E74: 19 99651-8840 | F74: Perícia | G74: 1002058-33.2024.5.02.0067 | H74: 45709 | I74: 0.35416667 | J74: Local: Rua Coronel Mursa, 56 – Brás | K74: São Paulo - SP | L74: 150 | N74: CUMPRIDO | O74: Arlindo Felipe Jr | P74: 11 99635-2611 | Q74: 50 | S74: SIM | T74: CUMPRIDO | U74: =Table_3[[#This Row],[VALOR]]-Table_3[[#This Row],[ CUSTO]] -> 100
B75: 45709 | D75: Jessica | E75: 41 9685-0539 | F75: Coleta de Assinaturas | G75: MAYLE MARTINS MOREIRA VIVAS | H75: 45709 | I75: 0.625 | J75: Rua Antônio de Albuquerque N° 330 - 9° Andar. (MG/BH) | K75: Belo Horizonte - MG | L75: =300+51.4 -> 351.4 | M75: ok | N75: CUMPRIDO | O75: Camila Simao | P75: 31 9474-0937 | Q75: =100+51.4 -> 151.4 | S75: SIM | T75: CUMPRIDO | U75: =Table_3[[#This Row],[VALOR]]-Table_3[[#This Row],[ CUSTO]] -> 200
B76: 45709 | D76: Thiago Coriolano | E76: 11 98775-8123 | F76: Una - Presencial | G76: 1002073-04.2024.5.02.0713 | H76: 45709 | I76: 0.54166667 | J76: 13ª da Zona Sul | K76: São Paulo - SP | L76: 250 | N76: CUMPRIDO | O76: Fernando Jorge | P76: 11 97233-6431 | Q76: 70 | S76: SIM | T76: CUMPRIDO | U76: =Table_3[[#This Row],[VALOR]]-Table_3[[#This Row],[ CUSTO]] -> 180
B77: 45685 | D77: LACOSTA ADVOGADOS | E77: 21 95922-4000 / 11 91039-6920 | F77: Audiência | H77: 45712 | I77: 0.58680556 | J77: 2ª Vara do Trabalho da Zona Leste | K77: São Paulo - SP | L77: 150 | N77: CUMPRIDO | O77: Joao Tomaz da Silva | P77: 11 97377-8980 | Q77: 70 | S77: SIM | T77: CUMPRIDO | U77: =Table_3[[#This Row],[VALOR]]-Table_3[[#This Row],[ CUSTO]] -> 80
B78: 45706 | D78: Jessica | E78: 41 9685-0539 | F78: Coleta de Assinaturas | G78: MARCOS ANTONIO SIMIONATO | H78: 45712 | I78: 0.41666667 | J78: Travessa Juno Gil de Lima, 342 - Bairro REsidencial Cambarás | K78: Ipeúna - SP | L78: =380+65.95 -> 445.95 | M78: ok | N78: CUMPRIDO | O78: Kely Stefany | P78: 19 99620-8379 | Q78: =120+65.95 -> 185.95 | S78: SIM | T78: CUMPRIDO | U78: =Table_3[[#This Row],[VALOR]]-Table_3[[#This Row],[ CUSTO]] -> 260
B79: 45709 | D79: Sepulveda | E79: 19 99651-8840 | F79: Perícia | H79: 45712 | I79: 0.33333333 | J79: Ajinomoto do Brasil | K79: Laranjal Paulista - SP | L79: 150 | N79: CUMPRIDO | O79: Gabriela Gomes | P79: 11 97747-2559 | Q79: 100 | S79: SIM | T79: CUMPRIDO | U79: =Table_3[[#This Row],[VALOR]]-Table_3[[#This Row],[ CUSTO]] -> 50
B80: 45685 | D80: LACOSTA ADVOGADOS | E80: 21 95922-4000 / 11 91039-6920 | F80: Audiência | H80: 45713 | I80: 0.41666667 | J80: 4ª da Zona Sul | K80: São Paulo - SP | L80: 300 | N80: CUMPRIDO | O80: Joao Tomaz da Silva | P80: 11 97377-8980 | Q80: 70 | S80: SIM | T80: CUMPRIDO | U80: =Table_3[[#This Row],[VALOR]]-Table_3[[#This Row],[ CUSTO]] -> 230
B81: 45702 | D81: Josiane | E81: 45 9979-5193 | F81: Conciliação - Presencial | H81: 45713 | I81: 0.41666667 | J81: Rua Ministro Raphael de Barros Monteiro, 110, 1º andar – CEJUSC, Jd. dos Camargos | K81: Barueri - SP | L81: 120 | N81: CUMPRIDO | O81: Caroline Gargoriano | P81: 11 98998-8542 | Q81: 70 | R81: des | S81: SIM | T81: CUMPRIDO | U81: =Table_3[[#This Row],[VALOR]]-Table_3[[#This Row],[ CUSTO]] -> 50
B82: 45707 | D82: Vivian Barbosa / Raquel Moreira | E82: 11 94569-1656 / 11 98450-5051 | F82: Instrução - Presencial | G82: 0011035-55.2024.5.15.0039 | H82: 45713 | I82: 0.48611111 | J82: Vara do Trabalho | K82: Capivari - SP | L82: 250 | N82: CUMPRIDO | O82: Marcia Araujo Batagim | P82: 41 9204-0259 | Q82: 100 | S82: SIM | T82: CUMPRIDO | U82: =Table_3[[#This Row],[VALOR]]-Table_3[[#This Row],[ CUSTO]] -> 150
B83: 45709 | D83: Sepulveda | E83: 19 99651-8840 | F83: Una - Presencial | H83: 45713 | I83: 0.54513889 | J83: 2ª da Zona Sul | K83: São Paulo - SP | L83: 150 | N83: CUMPRIDO | O83: Angélica Berenice Ramos dos Santos | P83: 11 99212-4259 | Q83: 70 | R83: 45731 | S83: SIM | T83: CUMPRIDO | U83: =Table_3[[#This Row],[VALOR]]-Table_3[[#This Row],[ CUSTO]] -> 80
B84: 45713 | D84: Jessica | E84: 41 9685-0539 | F84: Coleta de Assinaturas | G84: NELSINO ALMEIDA E SILVA | H84: 45713 | I84: 0.70833333 | J84: RUA DAS ANDORINHAS, 17, ALVARENGA | K84: São Bernardo do Campo - SP | L84: =350+16+36.8 -> 402.8 | M84: ok | N84: CUMPRIDO | O84: Patricia Selerges de Araújo | P84: 11 97030-7676 | Q84: =90+16+36.8 -> 142.8 | S84: SIM | T84: CUMPRIDO | U84: =Table_3[[#This Row],[VALOR]]-Table_3[[#This Row],[ CUSTO]] -> 260
B85: 45708 | D85: Eliana Ivano | E85: 11 99442-6135 | F85: Instrução - Presencial | H85: 45714 | I85: 0.66666667 | J85: Vara do Trabalho | K85: Itapeva - SP | L85: 250 | N85: CUMPRIDO | O85: Amanda Cristina Barbosa | P85: 15 98163-3812 | Q85: 220 | S85: SIM | T85: CUMPRIDO | U85: =Table_3[[#This Row],[VALOR]]-Table_3[[#This Row],[ CUSTO]] -> 30
B86: 45712 | D86: Diego Carrara Palandrani | E86: 44 9815-1208 | F86: Una - Presencial | G86: 1002053-81.2024.5.02.0076 | H86: 45714 | I86: 0.41666667 | J86: 76ª da Barra Funda | K86: São Paulo - SP | L86: 170 | N86: CUMPRIDO | O86: João Paulo Marques Santana | P86: 11 91517-5973 | Q86: 70 | S86: SIM | T86: CUMPRIDO | U86: =Table_3[[#This Row],[VALOR]]-Table_3[[#This Row],[ CUSTO]] -> 100
B87: 45712 | D87: Jessica | E87: 41 9685-0539 | F87: Coleta de Assinaturas | G87: LUIZ ALBERTO LESSA | H87: 45714 | I87: 0.375 | J87: Av. Nossa Senhora da Penha, N° 2796, Santa Luiza | K87: Vitória- ES | L87: 150 | M87: ok | N87: CUMPRIDO | O87: Jhonatan Schabo Carreira | P87: 27 98884-8778 | Q87: 90 | S87: SIM | T87: CUMPRIDO | U87: =Table_3[[#This Row],[VALOR]]-Table_3[[#This Row],[ CUSTO]] -> 60
B88: 45713 | D88: Sepulveda | E88: 19 99651-8840 | F88: Perícia | H88: 45714 | I88: 0.66666667 | J88: AVENIDA EMILIO CHECCHINATO , 1800, SAO ROQUE DA CHAVE | K88: Itupeva - SP | L88: 150 | N88: CUMPRIDO | O88: Karim Fernanda Ribeiro de Oliveira | P88: 11 97033-8981 | Q88: 100 | S88: SIM | T88: CUMPRIDO | U88: =Table_3[[#This Row],[VALOR]]-Table_3[[#This Row],[ CUSTO]] -> 50
B89: 45713 | D89: Estela Martins | E89: 19 99205-7804 | F89: Audiência | G89: 0000157-04.2025.5.09.0007 | H89: 45714 | I89: 0.39583333 | J89: 7ª | K89: Curitiba - PR | L89: 150 | N89: CUMPRIDO | O89: Jorjane Rahal | P89: 41 9875-3181 | Q89: 100 | S89: SIM | T89: CUMPRIDO | U89: =Table_3[[#This Row],[VALOR]]-Table_3[[#This Row],[ CUSTO]] -> 50
B90: 45713 | D90: Sepulveda | E90: 19 99651-8840 | F90: Instrução - Presencial | H90: 45714 | I90: 0.63888889 | J90: 2ª Vara do Trabalho | K90: Mauá - SP | L90: 150 | N90: CUMPRIDO | O90: Ronnie de Miranda Barroso | P90: 11 97976-3497 | Q90: 100 | S90: SIM | T90: CUMPRIDO | U90: =Table_3[[#This Row],[VALOR]]-Table_3[[#This Row],[ CUSTO]] -> 50
B91: 45713 | D91: Ramiris Kefler | E91: 27 99581-5484 | F91: Conciliação - Presencial | G91: 1011165-18.2024.8.26.0606 | H91: 45714 | I91: 0.58333333 | J91: Juizado Especial Cível | K91: Suzano - SP | L91: 150 | N91: CUMPRIDO | O91: Fernando Santos | P91: 11 98307-2224 | Q91: 70 | S91: SIM | T91: CUMPRIDO | U91: =Table_3[[#This Row],[VALOR]]-Table_3[[#This Row],[ CUSTO]] -> 80
B92: 45685 | D92: LACOSTA ADVOGADOS | E92: 21 95922-4000 / 11 91039-6920 | F92: Audiência | H92: 45715 | I92: 0.52083333 | J92: 40ª da Barra Funda | K92: São Paulo - SP | L92: 150 | N92: CUMPRIDO | O92: Joao Tomaz da Silva | P92: 11 97377-8980 | Q92: 70 | S92: SIM | T92: CUMPRIDO | U92: =Table_3[[#This Row],[VALOR]]-Table_3[[#This Row],[ CUSTO]] -> 80
B93: 45694 | D93: Patricia Detlinger | E93: 11 99707-7808 | F93: Conciliação - Presencial | H93: 45715 | I93: 0.64583333 | J93: CEJUSC | K93: Praia Grande - SP | L93: 200 | N93: CUMPRIDO | O93: Carla Melo | P93: 13 99763-3941 | Q93: 50 | R93: des | S93: SIM | T93: CUMPRIDO | U93: =Table_3[[#This Row],[VALOR]]-Table_3[[#This Row],[ CUSTO]] -> 150
B94: 45706 | D94: Josiane | E94: 45 9979-5193 | F94: Conciliação - Presencial | G94: 1015425-18.2024.8.26.0161 | H94: 45715 | I94: 0.625 | J94: CEJUSC local (Prédio das Varas Cíveis, Avenida Sete de Setembro, 409/413 | K94: Diadema - SP | L94: 120 | N94: CUMPRIDO | O94: Clécia Sousa Costa | P94: 11 99344-0783 | Q94: 50 | S94: SIM | T94: CUMPRIDO | U94: =Table_3[[#This Row],[VALOR]]-Table_3[[#This Row],[ CUSTO]] -> 70
B95: 45712 | D95: Leonardo Velloso Advocacia | E95: 31 9668-8383 | F95: Conciliação - Presencial | H95: 45715 | I95: 0.64583333 | J95: Cejusc Nossa Senhora do Ó | K95: São Paulo - SP | L95: 150 | N95: CUMPRIDO | O95: Giovana Ferreira | P95: 11 98467-6866 | Q95: 70 | S95: SIM | T95: CUMPRIDO | U95: =Table_3[[#This Row],[VALOR]]-Table_3[[#This Row],[ CUSTO]] -> 80
B96: 45713 | D96: Jessica | E96: 41 9685-0539 | F96: Coleta de Assinaturas | G96: MAGNO SERGIO DOS SANTOS RODRIGUES | H96: 45715 | I96: 0.58333333 | J96: Av. Nossa Senhora da Penha, N° 2796, Santa Luiza | K96: Vitória- ES | L96: 300 | M96: ok | N96: CUMPRIDO | O96: Jhonatan Schabo Carreira | P96: 27 98884-8778 | Q96: 90 | S96: SIM | T96: CUMPRIDO | U96: =Table_3[[#This Row],[VALOR]]-Table_3[[#This Row],[ CUSTO]] -> 210
B97: 45706 | D97: Gabriela Gamboa Serrano | E97: 11 99495-1075 | F97: Protocolo | H97: 45716 | J97: Delegacia | K97: Suzano - SP | L97: 60 | N97: CUMPRIDO | O97: Diligência Própria | S97: SIM | T97: CUMPRIDO | U97: =Table_3[[#This Row],[VALOR]]-Table_3[[#This Row],[ CUSTO]] -> 60
B98: 45715 | D98: Thiago Coriolano | E98: 11 98775-8123 | F98: Audiência | G98: 1000001-68.2025.5.02.0435 | H98: 45716 | I98: 0.41666667 | J98: 5ª Vara do Trabalho | K98: Santo André - SP | L98: 200 | N98: CUMPRIDO | O98: Joao Tomaz da Silva | P98: 11 97377-8980 | Q98: 70 | S98: SIM | T98: CUMPRIDO | U98: =Table_3[[#This Row],[VALOR]]-Table_3[[#This Row],[ CUSTO]] -> 130
B99: 45716 | D99: Thiago Coriolano | E99: 11 98775-8123 | F99: Acompanhamento | G99: 1001810-31.2024.5.02.0467 | H99: 45716 | I99: 0.39583333 | K99: São Bernardo do Campo - SP | L99: 300 | N99: CUMPRIDO | O99: Marcelo Bispo | P99: 31 9945-7190 | Q99: 100 | S99: SIM | T99: CUMPRIDO | U99: =Table_3[[#This Row],[VALOR]]-Table_3[[#This Row],[ CUSTO]] -> 200
U100: =Table_3[[#This Row],[VALOR]]-Table_3[[#This Row],[ CUSTO]] -> 0
U101: =Table_3[[#This Row],[VALOR]]-Table_3[[#This Row],[ CUSTO]] -> 0
U102: =Table_3[[#This Row],[VALOR]]-Table_3[[#This Row],[ CUSTO]] -> 0
...

Sheet MARÇO
B2: CONTROLE DE DILIGÊNCIAS
B4: SOLICITAÇÃO | C4: Nº. DOC9 | D4: SOLICITANTE | E4: TEL. | F4: TIPO DE DILIGÊNCIA | G4: Processo | H4: DATA | I4: HORA | J4: LOCAL | K4: Cidade - UF | L4: VALOR | M4: DATA PAG | N4: PAGAM. | O4: CONTRATADO | P4: TEL. 2 | Q4: CUSTO | R4: PRAZO | S4: PAGO | T4: STATUS | U4: LUCRO
B5: 45685 | D5: LACOSTA ADVOGADOS | E5: 21 95922-4000 / 11 91039-6920 | F5: Audiência | H5: 45722 | I5: 0.39583333 | J5: 90ª da Barra Funda | K5: São Paulo - SP | L5: 150 | N5: CUMPRIDO | O5: Joao Tomaz da Silva | P5: 11 97377-8980 | Q5: 70 | S5: SIM | T5: CUMPRIDO | U5: =Table_4[[#This Row],[VALOR]]-Table_4[[#This Row],[ CUSTO]] -> 80
B6: 45712 | D6: LACOSTA ADVOGADOS | E6: 21 95922-4000 / 11 91039-6920 | F6: Audiência | H6: 45722 | I6: 0.58333333 | J6: 29ª da Barra Funda | K6: São Paulo - SP | L6: 150 | N6: CUMPRIDO | O6: Joao Tomaz da Silva | P6: 11 97377-8980 | Q6: 70 | S6: SIM | T6: CUMPRIDO | U6: =Table_4[[#This Row],[VALOR]]-Table_4[[#This Row],[ CUSTO]] -> 80
B7: 45712 | D7: LACOSTA ADVOGADOS | E7: 21 95922-4000 / 11 91039-6920 | F7: Audiência | H7: 45734 | I7: 0.55208333 | J7: 64ª da Barra Funda | K7: São Paulo - SP | L7: 150 | N7: CUMPRIDO | O7: Joao Tomaz da Silva | P7: 11 97377-8980 | Q7: 70 | S7: SIM | T7: CUMPRIDO | U7: =Table_4[[#This Row],[VALOR]]-Table_4[[#This Row],[ CUSTO]] -> 80
B8: 45712 | D8: LACOSTA ADVOGADOS | E8: 21 95922-4000 / 11 91039-6920 | F8: Audiência | H8: 45734 | I8: 0.53472222 | J8: 14ª da Zona Leste | K8: São Paulo - SP | L8: 150 | N8: CUMPRIDO | O8: Elisangela ES - SOLUÇÕES JURÍDICAS | P8: 11 93067-5163 | Q8: 80 | S8: SIM | T8: CUMPRIDO | U8: =Table_4[[#This Row],[VALOR]]-Table_4[[#This Row],[ CUSTO]] -> 70
B9: 45712 | D9: LACOSTA ADVOGADOS | E9: 21 95922-4000 / 11 91039-6920 | F9: Audiência | H9: 45742 | I9: 0.5625 | J9: 14ª da Barra Funda | K9: São Paulo - SP | L9: 150 | N9: CUMPRIDO | O9: Joao Tomaz da Silva | P9: 11 97377-8980 | Q9: 70 | S9: SIM | T9: CUMPRIDO | U9: =Table_4[[#This Row],[VALOR]]-Table_4[[#This Row],[ CUSTO]] -> 80
B10: 45712 | D10: LACOSTA ADVOGADOS | E10: 21 95922-4000 / 11 91039-6920 | F10: Audiência | H10: 45743 | I10: 0.39583333 | J10: 75ª da Barra Funda | K10: São Paulo - SP | L10: 150 | N10: CUMPRIDO | O10: Joao Tomaz da Silva | P10: 11 97377-8980 | Q10: 70 | S10: SIM | T10: CUMPRIDO | U10: =Table_4[[#This Row],[VALOR]]-Table_4[[#This Row],[ CUSTO]] -> 80
B11: 45714 | D11: Marília Martins | E11: 62 9410-5041 | F11: UNA - Presencial | H11: 45726 | I11: 0.48611111 | J11: 11ª Vara do Trabalho | K11: Guarulhos - SP | L11: 200 | N11: CUMPRIDO | O11: Alessandra Oliveira | P11: 11 99656-3238 | Q11: 80 | S11: SIM | T11: CUMPRIDO | U11: =Table_4[[#This Row],[VALOR]]-Table_4[[#This Row],[ CUSTO]] -> 120
B12: 45715 | D12: Jessica | E12: 41 9685-0539 | F12: Coleta de Assinaturas | G12: JOSÉ IVAN BEZERRA | H12: 45722 | I12: 0.41666667 | J12: Av. Dom Luís, 807 – 20º e 21º andar, Meireles | K12: Fortaleza - CE | L12: =300+91.6+4 -> 395.6 | M12: ok | N12: CUMPRIDO | O12: Gabriela Sousa | P12: 85 8640-0693 | Q12: =80+4+91.6 -> 175.6 | S12: SIM | T12: CUMPRIDO | U12: =Table_4[[#This Row],[VALOR]]-Table_4[[#This Row],[ CUSTO]] -> 220
B13: 45716 | D13: Jessica | E13: 41 9685-0539 | F13: Coleta de Assinaturas | G13: VALDEVINO PEREIRA SANTOS | H13: 45722 | I13: 0.41666667 | J13: RUA Gumercindo Marota N 81. Bairro: Santo Amaro | K13: Joanópolis - SP | L13: =350+59.7 -> 409.7 | M13: ok | N13: CUMPRIDO | O13: Gunnar Alberto Quina | P13: 11 91263-6342 | Q13: =200+119.4 -> 319.4 | S13: SIM | T13: CUMPRIDO | U13: =Table_4[[#This Row],[VALOR]]-Table_4[[#This Row],[ CUSTO]] -> 90.3
B14: 45716 | D14: Aline Paixão / Coutinho e Zorzanelli | E14: 13 99777-5515 / 21 98612-3240 | F14: UNA - Presencial | G14: 0010744-17.2024.5.15.0084 | H14: 45723 | I14: 0.41666667 | J14: 4ª Vara do Trabalho | K14: São José dos Campos - SP | L14: 300 | N14: CUMPRIDO | O14: Helena do Amaral Olivar Simionelli | P14: 12 99108-0694 | Q14: 100 | S14: SIM | T14: CUMPRIDO | U14: =Table_4[[#This Row],[VALOR]]-Table_4[[#This Row],[ CUSTO]] -> 200
B15: 45716 | D15: Jessica | E15: 41 9685-0539 | F15: Coleta de Assinaturas | G15: MARIA NANCI RODRIGUES PINHEIRO | H15: 45726 | I15: 0.45833333 | J15: Av. Dom Luís, 807 – 20º e 21º andar, Meireles | K15: Fortaleza - CE | L15: =300+91.2 -> 391.2 | M15: ok | N15: CUMPRIDO | O15: Gabriela Sousa | P15: 85 8640-0693 | Q15: =80+91.6 -> 171.6 | S15: SIM | T15: CUMPRIDO | U15: =Table_4[[#This Row],[VALOR]]-Table_4[[#This Row],[ CUSTO]] -> 219.6
B16: 45716 | D16: Vivian Barbosa / Raquel Moreira | E16: 11 94569-1656 / 11 98450-5051 | F16: Inicial - Presencial | G16: 0011845-93.2024.5.15.0115 | H16: 45729 | I16: 0.55555556 | J16: 2ª Vara do Trabalho | K16: Presidente Prudente - SP | L16: 400 | N16: CUMPRIDO | O16: Janaina Joice de Sousa Lourenço | P16: 18 98143-5578 | Q16: 170 | S16: SIM | T16: CUMPRIDO | U16: =Table_4[[#This Row],[VALOR]]-Table_4[[#This Row],[ CUSTO]] -> 230
B17: 45716 | D17: Vivian Barbosa / Raquel Moreira | E17: 11 94569-1656 / 11 98450-5051 | F17: Inicial - Virtual | G17: 0012738-32.2024.5.15.0003 | H17: 45729 | I17: 0.33333333 | J17: 1ª Vara do Trabalho | K17: Sorocaba - SP | L17: 75 | N17: CUMPRIDO | O17: Priscilla Araújo | P17: 11 96379-9086 | S17: SIM | T17: CUMPRIDO | U17: =Table_4[[#This Row],[VALOR]]-Table_4[[#This Row],[ CUSTO]] -> 75
B18: 45716 | D18: Vinícius Silvério | E18: 41 9178-7396 | F18: Instrução - Presencial | G18: 0020887-16.2021.5.04.0007 | H18: 45736 | I18: 0.55555556 | J18: 7ª Vara do Trabalho | K18: Porto Alegre - RS | L18: 400 | N18: CUMPRIDO | O18: Marlon de Araújo Aita | P18: 51 8405-8197 | Q18: 120 | S18: SIM | T18: CUMPRIDO | U18: =Table_4[[#This Row],[VALOR]]-Table_4[[#This Row],[ CUSTO]] -> 280
B19: 45721 | D19: Sepulveda | E19: 19 99651-8840 | F19: UNA - Presencial | H19: 45722 | I19: 0.42708333 | J19: Vara do Trabalho | K19: Itatiba - SP | L19: 150 | N19: CUMPRIDO | O19: Natalia Kaori Toyoda | P19: 19 98109-8066 | Q19: 120 | S19: SIM | T19: CUMPRIDO | U19: =Table_4[[#This Row],[VALOR]]-Table_4[[#This Row],[ CUSTO]] -> 30
B20: 45722 | D20: Thiago Coriolano | E20: 11 98775-8123 | F20: Audiência | H20: 45723 | I20: 0.35416667 | J20: 2ª | K20: Santo André - SP | L20: 200 | N20: CUMPRIDO | O20: Aureni | P20: 11 99896-9511 | Q20: 70 | R20: desv | S20: SIM | T20: CUMPRIDO | U20: =Table_4[[#This Row],[VALOR]]-Table_4[[#This Row],[ CUSTO]] -> 130
B21: 45722 | D21: Sepulveda | E21: 19 99651-8840 | F21: UNA - Presencial | H21: 45726 | I21: 0.64583333 | J21: 1ª Vara do Trabalho | K21: Osasco - SP | L21: 150 | N21: CUMPRIDO | O21: Joao Tomaz da Silva | P21: 11 97377-8980 | Q21: 70 | S21: SIM | T21: CUMPRIDO | U21: =Table_4[[#This Row],[VALOR]]-Table_4[[#This Row],[ CUSTO]] -> 80
B22: 45722 | D22: Anna - Luan | E22: 45 9928-1123 | F22: Conciliação - Presencial | G22: 1017839-60.2024.8.26.0008 | H22: 45733 | I22: 0.58333333 | J22: 1ª Juizado Especial Cível de Tatuapé | K22: São Paulo - SP | L22: 120 | N22: CUMPRIDO | O22: Leandro Ribeiro Lima | P22: 19 98420-0002 | Q22: 50 | S22: SIM | T22: CUMPRIDO | U22: =Table_4[[#This Row],[VALOR]]-Table_4[[#This Row],[ CUSTO]] -> 70
B23: 45722 | D23: LACOSTA ADVOGADOS | E23: 21 95922-4000 / 11 91039-6920 | F23: Instrução - Presencial | H23: 45737 | I23: 0.60416667 | J23: 90ª da Barra Funda | K23: São Paulo - SP | L23: 150 | N23: CUMPRIDO | O23: Joao Tomaz da Silva | P23: 11 97377-8980 | Q23: 70 | S23: SIM | T23: CUMPRIDO | U23: =Table_4[[#This Row],[VALOR]]-Table_4[[#This Row],[ CUSTO]] -> 80
B24: 45723 | D24: Thiago Coriolano | E24: 11 98775-8123 | F24: Audiência | H24: 45723 | I24: 0.38541667 | J24: Virtual | L24: 170 | N24: CUMPRIDO | O24: Priscilla Araújo | P24: 11 96379-9086 | Q24: 50 | S24: SIM | T24: CUMPRIDO | U24: =Table_4[[#This Row],[VALOR]]-Table_4[[#This Row],[ CUSTO]] -> 120
B25: 45723 | D25: Beça e Coussirat | E25: 11 97678-8835 | F25: Audiência | H25: 45726 | I25: 0.37638889 | J25: 1ª Vara do Trabalho | K25: Rio de Janeiro - RJ | L25: 150 | N25: CUMPRIDO | O25: Luana Martha | P25: 21 99499-9021 | Q25: 50 | S25: SIM | T25: CUMPRIDO | U25: =Table_4[[#This Row],[VALOR]]-Table_4[[#This Row],[ CUSTO]] -> 100
B26: 45723 | D26: Jessica | E26: 41 9685-0539 | F26: Coleta de Assinaturas | G26: MARIA JOSEFA PEREIRA LIMA | H26: 45726 | I26: 0.41666667 | J26: Filial Barra Funda | K26: São Paulo - SP | L26: 300 | M26: ok | N26: CUMPRIDO | O26: Arlindo Felipe Jr | P26: 11 99635-2611 | Q26: 50 | S26: SIM | T26: CUMPRIDO | U26: =Table_4[[#This Row],[VALOR]]-Table_4[[#This Row],[ CUSTO]] -> 250
B27: 45723 | D27: LACOSTA ADVOGADOS | E27: 21 95922-4000 / 11 91039-6920 | F27: Audiência | H27: 45727 | I27: 0.38541667 | J27: 67ª Vara do Trabalho da Barra Funda | K27: São Paulo - SP | L27: 150 | N27: CUMPRIDO | O27: Joao Tomaz da Silva | P27: 11 97377-8980 | Q27: 70 | S27: SIM | T27: CUMPRIDO | U27: =Table_4[[#This Row],[VALOR]]-Table_4[[#This Row],[ CUSTO]] -> 80
B28: 45723 | D28: JH Gomes Advocacia | E28: 11 98492-3401 | F28: Audiência | G28: 1002117-53.2024.5.02.0606 | H28: 45729 | I28: 0.375 | J28: 6ª Vara do Trabalho da Zona Leste | K28: São Paulo - SP | L28: 150 | N28: CUMPRIDO | O28: Calebe Fernandes da Silva Araújo | P28: 91 8418-4224 | Q28: 50 | R28: desv | S28: SIM | T28: CUMPRIDO | U28: =Table_4[[#This Row],[VALOR]]-Table_4[[#This Row],[ CUSTO]] -> 100
B29: 45726 | D29: Diego Carrara Palandrani | E29: 44 9815-1208 | F29: UNA - Presencial | G29: 1002403-59.2024.5.02.0241 | H29: 45727 | I29: 0.45833333 | J29: 1ª Vara do Trabalho | K29: Cotia - SP | L29: 170 | N29: CUMPRIDO | O29: Andreia Arantes | P29: 11 94736-8565 | Q29: 80 | S29: SIM | T29: CUMPRIDO | U29: =Table_4[[#This Row],[VALOR]]-Table_4[[#This Row],[ CUSTO]] -> 90
B30: 45726 | D30: Jessica | E30: 41 9685-0539 | F30: Coleta de Assinaturas | G30: Daniela Maia Alves | H30: 45727 | I30: 0.41666667 | J30: Rua Dr Campos Jr, 40, Centro. Próximo da praça Tiradentes | K30: Sete Lagoas - MG | L30: =300+74.1 -> 374.1 | M30: ok | N30: CUMPRIDO | O30: Barbara Moreira | P30: 31 9545-2147 | Q30: =50+74.1 -> 124.1 | S30: SIM | T30: CUMPRIDO | U30: =Table_4[[#This Row],[VALOR]]-Table_4[[#This Row],[ CUSTO]] -> 250
B31: 45726 | D31: Sepulveda | E31: 19 99651-8840 | F31: UNA - Presencial | H31: 45729 | I31: 0.45833333 | J31: 5ª Vara do Trabalho | K31: Osasco - SP | L31: 150 | N31: CUMPRIDO | O31: Regiane Alves | P31: 11 97609-6392 | Q31: 70 | S31: SIM | T31: CUMPRIDO | U31: =Table_4[[#This Row],[VALOR]]-Table_4[[#This Row],[ CUSTO]] -> 80
B32: 45726 | D32: Sepulveda | E32: 19 99651-8840 | F32: Acompanhamento de Perícia | H32: 45730 | I32: 0.54166667 | J32: Rua Coronel Mursa, 56 – Brás | K32: São Paulo - SP | L32: 150 | N32: CUMPRIDO | O32: Arlindo Felipe Jr | P32: 11 99635-2611 | Q32: 50 | S32: SIM | T32: CUMPRIDO | U32: =Table_4[[#This Row],[VALOR]]-Table_4[[#This Row],[ CUSTO]] -> 100
B33: 45727 | D33: Thiago Coriolano | E33: 11 98775-8123 | F33: Audiência | H33: 45727 | I33: 0.625 | J33: Procon | K33: Suzano - SP | L33: 200 | N33: CUMPRIDO | O33: Bianca Mota | P33: 11 97068-3345 | Q33: 70 | S33: SIM | T33: CUMPRIDO | U33: =Table_4[[#This Row],[VALOR]]-Table_4[[#This Row],[ CUSTO]] -> 130
B34: 45727 | D34: Bruno Magalhães | E34: 62 9166-2415 | F34: Audiência | H34: 45728 | I34: 0.41666667 | J34: 55ª Vara do Trabalho | K34: Rio de Janeiro - RJ | L34: 400 | N34: CUMPRIDO | O34: Catharine Rosa Cervino | P34: 21 97127-0834 | Q34: 70 | S34: SIM | T34: CUMPRIDO | U34: =Table_4[[#This Row],[VALOR]]-Table_4[[#This Row],[ CUSTO]] -> 330
B35: 45727 | D35: Jessica | E35: 41 9685-0539 | F35: Coleta de Assinaturas | G35: Marcos Roberto Cortes | H35: 45728 | I35: 0.4375 | J35: Rua Mexico, 31, sala 703, Centro | K35: Rio de Janeiro - RJ | L35: =300+36.8 -> 336.8 | M35: ok | N35: CUMPRIDO | O35: Wesley Severino Mattos | P35: 21 98179-8221 | Q35: =100+36.8 -> 136.8 | S35: SIM | T35: CUMPRIDO | U35: =Table_4[[#This Row],[VALOR]]-Table_4[[#This Row],[ CUSTO]] -> 200
B36: 45727 | D36: Jessica | E36: 41 9685-0539 | F36: Coleta de Assinaturas | G36: ZORAIDE GOMES CARVALHO DE SABOYA | H36: 45728 | I36: 0.41666667 | J36: Rua Padre Carapuceiro, 858 Centro Empresarial Queiroz Galvão, Torre Cícero Dias 7° andar sala 706 | K36: Recife -PE | L36: =300+92 -> 392 | M36: ok | N36: CUMPRIDO | O36: Rafael Vasconcelos Dutra | P36: 81 8452-1092 | Q36: =50+92 -> 142 | S36: SIM | T36: CUMPRIDO | U36: =Table_4[[#This Row],[VALOR]]-Table_4[[#This Row],[ CUSTO]] -> 250
B37: 45727 | D37: LACOSTA ADVOGADOS | E37: 21 95922-4000 / 11 91039-6920 | F37: Audiência | G37: 1001197-82.2024.5.02.0411 | H37: 45729 | I37: 0.54166667 | J37: Vara do Trabalho | K37: Ribeirão Pires - SP | L37: 200 | N37: CUMPRIDO | O37: Roberta Senne Hidalgo | P37: 11 98278-5283 | Q37: 100 | S37: SIM | T37: CUMPRIDO | U37: =Table_4[[#This Row],[VALOR]]-Table_4[[#This Row],[ CUSTO]] -> 100
B38: 45727 | D38: Andre Oliveira | E38: 19 98127-4386 | F38: UNA - Presencial | G38: 1000178-62.2025.5.02.0716 | H38: 45730 | I38: 0.38194444 | J38: 16ª Vara do Trabalho da Zona Sul | K38: São Paulo - SP | L38: 200 | M38: ok | N38: CUMPRIDO | O38: Elisangela ES - SOLUÇÕES JURÍDICAS | P38: 11 93067-5163 | Q38: 80 | S38: SIM | T38: CUMPRIDO | U38: =Table_4[[#This Row],[VALOR]]-Table_4[[#This Row],[ CUSTO]] -> 120
B39: 45728 | D39: Thiago Coriolano | E39: 11 98775-8123 | F39: Audiência | H39: 45729 | I39: 0.38541667 | J39: 1ª Vara do Trabalho | K39: Suzano - SP | L39: 200 | N39: CUMPRIDO | O39: Thais Pecin | P39: 11 97496-7395 | Q39: 90 | R39: desv | S39: SIM | T39: CUMPRIDO | U39: =Table_4[[#This Row],[VALOR]]-Table_4[[#This Row],[ CUSTO]] -> 110
B40: 45728 | D40: Dayana Reis | E40: 11 94772-0646 | F40: Conciliação - Presencial | G40: 0801005-10.2025.8.19.0045 | H40: 45729 | I40: 0.65277778 | J40: Juizado Especial Cível | K40: Resende - RJ | L40: 250 | N40: CUMPRIDO | O40: Igor Ferreira | P40: 24 99981-3333 | Q40: 150 | S40: SIM | T40: CUMPRIDO | U40: =Table_4[[#This Row],[VALOR]]-Table_4[[#This Row],[ CUSTO]] -> 100
B41: 45728 | D41: Thulyo Augustto | E41: 62 9683-9870 | F41: Audiência | G41: 0000087-39.2025.5.08.0128 | H41: 45729 | I41: 0.39583333 | J41: 3ª Vara do Trabalho | K41: Marabá - PA | L41: 350 | N41: CUMPRIDO | O41: Cinthia Veloso Alho Igreja | P41: 94 9233-5899 | Q41: 150 | S41: SIM | T41: CUMPRIDO | U41: =Table_4[[#This Row],[VALOR]]-Table_4[[#This Row],[ CUSTO]] -> 200
B42: 45728 | D42: Jessica | E42: 41 9685-0539 | F42: Coleta de Assinaturas | G42: RUY ALVES DE PAIVA | H42: 45729 | I42: 0.41666667 | J42: Rua Via Acesso Dois, nº 64, casa, Condomínio residencial Terra Nova | K42: Uberaba - MG | L42: =300+74.1 -> 374.1 | M42: ok | N42: CUMPRIDO | O42: Ana Guimarães | P42: 34 9159-6726 | Q42: =100+74.1 -> 174.1 | R42: desv | S42: SIM | T42: CUMPRIDO | U42: =Table_4[[#This Row],[VALOR]]-Table_4[[#This Row],[ CUSTO]] -> 200
B43: 45728 | D43: Vivian Barbosa / Raquel Moreira | E43: 11 94569-1656 / 11 98450-5051 | F43: Instrução - Presencial | G43: 0011658-73.2024.5.15.0022 | H43: 45734 | I43: 0.45972222 | J43: Vara do Trabalho | K43: Mogi Mirim - SP | L43: 250 | N43: CUMPRIDO | O43: Daiane | P43: 19 98172-7578 | Q43: 90 | S43: SIM | T43: CUMPRIDO | U43: =Table_4[[#This Row],[VALOR]]-Table_4[[#This Row],[ CUSTO]] -> 160
B44: 45728 | D44: Vivian Barbosa / Raquel Moreira | E44: 11 94569-1656 / 11 98450-5051 | F44: Instrução - Presencial | G44: 0011217-32.2024.5.15.0139 | H44: 45735 | I44: 0.65277778 | J44: Vara do Trabalho | K44: Ubatuba - SP | L44: 250 | N44: CUMPRIDO | O44: Glaydson Roberto | P44: 12 99795-5162 | Q44: 100 | S44: SIM | T44: CUMPRIDO | U44: =Table_4[[#This Row],[VALOR]]-Table_4[[#This Row],[ CUSTO]] -> 150
B45: 45728 | D45: Andre Oliveira | E45: 19 98127-4386 | F45: Audiência | G45: 1000163-85.2025.5.02.0072 | H45: 45736 | I45: 0.36111111 | J45: 72ª Vara do Trabalho da Barra Funda | K45: São Paulo - SP | M45: ok | N45: CUMPRIDO | O45: Elisangela ES - SOLUÇÕES JURÍDICAS | P45: 11 93067-5163 | Q45: 50 | S45: SIM | T45: CUMPRIDO | U45: =Table_4[[#This Row],[VALOR]]-Table_4[[#This Row],[ CUSTO]] -> -50
B46: 45728 | D46: Andre Oliveira | E46: 19 98127-4386 | F46: Audiência | G46: 1000163-85.2025.5.02.0072 | H46: 45736 | I46: 0.36111111 | J46: 72ª Vara do Trabalho da Barra Funda | K46: São Paulo - SP | L46: 300 | M46: ok | N46: CUMPRIDO | O46: Joao Tomaz da Silva | P46: 11 97377-8980 | Q46: 70 | S46: SIM | T46: CUMPRIDO | U46: =Table_4[[#This Row],[VALOR]]-Table_4[[#This Row],[ CUSTO]] -> 230
B47: 45728 | D47: Andre Oliveira | E47: 19 98127-4386 | F47: UNA - Presencial | G47: 1001807-97.2024.5.02.0072 | H47: 45737 | I47: 0.375 | J47: 72ª Vara do Trabalho da Barra Funda | K47: São Paulo - SP | L47: 300 | M47: ok | N47: CUMPRIDO | O47: Joao Tomaz da Silva | P47: 11 97377-8980 | Q47: 120 | S47: SIM | T47: CUMPRIDO | U47: =Table_4[[#This Row],[VALOR]]-Table_4[[#This Row],[ CUSTO]] -> 180
B48: 45728 | D48: Andre Oliveira | E48: 19 98127-4386 | F48: Audiência | G48: 1000172-49.2025.5.02.0039 | H48: 45740 | I48: 0.39583333 | J48: 39ª Vara do Trabalho | K48: São Paulo - SP | L48: 200 | M48: ok | N48: CUMPRIDO | O48: Joao Tomaz da Silva | P48: 11 97377-8980 | Q48: 70 | S48: SIM | T48: CUMPRIDO | U48: =Table_4[[#This Row],[VALOR]]-Table_4[[#This Row],[ CUSTO]] -> 130
B49: 45729 | D49: Rodrigo Bezerra | E49: 11 99360-4364 | F49: Audiência Virtual | G49: 1000087-72.2025.5.02.0521 | H49: 45730 | I49: 0.48611111 | J49: Virtual | K49: Virtual | L49: 150 | N49: CUMPRIDO | O49: Priscilla Araújo | P49: 11 96379-9086 | Q49: 50 | S49: SIM | T49: CUMPRIDO | U49: =Table_4[[#This Row],[VALOR]]-Table_4[[#This Row],[ CUSTO]] -> 100
B50: 45729 | D50: Jessica | E50: 41 9685-0539 | F50: Coleta de Assinaturas | G50: TEREZINHA DE FATIMA DA SILVA | H50: 45730 | I50: 0.375 | J50: R SERAPHIM CORAL, 71, JARDIM ALVORADA | K50: Sumaré - SP | L50: =300+53.16 -> 353.16 | M50: ok | N50: CUMPRIDO | O50: Camila Rodrigues | P50: 19 98405-2277 | Q50: =100+53.16 -> 153.16 | S50: SIM | T50: CUMPRIDO | U50: =Table_4[[#This Row],[VALOR]]-Table_4[[#This Row],[ CUSTO]] -> 200
B51: 45729 | D51: Sepulveda | E51: 19 99651-8840 | F51: UNA - Presencial | H51: 45733 | I51: 0.5 | J51: Vara do Trabalho | K51: Itatiba - SP | L51: 150 | N51: CUMPRIDO | O51: Natália Martins Leite | P51: 11 96859-6050 | Q51: 100 | R51: desv | S51: SIM | T51: CUMPRIDO | U51: =Table_4[[#This Row],[VALOR]]-Table_4[[#This Row],[ CUSTO]] -> 50
B52: 45729 | D52: Dayana Reis | E52: 11 94772-0646 | F52: Conciliação - Presencial | G52: 0801005-10.2025.8.19.0045 | H52: 45733 | I52: 0.66666667 | J52: Juizado Especial Cível | K52: Resende - RJ | L52: 250 | N52: CUMPRIDO | O52: Igor Ferreira | P52: 24 99981-3333 | Q52: 150 | S52: SIM | T52: CUMPRIDO | U52: =Table_4[[#This Row],[VALOR]]-Table_4[[#This Row],[ CUSTO]] -> 100
B53: 45729 | D53: Jessica | E53: 41 9685-0539 | F53: Coleta de Assinaturas | G53: XAVIER SATIRO DE SOUSA | H53: 45734 | I53: 0.58333333 | J53: Av. Dom Luís, 807 – 20º e 21º andar, Meireles | K53: Fortaleza - CE | L53: =300 -> 300 | M53: ok | N53: CUMPRIDO | O53: Gabriela Sousa | P53: 85 8640-0693 | Q53: =80 -> 80 | S53: SIM | T53: CUMPRIDO | U53: =Table_4[[#This Row],[VALOR]]-Table_4[[#This Row],[ CUSTO]] -> 220
B54: 45729 | D54: Eliana Ivano | E54: 11 99442-6135 | F54: Instrução - Presencial | H54: 45734 | I54: 0.63888889 | J54: Vara do Trabalho | K54: Ubatuba - SP | L54: 250 | N54: CUMPRIDO | O54: Glaydson Roberto | P54: 12 99795-5162 | Q54: 100 | S54: SIM | T54: CUMPRIDO | U54: =Table_4[[#This Row],[VALOR]]-Table_4[[#This Row],[ CUSTO]] -> 150
B55: 45729 | D55: Jessica | E55: 41 9685-0539 | F55: Coleta de Assinaturas | G55: Conceição Braga | H55: 45734 | K55: Corumbá - MT | L55: =350+80+74.1 -> 504.1 | M55: ok | N55: CUMPRIDO | O55: Laura Elias Botelho | P55: 67 9602-6422 | Q55: =200+80+74.1 -> 354.1 | S55: SIM | T55: CUMPRIDO | U55: =Table_4[[#This Row],[VALOR]]-Table_4[[#This Row],[ CUSTO]] -> 150
B56: 45729 | D56: Andre Oliveira | E56: 19 98127-4386 | F56: Audiência | H56: 45741 | I56: 0.45833333 | J56: 55ª Vara do Trabalho da Barra Funda | K56: São Paulo - SP | M56: ok | N56: CUMPRIDO | O56: Taiana Santos | Q56: 50 | S56: SIM | T56: CUMPRIDO | U56: =Table_4[[#This Row],[VALOR]]-Table_4[[#This Row],[ CUSTO]] -> -50
B57: 45729 | D57: Andre Oliveira | E57: 19 98127-4386 | F57: Audiência | H57: 45741 | I57: 0.45833333 | J57: 55ª Vara do Trabalho da Barra Funda | K57: São Paulo - SP | L57: 350 | M57: ok | N57: CUMPRIDO | O57: Elisangela ES - SOLUÇÕES JURÍDICAS | P57: 11 93067-5163 | Q57: 70 | S57: SIM | T57: CUMPRIDO | U57: =Table_4[[#This Row],[VALOR]]-Table_4[[#This Row],[ CUSTO]] -> 280
B58: 45729 | D58: Andre Oliveira | E58: 19 98127-4386 | F58: Audiência | H58: 45743 | I58: 0.44444444 | J58: 83ª Vara do Trabalho da Barra Funda | K58: São Paulo - SP | L58: 200 | M58: ok | N58: CUMPRIDO | O58: Leandro dos Santos Silva | P58: 11 95343-6921 | Q58: 70 | S58: SIM | T58: CUMPRIDO | U58: =Table_4[[#This Row],[VALOR]]-Table_4[[#This Row],[ CUSTO]] -> 130
B59: 45729 | D59: Andre Oliveira | E59: 19 98127-4386 | F59: Audiência | H59: 45743 | I59: 0.53125 | J59: 2ª Vara do Trabalho | K59: Santana de Parnaíba - SP | L59: 300 | N59: CUMPRIDO | O59: Elisangela ES - SOLUÇÕES JURÍDICAS | P59: 11 93067-5163 | Q59: 150 | S59: SIM | T59: CUMPRIDO | U59: =Table_4[[#This Row],[VALOR]]-Table_4[[#This Row],[ CUSTO]] -> 150
B60: 45729 | D60: Simone Fraga | E60: 21 98403-8345 | K60: São Pedro da Aldeia - RJ | U60: =Table_4[[#This Row],[VALOR]]-Table_4[[#This Row],[ CUSTO]] -> 0
B61: 45730 | D61: Sepulveda | E61: 19 99651-8840 | F61: Acompanhamento de Perícia | H61: 45734 | I61: 0.5625 | J61: OPERGEL COMERCIAL E INDUSTRIAL DE PRODUTOS ALIMENTICIOS LTDA JOAQUIM SIMOES, 350, JARDIM VERA CRUZ | K61: Louveira - SP | L61: 150 | N61: CUMPRIDO | O61: Beatrice Hirsch | P61: 19 99693-8843 | Q61: 90 | S61: SIM | T61: CUMPRIDO | U61: =Table_4[[#This Row],[VALOR]]-Table_4[[#This Row],[ CUSTO]] -> 60
B62: 45730 | D62: Sepulveda | E62: 19 99651-8840 | F62: Acompanhamento de Perícia | H62: 45735 | I62: 0.41666667 | J62: Rua Domingos Piunti, 321, Bairro Progresso | K62: Itu - SP | L62: 150 | N62: CUMPRIDO | O62: Willian Matheus Costa de Paula | P62: 11 99887-0242 | Q62: 50 | S62: SIM | T62: CUMPRIDO | U62: =Table_4[[#This Row],[VALOR]]-Table_4[[#This Row],[ CUSTO]] -> 100
B63: 45730 | D63: Marcos Piva | E63: 11 96608-7561 | F63: Audiência | H63: 45740 | I63: 0.40625 | J63: 3ª Vara do Trabalho | K63: Santos - SP | L63: 300 | M63: ok | N63: CUMPRIDO | O63: IRB - Isabelle | P63: 13 98804-4390 | Q63: 130 | S63: SIM | T63: CUMPRIDO | U63: =Table_4[[#This Row],[VALOR]]-Table_4[[#This Row],[ CUSTO]] -> 170
B64: 45730 | D64: Marcos Piva | E64: 11 96608-7561 | F64: Audiência | H64: 45740 | I64: 0.36111111 | J64: 5ª Vara do Trabalho | K64: Santos - SP | L64: 300 | M64: ok | N64: CUMPRIDO | O64: IRB - Isabelle | P64: 13 98804-4390 | Q64: 130 | S64: SIM | T64: CUMPRIDO | U64: =Table_4[[#This Row],[VALOR]]-Table_4[[#This Row],[ CUSTO]] -> 170
B65: 45733 | D65: Sepulveda | E65: 19 99651-8840 | F65: Acompanhamento de Perícia | H65: 45733 | I65: 0.45833333 | K65: Capivari - SP | L65: 150 | N65: CUMPRIDO | O65: Márcia Araujo Batagim | P65: 41 9204-0259 | Q65: 100 | S65: SIM | T65: CUMPRIDO | U65: =Table_4[[#This Row],[VALOR]]-Table_4[[#This Row],[ CUSTO]] -> 50
B66: 45733 | D66: Gustavo Braga | E66: 61 8271-2059 | F66: Audiência | H66: 45734 | I66: 0.63541667 | J66: Vara do Trabalho | K66: Diamantina - MG | L66: 200 | N66: CUMPRIDO | O66: Karen Roberta Paranhos | P66: 38 9995-0495 | Q66: 150 | S66: SIM | T66: CUMPRIDO | U66: =Table_4[[#This Row],[VALOR]]-Table_4[[#This Row],[ CUSTO]] -> 50
B67: 45733 | D67: Jessica | E67: 41 9685-0539 | F67: Coleta de Assinaturas | G67: João de Souza Melo | H67: 45735 | I67: 0.66666667 | J67: Sede da Barra Funda | K67: São Paulo - SP | L67: =300+36.8 -> 336.8 | M67: ok | N67: CUMPRIDO | O67: Arlindo Felipe Jr | P67: 11 99635-2611 | Q67: =50+36.8 -> 86.8 | S67: SIM | T67: CUMPRIDO | U67: =Table_4[[#This Row],[VALOR]]-Table_4[[#This Row],[ CUSTO]] -> 250
B68: 45733 | D68: Valter da Conceição Cerqueira Júnior | E68: 73 9861-5118 | F68: Conciliação - Presencial | H68: 45737 | I68: 0.64583333 | J68: sala 05, 5 andar do JEC Vergueiro | K68: São Paulo - SP | L68: 200 | N68: CUMPRIDO | O68: Elisangela ES - SOLUÇÕES JURÍDICAS | P68: 11 93067-5163 | Q68: 80 | S68: SIM | T68: CUMPRIDO | U68: =Table_4[[#This Row],[VALOR]]-Table_4[[#This Row],[ CUSTO]] -> 120
B69: 45733 | D69: Josiane | E69: 45 9979-5193 | F69: Conciliação - Presencial | H69: 45743 | I69: 0.59722222 | J69: 13º Juizado Especial Cível da Regional do Méier | K69: Rio de Janeiro - RJ | L69: 120 | N69: CUMPRIDO | O69: Natália de Azevedo | P69: 21 99740-1290 | Q69: 120 | S69: SIM | T69: CUMPRIDO | U69: =Table_4[[#This Row],[VALOR]]-Table_4[[#This Row],[ CUSTO]] -> 0
B70: 45734 | D70: Leandro Ribeiro Lima | E70: 19 98420-0002 | F70: Audiência | H70: 45734 | I70: 0.63541667 | J70: 12ª Vara do Trabalho | K70: Guarulhos - SP | L70: 150 | N70: CUMPRIDO | O70: Alessandra Oliveira | P70: 11 99656-3238 | Q70: 80 | S70: SIM | T70: CUMPRIDO | U70: =Table_4[[#This Row],[VALOR]]-Table_4[[#This Row],[ CUSTO]] -> 70
B71: 45734 | D71: Coutinho e Zorzanelli Contratante | E71: 21 98612-3240 | F71: Instrução - Presencial | G71: 0010853-11.2024.5.15.0123 | H71: 45735 | I71: 0.58333333 | J71: Vara do Trabalho | K71: Capão Bonito - SP | L71: 400 | N71: CUMPRIDO | O71: Letícia de Oliveira Jacob | P71: 15 99763-3948 | Q71: 150 | S71: SIM | T71: CUMPRIDO | U71: =Table_4[[#This Row],[VALOR]]-Table_4[[#This Row],[ CUSTO]] -> 250
B72: 45734 | D72: Anna - Luan | E72: 45 9928-1123 | F72: Conciliação - Presencial | H72: 45743 | I72: 0.58333333 | J72: Juizado Especial Cível | K72: Santo André - SP | L72: 120 | N72: CUMPRIDO | O72: Stephanie Andrade de Oliveira | P72: 11 97638-6713 | Q72: 70 | S72: SIM | T72: CUMPRIDO | U72: =Table_4[[#This Row],[VALOR]]-Table_4[[#This Row],[ CUSTO]] -> 50
B73: 45735 | D73: Eliana Ivano | E73: 11 99442-6135 | F73: Audiência | H73: 45735 | I73: 0.46180556 | J73: 2ª Vara do Trabalho | K73: Jundiaí - SP | L73: 250 | N73: CUMPRIDO | O73: Neuza Maria Sousa Bessa | P73: 11 99892-5158 | Q73: 150 | S73: SIM | T73: CUMPRIDO | U73: =Table_4[[#This Row],[VALOR]]-Table_4[[#This Row],[ CUSTO]] -> 100
B74: 45735 | D74: Giselle - Pontes e Santana | E74: 31 9921-2646 | F74: UNA - Presencial | G74: 1000233-13.2025.5.02.0716 | H74: 45736 | I74: 0.35416667 | J74: 16ª Vara do Trabalho da Zona Sul | K74: São Paulo - SP | L74: 150 | N74: CUMPRIDO | O74: Patrícia de Oliveira Fernandes | P74: 11 98456-2122 | Q74: 70 | S74: SIM | T74: CUMPRIDO | U74: =Table_4[[#This Row],[VALOR]]-Table_4[[#This Row],[ CUSTO]] -> 80
B75: 45735 | D75: Jessica | E75: 41 9685-0539 | F75: Coleta de Assinaturas | G75: Acácio | H75: 45736 | I75: 0.39583333 | J75: Av guarabira 1082 | K75: João Pessoa - PB | L75: =300+93.6 -> 393.6 | M75: ok | N75: CUMPRIDO | O75: Adriana Franco | P75: 83 9964-9318 | Q75: =60+93.6 -> 153.6 | S75: SIM | T75: CUMPRIDO | U75: =Table_4[[#This Row],[VALOR]]-Table_4[[#This Row],[ CUSTO]] -> 240
B76: 45735 | D76: Ivan Rodrigues | E76: 15 99770-5277 | F76: Acompanhamento | H76: 45736 | J76: Fórum Cìvel | K76: Mogi das Cruzes - SP | L76: 300 | N76: CUMPRIDO | O76: Diligência Própria | S76: SIM | T76: CUMPRIDO | U76: =Table_4[[#This Row],[VALOR]]-Table_4[[#This Row],[ CUSTO]] -> 300
B77: 45735 | D77: Vivian Barbosa / Raquel Moreira | E77: 11 94569-1656 / 11 98450-5051 | F77: Inicial - Presencial | G77: 0011736-66.2024.5.15.0087 | H77: 45744 | I77: 0.46527778 | J77: 1ª Vara do Trabalho | K77: Paulínia - SP | L77: 500 | N77: CUMPRIDO | O77: Andréia Manzini | P77: 19 99452-9159 | Q77: 160 | S77: SIM | T77: CUMPRIDO | U77: =Table_4[[#This Row],[VALOR]]-Table_4[[#This Row],[ CUSTO]] -> 340
B78: 45736 | D78: Thiago Coriolano | E78: 11 98775-8123 | F78: UNA - Presencial | G78: 1000247-94.2025.5.02.0716 | H78: 45737 | I78: 0.39583333 | J78: 16ª Vara do Trabalho da Zona Sul | K78: São Paulo - SP | L78: 200 | N78: CUMPRIDO | O78: Patrícia de Oliveira Fernandes | P78: 11 98456-2122 | Q78: 70 | S78: SIM | T78: CUMPRIDO | U78: =Table_4[[#This Row],[VALOR]]-Table_4[[#This Row],[ CUSTO]] -> 130
B79: 45736 | D79: Beatriz Aragão & Bernardo | E79: 85 3252-2939 - 85 8405-1478 | F79: Audiência | H79: 45741 | I79: 0.39583333 | J79: 3ª Vara do Trabalho | K79: Jaboatão dos Guararapes - PE | L79: 170 | N79: CUMPRIDO | O79: Magno Alves | P79: 81 8828-7306 | Q79: 60 | S79: SIM | T79: CUMPRIDO | U79: =Table_4[[#This Row],[VALOR]]-Table_4[[#This Row],[ CUSTO]] -> 110
B80: 45736 | D80: Raissa - Concreserv | E80: 11 95107-8086 | F80: Conciliação - Presencial | H80: 45741 | I80: 0.58333333 | J80: 1ª Vara do Juizado Especial Cível de São Miguel Paulista | K80: São Paulo - SP | L80: 250 | N80: CUMPRIDO | O80: Andreza | P80: 11 98251-4885 | Q80: 100 | S80: SIM | T80: CUMPRIDO | U80: =Table_4[[#This Row],[VALOR]]-Table_4[[#This Row],[ CUSTO]] -> 150
B81: 45737 | D81: Milena Araujo | E81: 34 8435-8804 | F81: Cópias | G81: 0014221-25.2016.4.03.61050/011138-98.2016.4.03.6105 | H81: 45740 | J81: 5ª Vara Federal | K81: Campinas - SP | L81: 50 | N81: CUMPRIDO | O81: Arthur Della Negra | P81: 19 98820-9797 | Q81: 50 | S81: SIM | T81: CUMPRIDO | U81: =Table_4[[#This Row],[VALOR]]-Table_4[[#This Row],[ CUSTO]] -> 0
B82: 45737 | D82: Grace Bordalo | E82: 16 98822-1551 | F82: Sustentação Oral | G82: 1028926-13.2020.8.26.0506 | H82: 45741 | J82: Palácio da Justiça | K82: São Paulo - SP | L82: 600 | N82: CUMPRIDO | O82: Patrícia Aparecida Carneiro | P82: 11 98265-6766 | Q82: 300 | S82: SIM | T82: CUMPRIDO | U82: =Table_4[[#This Row],[VALOR]]-Table_4[[#This Row],[ CUSTO]] -> 300
B83: 45737 | D83: Jessica | E83: 41 9685-0539 | F83: Coleta de Assinaturas | G83: REGINALDO JACINTO DA SILVA | H83: 45742 | I83: 0.41666667 | J83: Rua Mexico, 31, sala 703, Centro | K83: Rio de Janeiro - RJ | L83: 300 | M83: ok | N83: CUMPRIDO | O83: Oswaldo Assumpção Jr | P83: 21 99672-1599 | Q83: 60 | S83: SIM | T83: CUMPRIDO | U83: =Table_4[[#This Row],[VALOR]]-Table_4[[#This Row],[ CUSTO]] -> 240
B84: 45740 | D84: Carlos Rodrigues da Silva Junior | E84: 11 99518-5004 | F84: Conciliação - Presencial | H84: 45741 | I84: 0.66666667 | J84: Juizado Especial Cível | K84: Suzano - SP | L84: 170 | N84: CUMPRIDO | O84: Alessandra Oliveira | P84: 11 99656-3238 | Q84: 60 | S84: SIM | T84: CUMPRIDO | U84: =Table_4[[#This Row],[VALOR]]-Table_4[[#This Row],[ CUSTO]] -> 110
B85: 45740 | D85: Thiago Coriolano | E85: 11 98775-8123 | F85: Audiência | G85: 0101305-10.2024.5.01.0074 | H85: 45741 | I85: 0.42708333 | J85: Vara do Trabalho | K85: Rio de Janeiro - RJ | L85: 250 | N85: CUMPRIDO | O85: Catharine Rosa Cervino | P85: 21 97127-0834 | Q85: 70 | S85: SIM | T85: CUMPRIDO | U85: =Table_4[[#This Row],[VALOR]]-Table_4[[#This Row],[ CUSTO]] -> 180
B86: 45740 | D86: Adriana Arruda | E86: 19 97128-1295 | F86: Cópias | H86: 45741 | J86: IBAMA | K86: Maceió - AL | L86: 200 | N86: CUMPRIDO | O86: Luiz Carlos Castro Lessa Júnior | P86: 82 9830-6063 | Q86: 100 | S86: SIM | T86: CUMPRIDO | U86: =Table_4[[#This Row],[VALOR]]-Table_4[[#This Row],[ CUSTO]] -> 100
B87: 45740 | D87: LACOSTA ADVOGADOS | E87: 21 95922-4000 / 11 91039-6920 | F87: Audiência | H87: 45742 | I87: 0.40277778 | J87: 80ª da Barra Funda | K87: São Paulo - SP | L87: 150 | N87: CUMPRIDO | O87: Joao Tomaz da Silva | P87: 11 97377-8980 | Q87: 70 | S87: SIM | T87: CUMPRIDO | U87: =Table_4[[#This Row],[VALOR]]-Table_4[[#This Row],[ CUSTO]] -> 80
B88: 45740 | D88: Jessica | E88: 41 9685-0539 | F88: Coleta de Assinaturas | G88: Silvia Pieroni | H88: 45742 | I88: 0.45833333 | J88: Sede da Barra Funda | K88: São Paulo - SP | L88: =300+36.8 -> 336.8 | M88: ok | N88: CUMPRIDO | O88: Amanda Pivott | P88: 11 94857-0549 | Q88: =70+36.8 -> 106.8 | S88: SIM | T88: CUMPRIDO | U88: =Table_4[[#This Row],[VALOR]]-Table_4[[#This Row],[ CUSTO]] -> 230
B89: 45740 | D89: LACOSTA ADVOGADOS | E89: 21 95922-4000 / 11 91039-6920 | F89: Audiência | H89: 45743 | I89: 0.40625 | J89: 28ª da Barra Funda | K89: São Paulo - SP | L89: 150 | N89: CUMPRIDO | O89: Amanda Pivott | P89: 11 94857-0549 | Q89: 70 | S89: SIM | T89: CUMPRIDO | U89: =Table_4[[#This Row],[VALOR]]-Table_4[[#This Row],[ CUSTO]] -> 80
B90: 45740 | D90: LACOSTA ADVOGADOS | E90: 21 95922-4000 / 11 91039-6920 | F90: Audiência | H90: 45743 | I90: 0.45833333 | J90: 1ª Vara do Trabalho | K90: Barueri - SP | L90: 150 | N90: CUMPRIDO | O90: Camila Roncalle | P90: 11 98992-0599 | Q90: 70 | S90: SIM | T90: CUMPRIDO | U90: =Table_4[[#This Row],[VALOR]]-Table_4[[#This Row],[ CUSTO]] -> 80
B91: 45741 | D91: Leonardo - Advocacia Soller | E91: 11 95657-2522 / 11 95657-2522 | F91: Conciliação - Presencial | G91: 0002963-94.2025.8.17.8201 | H91: 45742 | I91: 0.66666667 | J91: 24º Juizado Especial Cível | K91: Recife -PE | L91: 50 | N91: CUMPRIDO | O91: Rafael Vasconcelos Dutra | P91: 81 8452-1092 | S91: SIM | T91: CUMPRIDO | U91: =Table_4[[#This Row],[VALOR]]-Table_4[[#This Row],[ CUSTO]] -> 50
B92: 45741 | D92: Ivan Rodrigues | E92: 15 99770-5277 | F92: Acompanhamento | J92: Fórum Cìvel | K92: Mogi das Cruzes - SP | L92: 300 | N92: CUMPRIDO | O92: Diligência Própria | S92: SIM | T92: CUMPRIDO | U92: =Table_4[[#This Row],[VALOR]]-Table_4[[#This Row],[ CUSTO]] -> 300
B93: 45742 | D93: Rodrigo Bezerra | E93: 11 99360-4364 | F93: UNA - Presencial | G93: 1003160-16.2024.5.02.0221 | H93: 45743 | I93: 0.44444444 | J93: Vara do Trabalho | K93: Cajamar - SP | L93: 200 | N93: CUMPRIDO | O93: Jaqueline da Silva Machado | P93: 11 97581-8031 | Q93: 70 | S93: SIM | T93: CUMPRIDO | U93: =Table_4[[#This Row],[VALOR]]-Table_4[[#This Row],[ CUSTO]] -> 130
B94: 45742 | D94: Jessica | E94: 41 9685-0539 | F94: Coleta de Assinaturas | G94: EDIVALDO PEREIRA DA SILVA | H94: 45743 | I94: 0.41666667 | J94: Rua Antônio Rabelo Júnior, nº 161, Sala 1711 1712, Miramar | K94: João Pessoa - PB | L94: =300+95.6 -> 395.6 | M94: ok | N94: CUMPRIDO | O94: Adriana Franco | P94: 83 9964-9318 | Q94: =50+95.6 -> 145.6 | S94: SIM | T94: CUMPRIDO | U94: =Table_4[[#This Row],[VALOR]]-Table_4[[#This Row],[ CUSTO]] -> 250
B95: 45743 | D95: Gabriela Guerra Lima | E95: 11 97125-3227 | F95: Inicial - Presencial | H95: 45744 | I95: 0.50694444 | J95: 5ª Vara do Trabalho | K95: Ribeirão Preto - SP | L95: 250 | N95: CUMPRIDO | O95: Mayara Belfort | P95: 16 99138-1367 | Q95: 120 | S95: SIM | T95: CUMPRIDO | U95: =Table_4[[#This Row],[VALOR]]-Table_4[[#This Row],[ CUSTO]] -> 130
B96: 45747 | D96: Thiago Coriolano | E96: 11 98775-8123 | F96: UNA - Presencial | G96: 1002691-21.2024.5.02.0204 | H96: 45747 | I96: 0.5625 | J96: 4ª Vara do Trabalho | K96: Barueri - SP | L96: 250 | N96: CUMPRIDO | O96: Camila Roncalle | P96: 11 98992-0599 | Q96: 80 | S96: SIM | T96: CUMPRIDO | U96: =Table_4[[#This Row],[VALOR]]-Table_4[[#This Row],[ CUSTO]] -> 170
D97: Amanda Betanin | E97: 45 9814-7028 | F97: Conciliação - Presencial | J97: Juizado Especial Cível | K97: São João - PR | U97: =Table_4[[#This Row],[VALOR]]-Table_4[[#This Row],[ CUSTO]] -> 0
U98: =Table_4[[#This Row],[VALOR]]-Table_4[[#This Row],[ CUSTO]] -> 0
U99: =Table_4[[#This Row],[VALOR]]-Table_4[[#This Row],[ CUSTO]] -> 0
U100: =Table_4[[#This Row],[VALOR]]-Table_4[[#This Row],[ CUSTO]] -> 0
U101: =Table_4[[#This Row],[VALOR]]-Table_4[[#This Row],[ CUSTO]] -> 0
U102: =Table_4[[#This Row],[VALOR]]-Table_4[[#This Row],[ CUSTO]] -> 0
...

Sheet ABRIL
B2: CONTROLE DE DILIGÊNCIAS
B4: SOLICITAÇÃO | C4: Nº. DOC9 | D4: SOLICITANTE | E4: TEL. | F4: TIPO DE DILIGÊNCIA | G4: Processo | H4: DATA | I4: HORA | J4: LOCAL | K4: Cidade - UF | L4: VALOR | M4: DATA PAG | N4: PAGAM. | O4: CONTRATADO | P4: TEL. 2 | Q4: CUSTO | R4: PRAZO | S4: PAGO | T4: STATUS | U4: LUCRO
B5: 45729 | D5: Andre Oliveira | E5: 19 98127-4386 | F5: Audiência | H5: 45748 | I5: 0.63194444 | J5: 3ª Vara do Trabalho | K5: Santos - SP | L5: 300 | M5: ok | N5: CUMPRIDO | O5: IRB - Isabelle | P5: 13 98804-4390 | Q5: 130 | S5: SIM | T5: CUMPRIDO | U5: =Table_5[[#This Row],[VALOR]]-Table_5[[#This Row],[ CUSTO]] -> 170
B6: 45730 | D6: Marcos Piva | E6: 11 96608-7561 | F6: Audiência | H6: 45748 | I6: 0.38194444 | J6: 6ª Vara do Trabalho | K6: Santos - SP | L6: 300 | M6: ok | N6: CUMPRIDO | O6: IRB - Isabelle | P6: 13 98804-4390 | Q6: 130 | S6: SIM | T6: CUMPRIDO | U6: =Table_5[[#This Row],[VALOR]]-Table_5[[#This Row],[ CUSTO]] -> 170
B7: 45740 | D7: LACOSTA ADVOGADOS | E7: 21 95922-4000 / 11 91039-6920 | F7: Advogado | H7: 45748 | I7: 0.41666667 | J7: 79ª Vara do Trabalho da Barra Funda | K7: São Paulo - SP | L7: 150 | M7: ok | N7: CUMPRIDO | O7: Laura Mautone | P7: 11 99305-2938 | Q7: 70 | R7: ok | S7: SIM | T7: CUMPRIDO | U7: =Table_5[[#This Row],[VALOR]]-Table_5[[#This Row],[ CUSTO]] -> 80
B8: 45741 | D8: Grace Bordalo | E8: 16 98822-1551 | F8: Sustentação Oral | H8: 45748 | J8: STJ | K8: Virtual | L8: 800 | N8: CUMPRIDO | O8: Patrícia Aparecida Carneiro | P8: 11 98265-6766 | Q8: 400 | R8: ok | S8: SIM | T8: CUMPRIDO | U8: =Table_5[[#This Row],[VALOR]]-Table_5[[#This Row],[ CUSTO]] -> 400
B9: 45742 | D9: Jessica | E9: 41 9685-0539 | F9: Coleta de Assinaturas | G9: JOSE VIANA LIMA | H9: 45748 | I9: 0.45833333 | J9: Filial da Barra Funda | K9: São Paulo - SP | L9: 300 | M9: ok | N9: CUMPRIDO | O9: Lucas Dias Soares | P9: 11 98307-6405 | Q9: 60 | R9: ok | S9: SIM | T9: CUMPRIDO | U9: =Table_5[[#This Row],[VALOR]]-Table_5[[#This Row],[ CUSTO]] -> 240
B10: 45743 | D10: Salem Advogados | E10: 11 95605-9699 | F10: Inicial - Virtual | G10: 0011900-98.2024.5.15.0097 | H10: 45748 | I10: 0.56944444 | J10: 4ª Vara do Trabalho | K10: Jundiaí - SP | N10: CUMPRIDO | O10: Joao Tomaz da Silva | P10: 11 97377-8980 | Q10: 40 | R10: ok | S10: SIM | T10: CUMPRIDO | U10: =Table_5[[#This Row],[VALOR]]-Table_5[[#This Row],[ CUSTO]] -> -40
B11: 45744 | D11: Fett Advogados Bruna Ferracini | E11: 51 9184-8885 | F11: Instrução - Presencial | G11: 0000611-69.2024.5.12.0060 | H11: 45748 | I11: 0.63541667 | J11: 3ª Vara do Trabalho | K11: Lages - SC | L11: 300 | N11: CUMPRIDO | O11: Andréa Cristina da Rosa | P11: 49 8812-6119 | Q11: 230 | R11: ok | S11: SIM | T11: CUMPRIDO | U11: =Table_5[[#This Row],[VALOR]]-Table_5[[#This Row],[ CUSTO]] -> 70
B12: 45747 | D12: Marcos Piva | E12: 11 96608-7561 | F12: Audiência | H12: 45748 | I12: 0.34375 | J12: 43ª Vara do Trabalho da Barra Funda | K12: São Paulo - SP | L12: 150 | M12: ok | N12: CUMPRIDO | O12: Amanda Rodrigues | P12: 11 95960-2876 | Q12: 50 | S12: SIM | T12: CUMPRIDO | U12: =Table_5[[#This Row],[VALOR]]-Table_5[[#This Row],[ CUSTO]] -> 100
B13: 45747 | D13: Cristiano Aparecido | E13: 11 98519-3150 | F13: Audiência | H13: 45748 | I13: 0.48958333 | J13: Trabalho da Zona Sul | K13: São Paulo - SP | L13: 120 | N13: CUMPRIDO | O13: Larissa Queiroz | P13: 11 91477-2823 | Q13: 70 | R13: desv | S13: SIM | T13: CUMPRIDO | U13: =Table_5[[#This Row],[VALOR]]-Table_5[[#This Row],[ CUSTO]] -> 50
B14: 45748 | D14: Rodrigo Bezerra | E14: 11 99360-4364 | F14: Audiência | H14: 45748 | I14: 0.66666667 | J14: Vara Federal | K14: São Paulo - SP | L14: 150 | N14: CUMPRIDO | O14: Ivo Rodrigues da Silva | P14: 11 98904-9114 | Q14: 70 | R14: ok | S14: SIM | T14: CUMPRIDO | U14: =Table_5[[#This Row],[VALOR]]-Table_5[[#This Row],[ CUSTO]] -> 80
B15: 45740 | D15: LACOSTA ADVOGADOS | E15: 21 95922-4000 / 11 91039-6920 | F15: Advogado | H15: 45749 | I15: 0.35763889 | J15: Vara do Trabalho | K15: Caçapava - SP | L15: 150 | M15: ok | N15: CUMPRIDO | O15: Keroleyni Rabello de Moura | P15: 12 99687-7381 | Q15: 70 | S15: SIM | T15: CUMPRIDO | U15: =Table_5[[#This Row],[VALOR]]-Table_5[[#This Row],[ CUSTO]] -> 80
B16: 45744 | D16: Fett Advogados Bruna Ferracini | E16: 51 9184-8885 | F16: UNA Presencial | G16: 0021601-41.2024.5.04.0404 | H16: 45749 | I16: 0.60416667 | J16: 4ª Vara do Trabalho | K16: Caxias do Sul - RS | L16: 200 | N16: CUMPRIDO | O16: Aline Patrícia Leonarski de Jesus | P16: 54 9686-0227 | Q16: 100 | S16: SIM | T16: CUMPRIDO | U16: =Table_5[[#This Row],[VALOR]]-Table_5[[#This Row],[ CUSTO]] -> 100
B17: 45744 | D17: Fett Advogados Bruna Ferracini | E17: 51 9184-8885 | F17: UNA Presencial | G17: 0021746-64.2024.5.04.0512 | H17: 45749 | I17: 0.39583333 | J17: 2ª Vara do Trabalho | K17: Bento Gonçalves - RS | L17: 200 | N17: CUMPRIDO | O17: Carol Coelho Kern | P17: 54 9619-7803 | Q17: 100 | S17: SIM | T17: CUMPRIDO | U17: =Table_5[[#This Row],[VALOR]]-Table_5[[#This Row],[ CUSTO]] -> 100
B18: 45747 | D18: Thulyo Augustto | E18: 62 9683-9870 | F18: Instrução - Presencial | H18: 45749 | I18: 0.57638889 | J18: 11ª Vara do Trabalho | K18: Brasília - DF | L18: 250 | N18: CUMPRIDO | O18: Maria Nubia | P18: 61 8411-7957 | Q18: 70 | R18: desv | S18: SIM | T18: CUMPRIDO | U18: =Table_5[[#This Row],[VALOR]]-Table_5[[#This Row],[ CUSTO]] -> 180
B19: 45748 | D19: Jessica | E19: 41 9685-0539 | F19: Coleta de Assinaturas | G19: JOSE VIANA LIMA | H19: 45749 | I19: 0.33333333 | J19: Filial da Barra Funda | K19: São Paulo - SP | L19: =170+44.75 -> 214.75 | M19: ok | N19: CUMPRIDO | O19: Lucas Dias Soares | P19: 11 98307-6405 | Q19: =60+44.75 -> 104.75 | S19: SIM | T19: CUMPRIDO | U19: =Table_5[[#This Row],[VALOR]]-Table_5[[#This Row],[ CUSTO]] -> 110
B20: 45748 | D20: Thiago Coriolano | E20: 11 98775-8123 | F20: Audiência | H20: 45749 | I20: 0.41666667 | J20: Vara do Trabalho | K20: Atibaia - SP | L20: 250 | N20: CUMPRIDO | O20: Patricia Von Ah | P20: 19 99155-8565 | Q20: 100 | S20: SIM | T20: CUMPRIDO | U20: =Table_5[[#This Row],[VALOR]]-Table_5[[#This Row],[ CUSTO]] -> 150
B21: 45729 | D21: Andre Oliveira | E21: 19 98127-4386 | F21: Audiência | H21: 45750 | I21: 0.59027778 | J21: 4ª Vara do Trabalho | K21: Santo André - SP | N21: CUMPRIDO | O21: Elisangela ES - SOLUÇÕES JURÍDICAS | P21: 11 93067-5163 | Q21: 60 | S21: SIM | T21: CUMPRIDO | U21: =Table_5[[#This Row],[VALOR]]-Table_5[[#This Row],[ CUSTO]] -> -60
B22: 45729 | D22: Andre Oliveira | E22: 19 98127-4386 | F22: Audiência | H22: 45750 | I22: 0.59027778 | J22: 4ª Vara do Trabalho | K22: Santo André - SP | L22: 300 | N22: CUMPRIDO | O22: Joao Tomaz da Silva | P22: 11 97377-8980 | Q22: 70 | S22: SIM | T22: CUMPRIDO | U22: =Table_5[[#This Row],[VALOR]]-Table_5[[#This Row],[ CUSTO]] -> 230
B23: 45730 | D23: Marcos Piva | E23: 11 96608-7561 | F23: Audiência | H23: 45750 | I23: 0.58680556 | J23: 4ª Vara do Trabalho | K23: Santo André - SP | N23: CUMPRIDO | O23: Elisangela ES - SOLUÇÕES JURÍDICAS | P23: 11 93067-5163 | Q23: 60 | S23: SIM | T23: CUMPRIDO | U23: =Table_5[[#This Row],[VALOR]]-Table_5[[#This Row],[ CUSTO]] -> -60
B24: 45730 | D24: Marcos Piva | E24: 11 96608-7561 | F24: Audiência | H24: 45750 | I24: 0.58680556 | J24: 4ª Vara do Trabalho | K24: Santo André - SP | L24: 300 | N24: CUMPRIDO | O24: Joao Tomaz da Silva | P24: 11 97377-8980 | Q24: 70 | S24: SIM | T24: CUMPRIDO | U24: =Table_5[[#This Row],[VALOR]]-Table_5[[#This Row],[ CUSTO]] -> 230
B25: 45749 | D25: Jessica | E25: 41 9685-0539 | F25: Coleta de Assinaturas | G25: Manoel Sebastião | H25: 45750 | I25: 0.58333333 | J25: Sala da OAB | K25: Rolândia - PR | L25: =300+27 -> 327 | M25: ok | N25: CUMPRIDO | O25: Gabriel José Pereira de Souza | P25: 43 9636-6543 | Q25: =120+27 -> 147 | S25: SIM | T25: CUMPRIDO | U25: =Table_5[[#This Row],[VALOR]]-Table_5[[#This Row],[ CUSTO]] -> 180
B26: 45749 | D26: Jessica | E26: 41 9685-0539 | F26: Coleta de Assinaturas | G26: CLEUTON JOSE CAETANO | H26: 45750 | I26: 0.66666667 | J26: Rua do Petróleo N° 438, Bairro Centro | K26: Carolina - MA | L26: =500+121.5 -> 621.5 | M26: ok | N26: CUMPRIDO | O26: Gabriela Aranha Peres Rodrigues | P26: 99 8245-4625 | Q26: =150+121.5 -> 271.5 | S26: SIM | T26: CUMPRIDO | U26: =Table_5[[#This Row],[VALOR]]-Table_5[[#This Row],[ CUSTO]] -> 350
B27: 45743 | D27: Salem Advogados | E27: 11 95605-9699 | F27: UNA Presencial | G27: 1002493-27.2024.5.02.0610 | H27: 45751 | I27: 0.55555556 | J27: 10ª Vara do Trabalho da Zona Leste | K27: São Paulo - SP | L27: 150 | N27: CUMPRIDO | O27: Joao Tomaz da Silva | P27: 11 97377-8980 | Q27: 70 | S27: SIM | T27: CUMPRIDO | U27: =Table_5[[#This Row],[VALOR]]-Table_5[[#This Row],[ CUSTO]] -> 80
B28: 45751 | D28: LACOSTA ADVOGADOS | E28: 21 95922-4000 / 11 91039-6920 | F28: Advogado | H28: 45754 | I28: 0.625 | J28: 87ª Vara do Trabalho da Barra Funda | K28: São Paulo - SP | L28: 150 | N28: CUMPRIDO | O28: Amanda Pivott | P28: 11 94857-0549 | Q28: 70 | R28: 45792 | S28: SIM | T28: CUMPRIDO | U28: =Table_5[[#This Row],[VALOR]]-Table_5[[#This Row],[ CUSTO]] -> 80
B29: 45751 | D29: Thulyo Augustto | E29: 62 9683-9870 | F29: Instrução - Presencial | G29: 0000087-39.2025.5.08.0128 | H29: 45754 | I29: 0.35416667 | J29: 3ª Vara do Trabalho | K29: Marabá - PA | L29: 350 | N29: CUMPRIDO | O29: Cinthia Veloso | P29: 94 9233-5899 | Q29: 150 | S29: SIM | T29: CUMPRIDO | U29: =Table_5[[#This Row],[VALOR]]-Table_5[[#This Row],[ CUSTO]] -> 200
B30: 45751 | D30: Beatriz Aragão & Bernardo | E30: 85 3252-2939 - 85 8405-1478 | F30: Audiência | G30: 0000145-53.2025.5.05.0022 | H30: 45754 | I30: 0.37847222 | J30: 22ª Vara do Trabalho | K30: Salvador - BA | L30: 170 | N30: CUMPRIDO | O30: Isadora Lopes Onofre | P30: 71 8392-7455 | Q30: 70 | S30: SIM | T30: CUMPRIDO | U30: =Table_5[[#This Row],[VALOR]]-Table_5[[#This Row],[ CUSTO]] -> 100
B31: 45751 | D31: Beatriz Aragão & Bernardo | E31: 85 3252-2939 - 85 8405-1478 | F31: Audiência | G31: 0002484-89.2024.5.09.0092 | H31: 45754 | I31: 0.59722222 | J31: Vara do Trabalho | K31: Cianorte - PR | L31: 200 | N31: CUMPRIDO | O31: KAREN DA SILVA BELTRAME | P31: 44 9937-9842 | Q31: 100 | S31: SIM | T31: CUMPRIDO | U31: =Table_5[[#This Row],[VALOR]]-Table_5[[#This Row],[ CUSTO]] -> 100
B32: 45751 | D32: Jessica | E32: 41 9685-0539 | F32: Cópia | G32: 0001968-74.2003.4.05.8410 | H32: 45754 | I32: 0.5 | J32: 7ª Vara do JEF | K32: Natal - RN | L32: 300 | M32: ok | N32: CUMPRIDO | O32: Maria Luiza | P32: 84 9841-2493 | Q32: 40 | R32: desv | S32: SIM | T32: CUMPRIDO | U32: =Table_5[[#This Row],[VALOR]]-Table_5[[#This Row],[ CUSTO]] -> 260
B33: 45754 | D33: LACOSTA ADVOGADOS | E33: 21 95922-4000 / 11 91039-6920 | F33: Preposto | H33: 45754 | I33: 0.625 | J33: 87ª Vara do Trabalho da Barra Funda | K33: São Paulo - SP | L33: 120 | N33: CUMPRIDO | O33: Nizael De Oliveira | P33: 11 98714-8872 | Q33: 40 | S33: SIM | T33: CUMPRIDO | U33: =Table_5[[#This Row],[VALOR]]-Table_5[[#This Row],[ CUSTO]] -> 80
B34: 45730 | D34: Marcos Piva | E34: 11 96608-7561 | F34: Audiência | G34: 1000224-14.2025.5.02.0502 | H34: 45755 | I34: 0.44791667 | J34: 2ª Vara do Trabalho | K34: Taboão da Serra - SP | L34: 300 | M34: ok | N34: CUMPRIDO | O34: Elisangela ES - SOLUÇÕES JURÍDICAS | P34: 11 93067-5163 | Q34: 150 | S34: SIM | T34: CUMPRIDO | U34: =Table_5[[#This Row],[VALOR]]-Table_5[[#This Row],[ CUSTO]] -> 150
B35: 45742 | D35: Murilo Máximo | E35: 11 98224-3603 | F35: Instrução - Presencial | H35: 45755 | I35: 0.35416667 | J35: 1ª Vara do Trabalho | K35: Euclides da Cunha - BA | L35: 300 | N35: CUMPRIDO | O35: Renata Lima | P35: 71 9979-5567 | Q35: 150 | S35: SIM | T35: CUMPRIDO | U35: =Table_5[[#This Row],[VALOR]]-Table_5[[#This Row],[ CUSTO]] -> 150
B36: 45749 | D36: Eliana | E36: 11 99955-0733 | F36: Sustentação Oral | G36: 1028588-34.2023.8.26.0506 | H36: 45755 | I36: 0.58333333 | J36: 10ª Câmara Direito Privado | K36: São Paulo - SP | L36: 800 | N36: CUMPRIDO | O36: Patrícia Aparecida Carneiro | P36: 11 98265-6766 | Q36: 300 | S36: SIM | T36: CUMPRIDO | U36: =Table_5[[#This Row],[VALOR]]-Table_5[[#This Row],[ CUSTO]] -> 500
B37: 45751 | D37: Jessica | E37: 41 9685-0539 | F37: Coleta de Assinaturas | G37: JOAO TADEU VITAL | H37: 45755 | I37: 0.4375 | J37: Filial da Barra Funda | K37: São Paulo - SP | L37: =300+36.8 -> 336.8 | M37: ok | N37: CUMPRIDO | O37: Arlindo Felipe Jr | P37: 11 99635-2611 | Q37: =50+36.8 -> 86.8 | S37: SIM | T37: CUMPRIDO | U37: =Table_5[[#This Row],[VALOR]]-Table_5[[#This Row],[ CUSTO]] -> 250
B38: 45751 | D38: Sepulveda Advogados Associados | E38: 19 99651-8840 | F38: Acompanhamento de perícia | H38: 45755 | I38: 0.35416667 | J38: RUA MARECHAL RONDON, 1768, PEDREGULHO | K38: Salto - SP | L38: 150 | N38: CUMPRIDO | O38: Larissa Domenice Nunes | P38: 11 99863-4716 | Q38: 80 | S38: SIM | T38: CUMPRIDO | U38: =Table_5[[#This Row],[VALOR]]-Table_5[[#This Row],[ CUSTO]] -> 70
B39: 45740 | D39: LACOSTA ADVOGADOS | E39: 21 95922-4000 / 11 91039-6920 | F39: Advogado | H39: 45756 | I39: 0.36458333 | J39: 58ª Vara do Trabalho da Barra Funda | K39: São Paulo - SP | L39: 150 | N39: CUMPRIDO | O39: Joao Tomaz da Silva | P39: 11 97377-8980 | Q39: 70 | S39: SIM | T39: CUMPRIDO | U39: =Table_5[[#This Row],[VALOR]]-Table_5[[#This Row],[ CUSTO]] -> 80
B40: 45751 | D40: LACOSTA ADVOGADOS | E40: 21 95922-4000 / 11 91039-6920 | F40: Advogado | H40: 45756 | I40: 0.48958333 | J40: 1ª Vara do Trabalho | K40: Praia Grande - SP | L40: 150 | N40: CUMPRIDO | O40: IRB - Isabelle | P40: 13 98804-4390 | Q40: 130 | S40: SIM | T40: CUMPRIDO | U40: =Table_5[[#This Row],[VALOR]]-Table_5[[#This Row],[ CUSTO]] -> 20
B41: 45751 | D41: LACOSTA ADVOGADOS | E41: 21 95922-4000 / 11 91039-6920 | F41: Preposto | H41: 45756 | I41: 0.48958333 | J41: 1ª Vara do Trabalho | K41: Praia Grande - SP | L41: 130 | N41: CUMPRIDO | O41: IRB - Isabelle | P41: 13 98804-4390 | S41: SIM | T41: CUMPRIDO | U41: =Table_5[[#This Row],[VALOR]]-Table_5[[#This Row],[ CUSTO]] -> 130
B42: 45751 | D42: Sepulveda Advogados Associados | E42: 19 99651-8840 | F42: Acompanhamento de perícia | H42: 45756 | I42: 0.39583333 | J42: SARNI & OLIVEIRA CARVALHO CLINICA ODONTOLOGICA LTDA - Avenida Inocêncio Seráfico, 4522, Vila Dirce | K42: Carapicuíba - SP | L42: 150 | N42: CUMPRIDO | O42: Selma Olegário | P42: 11 98180-2548 | Q42: 80 | S42: SIM | T42: CUMPRIDO | U42: =Table_5[[#This Row],[VALOR]]-Table_5[[#This Row],[ CUSTO]] -> 70
B43: 45755 | D43: Beatriz Aragão & Bernardo | E43: 85 3252-2939 - 85 8405-1478 | F43: Inicial - Presencial | G43: 0010026-93.2025.5.15.0113 | H43: 45756 | I43: 0.59027778 | J43: 5ª Vara do Trabalho | K43: Ribeirão Preto - SP | L43: 200 | N43: CUMPRIDO | O43: Mayara Belfort | P43: 16 99138-1367 | Q43: 60 | S43: SIM | T43: CUMPRIDO | U43: =Table_5[[#This Row],[VALOR]]-Table_5[[#This Row],[ CUSTO]] -> 140
B44: 45756 | D44: Jessica | E44: 41 9685-0539 | F44: Coleta de Assinaturas | G44: GILDETE DAS NEVES FERREIRA | H44: 45756 | I44: 0.58333333 | J44: Rua Mar Del Prata, 44-E - Coutos | K44: Salvador - BA | L44: =380+76.9 -> 456.9 | M44: ok | N44: CUMPRIDO | O44: Rodrigo Daniel | P44: 71 9914-4147 | Q44: =150+76.9 -> 226.9 | S44: SIM | T44: CUMPRIDO | U44: =Table_5[[#This Row],[VALOR]]-Table_5[[#This Row],[ CUSTO]] -> 230
B45: 45740 | D45: LACOSTA ADVOGADOS | E45: 21 95922-4000 / 11 91039-6920 | F45: Audiência | H45: 45757 | I45: 0.61111111 | J45: 9ª Vara do Trabalho da Barra Funda | K45: São Paulo - SP | L45: 150 | N45: CUMPRIDO | O45: Joao Tomaz da Silva | P45: 11 97377-8980 | Q45: 70 | S45: SIM | T45: CUMPRIDO | U45: =Table_5[[#This Row],[VALOR]]-Table_5[[#This Row],[ CUSTO]] -> 80
B46: 45743 | D46: Salem Advogados | E46: 11 95605-9699 | F46: Instrução - Presencial | G46: 1001430-73.2024.5.02.0025 | H46: 45757 | I46: 0.375 | J46: 25ª Vara do Trabalho da Barra Funda | K46: São Paulo - SP | L46: 150 | N46: CUMPRIDO | O46: Claudia | P46: 11 95000-1956 | Q46: 100 | S46: SIM | T46: CUMPRIDO | U46: =Table_5[[#This Row],[VALOR]]-Table_5[[#This Row],[ CUSTO]] -> 50
B47: 45757 | D47: Adriana Arruda | E47: 19 97128-1295 | F47: Cópias | G47: EPT-1500-501225/2020 | H47: 45758 | I47: 0.5 | J47: SEFAZ | K47: Maceió - AL | L47: 200 | N47: CUMPRIDO | O47: Cláudio Felipe da Silva Alves | P47: 82 9973-6492 | Q47: 70 | S47: SIM | T47: CUMPRIDO | U47: =Table_5[[#This Row],[VALOR]]-Table_5[[#This Row],[ CUSTO]] -> 130
B48: 45758 | D48: Jessica | E48: 41 9685-0539 | F48: Coleta de Assinaturas | G48: HIROSHI MAEKAWA | H48: 45758 | I48: 0.58333333 | J48: Rua Caiçara, 314, bairro Piratininga | K48: Campo Grande - MS | L48: =300+51.4 -> 351.4 | M48: ok | N48: CUMPRIDO | O48: Paloma da Silva Coimbra | P48: 67 9645-7076 | Q48: =80+51.4 -> 131.4 | S48: SIM | T48: CUMPRIDO | U48: =Table_5[[#This Row],[VALOR]]-Table_5[[#This Row],[ CUSTO]] -> 220
B49: 45748 | D49: Lucas Mançano | E49: 61 9143-8757 | F49: UNA Presencial | G49: 0001617-64.2024.5.13.0002 | H49: 45761 | I49: 0.52083333 | J49: 2ª Vara do Trabalho | K49: João Pessoa - PE | L49: 250 | N49: CUMPRIDO | O49: Adriana Augusta Pereira Franco | P49: 83 9964-9318 | Q49: 80 | R49: desv | S49: SIM | T49: CUMPRIDO | U49: =Table_5[[#This Row],[VALOR]]-Table_5[[#This Row],[ CUSTO]] -> 170
B50: 45757 | D50: Beatriz Aragão & Bernardo | E50: 85 3252-2939 - 85 8405-1478 | F50: UNA Presencial | G50: 1000376-78.2025.5.02.0044 | H50: 45761 | I50: 0.375 | J50: 44ª Vara do Trabalho da Barra Funda | K50: São Paulo - SP | L50: 170 | N50: CUMPRIDO | O50: Amanda Pivott | P50: 11 94857-0549 | Q50: 70 | R50: 45792 | S50: SIM | T50: CUMPRIDO | U50: =Table_5[[#This Row],[VALOR]]-Table_5[[#This Row],[ CUSTO]] -> 100
B51: 45757 | D51: Beatriz Aragão & Bernardo | E51: 85 3252-2939 - 85 8405-1478 | F51: UNA Presencial | G51: 0001558-56.2024.5.06.0201 | H51: 45761 | I51: 0.40625 | J51: Vara do Trabalho | K51: Vitória de Santo Antão - PE | L51: 200 | N51: CUMPRIDO | O51: Júlio César Oliveira Lopes | P51: 81 9482-0008 | Q51: 70 | R51: desv | S51: SIM | T51: CUMPRIDO | U51: =Table_5[[#This Row],[VALOR]]-Table_5[[#This Row],[ CUSTO]] -> 130
B52: 45757 | D52: Beatriz Aragão & Bernardo | E52: 85 3252-2939 - 85 8405-1478 | F52: UNA Presencial | G52: 0002485-74.2024.5.09.0092 | H52: 45761 | I52: 0.58333333 | J52: Vara do Trabalho | K52: Cianorte - PR | L52: 170 | N52: CUMPRIDO | O52: KAREN DA SILVA BELTRAME | P52: 44 9937-9842 | Q52: 70 | S52: SIM | T52: CUMPRIDO | U52: =Table_5[[#This Row],[VALOR]]-Table_5[[#This Row],[ CUSTO]] -> 100
B53: 45758 | D53: Andre Oliveira | E53: 19 98127-4386 | F53: UNA Presencial | G53: 1000438-30.2025.5.02.0041 | H53: 45761 | I53: 0.67708333 | J53: 41ª Vara do Trabalho da Barra Funda | K53: São Paulo - SP | L53: 200 | M53: ok | N53: CUMPRIDO | O53: Joao Tomaz da Silva | P53: 11 97377-8980 | Q53: 70 | S53: SIM | T53: CUMPRIDO | U53: =Table_5[[#This Row],[VALOR]]-Table_5[[#This Row],[ CUSTO]] -> 130
B54: 45761 | D54: Camilla - Luan | E54: 45 9814-5796 | F54: Conciliação - Presencial | G54: 1003910-96.2025.8.26.0016 | H54: 45761 | I54: 0.6875 | J54: 1º JEC da Vergueiro | K54: São Paulo - SP | L54: 120 | N54: CUMPRIDO | O54: Naiara Santos Nascimento | P54: 11 97123-1691 | Q54: 50 | S54: SIM | T54: CUMPRIDO | U54: =Table_5[[#This Row],[VALOR]]-Table_5[[#This Row],[ CUSTO]] -> 70
B55: 45751 | D55: Josiane - Luan | E55: 45 9979-5193 | F55: Conciliação - Presencial | H55: 45762 | I55: 0.63541667 | J55: 14º Juizado Especial Cível de Jacarepaguá | K55: Rio de Janeiro - RJ | L55: 120 | N55: CUMPRIDO | O55: Mateus Nepomuceno Guedes | P55: 21 99453-9048 | Q55: 50 | R55: desv | S55: SIM | T55: CUMPRIDO | U55: =Table_5[[#This Row],[VALOR]]-Table_5[[#This Row],[ CUSTO]] -> 70
B56: 45756 | D56: Vivian Barbosa / Raquel Moreira | E56: 11 94569-1656 / 11 98450-5051 | F56: Instrução - Presencial | G56: 0010192-11.2025.5.15.0054 | H56: 45762 | I56: 0.4375 | J56: 1ª Vara do Trabalho | K56: Sertãozinho - SP | L56: 500 | N56: CUMPRIDO | O56: Débora Carolina Ferreira | P56: 16 99212-2775 | Q56: 120 | S56: SIM | T56: CUMPRIDO | U56: =Table_5[[#This Row],[VALOR]]-Table_5[[#This Row],[ CUSTO]] -> 380
B57: 45762 | D57: Jessica | E57: 41 9685-0539 | F57: Coleta de Assinaturas | G57: JANDIRA DE SOUZA NASCIEMENTO | H57: 45763 | I57: 0.41666667 | J57: Filial da Barra Funda | K57: São Paulo - SP | L57: =300+40.4 -> 340.4 | N57: CUMPRIDO | O57: Arlindo Felipe Jr | P57: 11 99635-2611 | Q57: =50+40.4 -> 90.4 | S57: SIM | T57: CUMPRIDO | U57: =Table_5[[#This Row],[VALOR]]-Table_5[[#This Row],[ CUSTO]] -> 250
B58: 45763 | D58: Jessica | E58: 41 9685-0539 | F58: Coleta de Assinaturas | G58: Maria de Lourdes | H58: 45763 | I58: 0.58333333 | J58: Rua Pedro Francisco de Castro nr/122 centro | K58: Conde - BA | L58: =500+123.84 -> 623.84 | N58: CUMPRIDO | O58: Lúcio Mauro Amorim dos Santos | P58: 75 9199-2245 | Q58: =150+123.84 -> 273.84 | S58: SIM | T58: CUMPRIDO | U58: =Table_5[[#This Row],[VALOR]]-Table_5[[#This Row],[ CUSTO]] -> 350
B59: 45761 | D59: Jessica | E59: 41 9685-0539 | F59: Coleta de Assinaturas | G59: OLIVEIRA ARAUJO LIMA | H59: 45764 | I59: 0.33333333 | J59: Filial da Barra Funda | K59: São Paulo - SP | L59: =300+40.4 -> 340.4 | N59: CUMPRIDO | O59: Arlindo Felipe Jr | P59: 11 99635-2611 | Q59: =50+40.4 -> 90.4 | S59: SIM | T59: CUMPRIDO | U59: =Table_5[[#This Row],[VALOR]]-Table_5[[#This Row],[ CUSTO]] -> 250
B60: 45761 | D60: Jessica | E60: 41 9685-0539 | F60: Coleta de Assinaturas | G60: RAIMUNDO RODRIGUES | H60: 45764 | I60: 0.5 | J60: Rua Mexico, 31, sala 703, Centro | K60: Rio de Janeiro - RJ | L60: 300 | N60: CUMPRIDO | O60: Oswaldo Assumpção Jr | P60: 21 99672-1599 | Q60: 60 | S60: SIM | T60: CUMPRIDO | U60: =Table_5[[#This Row],[VALOR]]-Table_5[[#This Row],[ CUSTO]] -> 240
B61: 45762 | D61: Jessica | E61: 41 9685-0539 | F61: Coleta de Assinaturas | G61: Cliente Bento Ambrosio | H61: 45764 | I61: 0.375 | J61: Av. Dom Luís, 807 – 20º e 21º andar, Meireles | K61: Fortaleza - CE | L61: =300+100.5+5 -> 405.5 | N61: CUMPRIDO | O61: Gabriela Sousa | P61: 85 8640-0693 | Q61: =80+100.5+5 -> 185.5 | S61: SIM | T61: CUMPRIDO | U61: =Table_5[[#This Row],[VALOR]]-Table_5[[#This Row],[ CUSTO]] -> 220
B62: 45762 | D62: Jessica | E62: 41 9685-0539 | F62: Coleta de Assinaturas | G62: Manoel Pedroza Ramada | H62: 45764 | I62: 0.54166667 | J62: Rua Mexico, 31, sala 703, Centro | K62: Rio de Janeiro - RJ | L62: =300+41.6 -> 341.6 | N62: CUMPRIDO | O62: Oswaldo Assumpção Jr | P62: 21 99672-1599 | Q62: =40+41.6 -> 81.6 | S62: SIM | T62: CUMPRIDO | U62: =Table_5[[#This Row],[VALOR]]-Table_5[[#This Row],[ CUSTO]] -> 260
B63: 45762 | D63: Jessica | E63: 41 9685-0539 | F63: Coleta de Assinaturas | G63: VALDIR EVANGELISTA DE SANTANA | H63: 45764 | I63: 0.41666667 | J63: Rua Ewerton Visco, N°290, sala 1901, Edif. Boulevard Side Empresarial, Caminho das Árvores | K63: Salvador - BA | L63: =300+84.9 -> 384.9 | N63: CUMPRIDO | O63: Rodrigo Daniel | P63: 71 9914-4147 | Q63: =60+84.9 -> 144.9 | S63: SIM | T63: CUMPRIDO | U63: =Table_5[[#This Row],[VALOR]]-Table_5[[#This Row],[ CUSTO]] -> 240
B64: 45764 | D64: Jessica Nunes | E64: 351 936 331 691 | F64: Certidão de Cartório | G64: Marcia Tiemi da Silva Matsumoto | H64: 45764 | J64: 9º Oficio de Registro Civil das Pessoas Naturais | K64: Campo Grande - MS | L64: =250+95.39 -> 345.39 | N64: CUMPRIDO | O64: Paloma Coimbra | P64: 67 9645-7076 | Q64: =95.39 -> 95.39 | S64: SIM | T64: CUMPRIDO | U64: =Table_5[[#This Row],[VALOR]]-Table_5[[#This Row],[ CUSTO]] -> 250
B65: 45764 | D65: Jessica Nunes | E65: 351 936 331 691 | F65: Certidão de Cartório | G65: Paulo Isac da Silva Pereira | H65: 45764 | J65: Cartório de Registro Civil de Pessoas Naturais | K65: Ribeirão das Neves | L65: =382.8 -> 382.8 | N65: CUMPRIDO | Q65: 52.8 | S65: SIM | T65: CUMPRIDO | U65: =Table_5[[#This Row],[VALOR]]-Table_5[[#This Row],[ CUSTO]] -> 330
B66: 45730 | D66: Marcos Piva | E66: 11 96608-7561 | F66: UNA Presencial | G66: 1000309-07.2025.5.02.0435 | H66: 45769 | I66: 0.45138889 | J66: 5ª Vara do Trabalho | K66: Santo André - SP | L66: 300 | M66: ok | N66: CUMPRIDO | O66: Elisangela ES - SOLUÇÕES JURÍDICAS | P66: 11 93067-5163 | Q66: 150 | R66: ok | S66: SIM | T66: CUMPRIDO | U66: =Table_5[[#This Row],[VALOR]]-Table_5[[#This Row],[ CUSTO]] -> 150
B67: 45740 | D67: LACOSTA ADVOGADOS | E67: 21 95922-4000 / 11 91039-6920 | F67: Audiência | H67: 45769 | I67: 0.35416667 | J67: Vara do Trabalho | K67: Caçapava - SP | L67: 200 | N67: CUMPRIDO | O67: Keroleyni Rabello de Moura | P67: 12 99687-7381 | Q67: 70 | S67: SIM | T67: CUMPRIDO | U67: =Table_5[[#This Row],[VALOR]]-Table_5[[#This Row],[ CUSTO]] -> 130
B68: 45758 | D68: Amanda Betanin - Luan | E68: 45 9814-7028 | F68: Conciliação - Presencial | G68: 1000944-87.2025.8.26.0008 | H68: 45769 | I68: 0.5625 | J68: 1ª Vara do Juizado Especial Cível de Tatuapé | K68: São Paulo - SP | L68: 120 | N68: CUMPRIDO | O68: Joao Tomaz da Silva | P68: 11 97377-8980 | Q68: 50 | S68: SIM | T68: CUMPRIDO | U68: =Table_5[[#This Row],[VALOR]]-Table_5[[#This Row],[ CUSTO]] -> 70
B69: 45762 | D69: Marcos Piva | E69: 11 96608-7561 | F69: UNA Presencial | G69: 1000184-46.202.5.02.0465 | H69: 45769 | I69: 0.39583333 | J69: 5ª Vara do Trabalho | K69: São Bernardo do Campo - SP | L69: 300 | M69: ok | N69: CUMPRIDO | O69: Elisangela ES - SOLUÇÕES JURÍDICAS | P69: 11 93067-5163 | Q69: 150 | R69: ok | S69: SIM | T69: CUMPRIDO | U69: =Table_5[[#This Row],[VALOR]]-Table_5[[#This Row],[ CUSTO]] -> 150
B70: 45764 | D70: Jessica | E70: 41 9685-0539 | F70: Coleta de Assinaturas | H70: 45769 | I70: 0.45833333 | J70: Filial da Barra Funda | K70: São Paulo - SP | L70: 300 | N70: CUMPRIDO | O70: Arlindo Felipe Jr | P70: 11 99635-2611 | Q70: 50 | S70: SIM | T70: CUMPRIDO | U70: =Table_5[[#This Row],[VALOR]]-Table_5[[#This Row],[ CUSTO]] -> 250
B71: 45764 | D71: Fett Advogados Bruna Ferracini | E71: 51 9184-8885 | F71: Instrução - Presencial | G71: 0020596-48.2024.5.04.0124 | H71: 45769 | I71: 0.40972222 | J71: 4ª Vara do Trabalho | K71: Rio Grande - RS | L71: 200 | N71: CUMPRIDO | O71: Juliana Couto | P71: 53 8106-9910 | Q71: 70 | S71: SIM | T71: CUMPRIDO | U71: =Table_5[[#This Row],[VALOR]]-Table_5[[#This Row],[ CUSTO]] -> 130
B72: 45766 | D72: João Lucas | E72: 11 97302-8126 | F72: Instrução - Presencial | G72: 0010972-27.2023.5.15.0116 | H72: 45769 | I72: 0.41666667 | J72: Vara do Trabalho | K72: Tatuí - SP | L72: 400 | N72: CUMPRIDO | O72: Mariana Campos | P72: 19 99153-6952 | Q72: 300 | S72: SIM | T72: CUMPRIDO | U72: =Table_5[[#This Row],[VALOR]]-Table_5[[#This Row],[ CUSTO]] -> 100
B73: 45769 | D73: Rodrigo Bezerra | E73: 11 99360-4364 | F73: Audiência | H73: 45769 | I73: 0.72222222 | J73: Virtual | K73: Santa Catarina | L73: 200 | N73: CUMPRIDO | O73: Gabriela Machado Soares | P73: 53 9139-9707 | Q73: 100 | S73: SIM | T73: CUMPRIDO | U73: =Table_5[[#This Row],[VALOR]]-Table_5[[#This Row],[ CUSTO]] -> 100
B74: 45769 | D74: Jessica | E74: 41 9685-0539 | F74: Coleta de Assinaturas | G74: RAIMUNDO VIEIRA DE MELO | H74: 45769 | I74: 0.66666667 | J74: Rua Gênero de Oliveira, 1356, Lagoa Seca | K74: Juazeiro do Norte - CE | L74: =300+133.3+4 -> 437.3 | N74: CUMPRIDO | O74: Thalysson Gabriel | P74: 88 9650-3686 | Q74: =50+133.3+4 -> 187.3 | S74: SIM | T74: CUMPRIDO | U74: =Table_5[[#This Row],[VALOR]]-Table_5[[#This Row],[ CUSTO]] -> 250
B75: 45763 | D75: Beatriz Aragão & Bernardo | E75: 85 3252-2939 - 85 8405-1478 | F75: UNA Presencial | G75: 1000277-28.2025.5.02.0491 | H75: 45770 | I75: 0.38541667 | J75: 1ª Vara do Trabalho | K75: Suzano - SP | L75: 200 | N75: CUMPRIDO | O75: Fernando Santos | P75: 11 98307-2224 | Q75: 70 | S75: SIM | T75: CUMPRIDO | U75: =Table_5[[#This Row],[VALOR]]-Table_5[[#This Row],[ CUSTO]] -> 130
B76: 45763 | D76: Andre Oliveira | E76: 19 98127-4386 | F76: UNA Presencial | G76: 1000154-65.2025.5.02.0447 | H76: 45770 | I76: 0.55555556 | J76: 7ª Vara do Trabalho | K76: Santos - SP | L76: 300 | M76: ok | N76: CUMPRIDO | O76: IRB - Isabelle | P76: 13 98804-4390 | Q76: 130 | S76: SIM | T76: CUMPRIDO | U76: =Table_5[[#This Row],[VALOR]]-Table_5[[#This Row],[ CUSTO]] -> 170
B77: 45764 | D77: Laís Duarte | E77: 34 8864-3914 | F77: Instrução - Presencial | H77: 45770 | I77: 0.58333333 | J77: 5ª Vara do Trabalho | K77: Ribeirão Preto - SP | L77: 250 | N77: CUMPRIDO | O77: Mayara Belfort | P77: 16 99138-1367 | Q77: 70 | S77: SIM | T77: CUMPRIDO | U77: =Table_5[[#This Row],[VALOR]]-Table_5[[#This Row],[ CUSTO]] -> 180
B78: 45766 | D78: João Lucas | E78: 11 97302-8126 | F78: Instrução - Presencial | H78: 45770 | I78: 0.4375 | J78: Vara do Trabalho | K78: Tatuí - SP | L78: 400 | N78: CUMPRIDO | O78: Mariana Campos | P78: 19 99153-6952 | Q78: 280 | S78: SIM | T78: CUMPRIDO | U78: =Table_5[[#This Row],[VALOR]]-Table_5[[#This Row],[ CUSTO]] -> 120
B79: 45766 | D79: João Lucas | E79: 11 97302-8126 | F79: Instrução - Presencial | H79: 45770 | I79: 0.39583333 | J79: Vara do Trabalho | K79: Tatuí - SP | L79: 400 | N79: CUMPRIDO | O79: Mariana Campos | P79: 19 99153-6952 | Q79: 300 | S79: SIM | T79: CUMPRIDO | U79: =Table_5[[#This Row],[VALOR]]-Table_5[[#This Row],[ CUSTO]] -> 100
B80: 45763 | D80: Beatriz Aragão & Bernardo | E80: 85 3252-2939 - 85 8405-1478 | F80: UNA Presencial | G80: 1000277-28.2025.5.02.0491 | H80: 45771 | I80: 0.375 | J80: 2ª Vara do Trabalho | K80: Aracaju - SE | L80: 170 | N80: CUMPRIDO | O80: Aryele Varjão | P80: 79 9110-5392 | Q80: 60 | S80: SIM | T80: CUMPRIDO | U80: =Table_5[[#This Row],[VALOR]]-Table_5[[#This Row],[ CUSTO]] -> 110
B81: 45769 | D81: Andre Oliveira | E81: 19 98127-4386 | F81: UNA Presencial | G81: 1000324-96.2025.5.02.0201 | H81: 45771 | I81: 0.58333333 | J81: 1ª Vara do Trabalho | K81: Barueri - SP | L81: 300 | M81: ok | N81: CUMPRIDO | O81: Elisangela ES - SOLUÇÕES JURÍDICAS | P81: 11 93067-5163 | Q81: 150 | S81: SIM | T81: CUMPRIDO | U81: =Table_5[[#This Row],[VALOR]]-Table_5[[#This Row],[ CUSTO]] -> 150
B82: 45769 | D82: Andre Oliveira | E82: 19 98127-4386 | F82: UNA Presencial | G82: 1000164-12.2025.5.02.0447 | H82: 45771 | I82: 0.40277778 | J82: 7ª Vara do Trabalho | K82: Santos - SP | L82: 300 | M82: ok | N82: CUMPRIDO | O82: IRB - Isabelle | P82: 13 98804-4390 | Q82: 130 | S82: SIM | T82: CUMPRIDO | U82: =Table_5[[#This Row],[VALOR]]-Table_5[[#This Row],[ CUSTO]] -> 170
B83: 45769 | D83: Rafaela - Policred e Prescred | E83: 11 96538-1745 | F83: Audiência Virtual | H83: 45771 | I83: 0.37847222 | J83: Virtual | K83: Bahia | L83: 250 | N83: CUMPRIDO | O83: Joao Tomaz da Silva | P83: 11 97377-8980 | Q83: 50 | S83: SIM | T83: CUMPRIDO | U83: =Table_5[[#This Row],[VALOR]]-Table_5[[#This Row],[ CUSTO]] -> 200
B84: 45770 | D84: Jessica | E84: 41 9685-0539 | F84: Coleta de Assinaturas | G84: JANDIRA DE SOUZA NASCIMENTO | H84: 45771 | I84: 0.54166667 | J84: Rua Professora Dina Rizzi, 587, JD Aurora, Zona Leste | K84: São Paulo - SP | L84: =300+40.4 -> 340.4 | N84: CUMPRIDO | O84: Diligência Própria | Q84: 40.4 | S84: SIM | T84: CUMPRIDO | U84: =Table_5[[#This Row],[VALOR]]-Table_5[[#This Row],[ CUSTO]] -> 300
B85: 45730 | D85: Marcos Piva | E85: 11 96608-7561 | F85: Audiência | G85: 1000195-38.2025.5.02.0445 | H85: 45772 | I85: 0.58680556 | J85: 5ª Vara do Trabalho | K85: Santos - SP | L85: 300 | M85: ok | N85: CUMPRIDO | O85: IRB - Isabelle | P85: 13 98804-4390 | Q85: 50 | S85: SIM | T85: CUMPRIDO | U85: =Table_5[[#This Row],[VALOR]]-Table_5[[#This Row],[ CUSTO]] -> 250
B86: 45772 | D86: Jessica | E86: 41 9685-0539 | F86: Coleta de Assinaturas | G86: ROGÉRIO LÚCIO DE FARIA | H86: 45772 | I86: 0.66666667 | J86: Rua Laercio Vieira, nº 106, Bairro: Expedicionários | K86: Resende Costa - MG | L86: =300+89.65 -> 389.65 | N86: CUMPRIDO | O86: Elton Resende Santos | P86: 32 9946-4567 | Q86: =45+89.65 -> 134.65 | S86: SIM | T86: CUMPRIDO | U86: =Table_5[[#This Row],[VALOR]]-Table_5[[#This Row],[ CUSTO]] -> 255
B87: 45772 | D87: Jessica | E87: 41 9685-0539 | F87: Coleta de Assinaturas | G87: RENATO JOSE DE FARIA | H87: 45773 | I87: 0.41666667 | J87: Rua Felipe Paulo Curi, nº 67, Bairro: Centro | K87: Barbacena - MG | L87: =400+84.5 -> 484.5 | N87: CUMPRIDO | O87: Daniela Nascimento | P87: 32 8516-9620 | Q87: =100+84.5 -> 184.5 | S87: SIM | T87: CUMPRIDO | U87: =Table_5[[#This Row],[VALOR]]-Table_5[[#This Row],[ CUSTO]] -> 300
B88: 45771 | D88: Danielle Peruzzo | E88: 11 99584-7776 | F88: Sustentação Oral | G88: 0011197-07.2022.5.03.0087 | H88: 45775 | I88: 0.58333333 | J88: TRT3 | K88: Belo Horizonte - MG | L88: 600 | N88: CUMPRIDO | O88: Danilo Freire | P88: 31 8358-4504 | Q88: 250 | S88: SIM | T88: CUMPRIDO | U88: =Table_5[[#This Row],[VALOR]]-Table_5[[#This Row],[ CUSTO]] -> 350
B89: 45771 | D89: Andre Oliveira | E89: 19 98127-4386 | F89: UNA Presencial | G89: 1000140-02.2025.5.02.0441 | H89: 45775 | I89: 0.59722222 | J89: 1ª Vara do Trabalho | K89: Santos - SP | L89: 300 | M89: ok | N89: CUMPRIDO | O89: IRB - Isabelle | P89: 13 98804-4390 | Q89: 130 | S89: SIM | T89: CUMPRIDO | U89: =Table_5[[#This Row],[VALOR]]-Table_5[[#This Row],[ CUSTO]] -> 170
B90: 45771 | D90: Andre Oliveira | E90: 19 98127-4386 | F90: UNA Presencial | G90: 1000428-28.2025.5.02.0027 | H90: 45775 | I90: 0.36805556 | J90: 27ª Vara do Trabalho da Barra Funda | K90: São Paulo - SP | L90: 200 | M90: ok | N90: CUMPRIDO | O90: Elisangela ES - SOLUÇÕES JURÍDICAS | P90: 11 93067-5163 | Q90: 90 | S90: SIM | T90: CUMPRIDO | U90: =Table_5[[#This Row],[VALOR]]-Table_5[[#This Row],[ CUSTO]] -> 110
B91: 45771 | D91: Mirlla - BCC Advocacia | E91: 61 9831-3480 | F91: Conciliação - Presencial | G91: 1018541-79.2024.8.26.0016 | H91: 45775 | I91: 0.69791667 | J91: 2ª Vara do JEC da Vergueiro | K91: São Paulo - SP | L91: 150 | N91: CUMPRIDO | O91: Joao Tomaz da Silva | P91: 11 97377-8980 | Q91: 60 | S91: SIM | T91: CUMPRIDO | U91: =Table_5[[#This Row],[VALOR]]-Table_5[[#This Row],[ CUSTO]] -> 90
B92: 45772 | D92: Marcos Piva | E92: 11 96608-7561 | F92: Audiência | G92: 1000195-38.2025.5.02.0445 | H92: 45775 | I92: 0.50347222 | J92: 5ª Vara do Trabalho | K92: Santos - SP | N92: CUMPRIDO | O92: IRB - Isabelle | P92: 13 98804-4390 | S92: SIM | T92: CUMPRIDO | U92: =Table_5[[#This Row],[VALOR]]-Table_5[[#This Row],[ CUSTO]] -> 0
B93: 45775 | D93: Thiago Coriolano | E93: 11 98775-8123 | F93: Instrução - Presencial | H93: 45775 | I93: 0.42361111 | J93: 5ª Vara do Trabalho | K93: São Bernardo do Campo - SP | L93: 200 | N93: CUMPRIDO | O93: Letícia dos Reis Messias | P93: 11 98309-0593 | Q93: 70 | S93: SIM | T93: CUMPRIDO | U93: =Table_5[[#This Row],[VALOR]]-Table_5[[#This Row],[ CUSTO]] -> 130
B94: 45775 | D94: Caio Casemiro | E94: 62 9226-9798 | F94: Conciliação - Presencial | G94: 0008631-46.2025.8.17.8201 | H94: 45775 | I94: 0.63194444 | J94: 9º JEC | K94: Recife - PE | L94: 150 | N94: CUMPRIDO | O94: Sara Lima | P94: 81 8275-9544 | Q94: 50 | S94: SIM | T94: CUMPRIDO | U94: =Table_5[[#This Row],[VALOR]]-Table_5[[#This Row],[ CUSTO]] -> 100
B95: 45763 | D95: LACOSTA ADVOGADOS | E95: 21 95922-4000 / 11 91039-6920 | F95: Audiência | H95: 45776 | I95: 0.4375 | J95: 29ª Vara do Trabalho da Barra Funda | K95: São Paulo - SP | L95: 150 | N95: CUMPRIDO | O95: Joao Tomaz da Silva | P95: 11 97377-8980 | Q95: 70 | S95: SIM | T95: CUMPRIDO | U95: =Table_5[[#This Row],[VALOR]]-Table_5[[#This Row],[ CUSTO]] -> 80
B96: 45771 | D96: Danielle Peruzzo | E96: 11 99584-7776 | F96: Sustentação Oral | G96: 0000638-22.2024.5.08.0106 | H96: 45776 | I96: 0.375 | J96: TRT8 | K96: Belém - PA | L96: 600 | N96: CUMPRIDO | O96: Ana Carolina | P96: 91 9305-0424 | Q96: 200 | S96: SIM | T96: CUMPRIDO | U96: =Table_5[[#This Row],[VALOR]]-Table_5[[#This Row],[ CUSTO]] -> 400
B97: 45771 | D97: Raissa - Concreserv | E97: 11 95107-8086 | F97: Conciliação - Presencial | H97: 45776 | I97: 0.60416667 | J97: 1ª Vara do Juizado Especial Cível de São Miguel Paulista | K97: São Paulo - SP | L97: 250 | N97: CUMPRIDO | O97: Andreza | P97: 11 98251-4885 | Q97: 100 | S97: SIM | T97: CUMPRIDO | U97: =Table_5[[#This Row],[VALOR]]-Table_5[[#This Row],[ CUSTO]] -> 150
B98: 45771 | D98: Jessica | E98: 41 9685-0539 | F98: Coleta de Assinaturas | G98: Josinaldo Bezerra da Costa | H98: 45776 | I98: 0.375 | J98: Rua Antônio Rabelo Júnior, nº 161, Sala 1711 1712, Miramar | K98: João Pessoa - PB | L98: =300+0.85+100.5 -> 401.35 | M98: ok | N98: CUMPRIDO | O98: Jairo de Oliveira | P98: 83 9367-7777 | Q98: =60+0.85+12+100.5 -> 173.35 | S98: SIM | T98: CUMPRIDO | U98: =Table_5[[#This Row],[VALOR]]-Table_5[[#This Row],[ CUSTO]] -> 228
B99: 45772 | D99: Fett Advogados Bruna Ferracini | E99: 51 9184-8885 | F99: UNA Presencial | G99: 0020318-52.2025.5.04.0402 | H99: 45776 | I99: 0.38194444 | J99: 2ª Vara do Trabalho | K99: Caxias do Sul - RS | L99: 200 | N99: CUMPRIDO | O99: Carol Coelho | P99: 54 9619-7803 | Q99: 100 | S99: SIM | T99: CUMPRIDO | U99: =Table_5[[#This Row],[VALOR]]-Table_5[[#This Row],[ CUSTO]] -> 100
B100: 45776 | D100: Jessica | E100: 41 9685-0539 | F100: Coleta de Assinaturas | G100: SORAIA DE MOURA VELOSO | H100: 45776 | I100: 0.54166667 | J100: Rua dos Inconfidentes, 911, 7° andar - Savassi | K100: Belo Horizonte - MG | L100: 300 | M100: ok | N100: CUMPRIDO | O100: Lucas Eduardo Gonçalves Toledo | P100: 21 99811-0071 | Q100: 50 | R100: desv | S100: SIM | T100: CUMPRIDO | U100: =Table_5[[#This Row],[VALOR]]-Table_5[[#This Row],[ CUSTO]] -> 250
B101: 45770 | D101: Maiara - Luan | E101: 45 9813-1519 | F101: Conciliação - Presencial | G101: 1004121-68.2025.8.26.0005 | H101: 45777 | I101: 0.48263889 | J101: 1ª Vara do Juizado Especial Cível - São Miguel Paulista | K101: São Paulo - SP | L101: 120 | N101: CUMPRIDO | O101: Andreza | P101: 11 98251-4885 | Q101: 60 | S101: SIM | T101: CUMPRIDO | U101: =Table_5[[#This Row],[VALOR]]-Table_5[[#This Row],[ CUSTO]] -> 60
B102: 45772 | D102: Beatriz Aragão & Bernardo | E102: 85 3252-2939 - 85 8405-1478 | F102: Audiência | G102: 0100314-71.2025.5.01.0018 | H102: 45777 | I102: 0.38541667 | J102: 18ª Vara do Trabalho | K102: Rio de Janeiro - RJ | L102: 170 | N102: CUMPRIDO | O102: Mayara Lahas | P102: 21 99474-4417 | Q102: 80 | S102: SIM | T102: CUMPRIDO | U102: =Table_5[[#This Row],[VALOR]]-Table_5[[#This Row],[ CUSTO]] -> 90
...

Sheet MAIO
B2: CONTROLE DE DILIGÊNCIAS
B4: SOLICITAÇÃO | C4: Nº. DOC9 | D4: SOLICITANTE | E4: TEL. | F4: TIPO DE DILIGÊNCIA | G4: Processo ou Cliente | H4: DATA | I4: HORA | J4: LOCAL | K4: Cidade - UF | L4: VALOR | M4: DATA PAG | N4: PAGAM. | O4: CONTRATADO | P4: TEL. 2 | Q4: CUSTO | R4: PRAZO | S4: PAGO | T4: STATUS | U4: LUCRO
B5: 45775 | D5: Andre Oliveira | E5: 19 98127-4386 | F5: UNA Presencial | G5: 1000311-43.2025.5.02.0025 | H5: 45782 | I5: 0.61111111 | J5: 25ª Vara do Trabalho da Barra Funda | K5: São Paulo - SP | L5: 200 | M5: ok | N5: CUMPRIDO | O5: Joao Tomaz da Silva | P5: 11 97377-8980 | Q5: 70 | S5: SIM | T5: CUMPRIDO | U5: =Table_516[[#This Row],[VALOR]]-Table_516[[#This Row],[ CUSTO]] -> 130
B6: 45775 | D6: Andre Oliveira | E6: 19 98127-4386 | F6: UNA Presencial | G6: 1000287-69.2025.5.02.0201 | H6: 45782 | I6: 0.63194444 | J6: 1ª Vara do Trabalho | K6: Barueri - SP | L6: 300 | M6: ok | N6: CUMPRIDO | O6: Camila Roncalle | P6: 11 98992-0599 | Q6: 130 | S6: SIM | T6: CUMPRIDO | U6: =Table_516[[#This Row],[VALOR]]-Table_516[[#This Row],[ CUSTO]] -> 170
B7: 45775 | D7: Thulyo Augustto | E7: 62 9683-9870 | F7: Audiência | G7: 0000793-29.2024.5.10.0022 | H7: 45782 | I7: 0.61111111 | J7: 22ª Vara do Trabalho | K7: Brasília - DF | L7: 250 | N7: CUMPRIDO | O7: Luana Amancio | P7: 61 8542-3080 | Q7: 100 | S7: SIM | T7: CUMPRIDO | U7: =Table_516[[#This Row],[VALOR]]-Table_516[[#This Row],[ CUSTO]] -> 150
B8: 45779 | D8: Beatriz Aragão & Bernardo | E8: 85 3252-2939 - 85 8405-1478 | F8: Audiência | G8: 0000243-33.2025.5.21.0009 | H8: 45782 | I8: 0.36458333 | J8: 9ª Vara do Trabalho | K8: Natal - RN | L8: 170 | N8: CUMPRIDO | O8: Livanaldo Bernardino | P8: 84 8718-3858 | Q8: 100 | S8: SIM | T8: CUMPRIDO | U8: =Table_516[[#This Row],[VALOR]]-Table_516[[#This Row],[ CUSTO]] -> 70
B9: 45779 | D9: Fett Advogados Bruna Ferracini | E9: 51 9184-8885 | F9: Instrução - Presencial | G9: 0000115-17.2025.5.09.0245 | H9: 45782 | I9: 0.4375 | J9: Vara do Trabalho | K9: Pinhais - PR | L9: 200 | N9: CUMPRIDO | O9: Jorjane Saab Rahal | P9: 41 9875-3181 | Q9: 100 | S9: SIM | T9: CUMPRIDO | U9: =Table_516[[#This Row],[VALOR]]-Table_516[[#This Row],[ CUSTO]] -> 100
B10: 45730 | D10: Marcos Piva | E10: 11 96608-7561 | F10: Audiência | G10: 1000164-27.2025.5.02.0442 | H10: 45783 | I10: 0.38541667 | J10: 2ª Vara do Trabalho | K10: Santos - SP | L10: 300 | N10: CUMPRIDO | O10: IRB - Isabelle | P10: 13 98804-4390 | Q10: 130 | S10: SIM | T10: CUMPRIDO | U10: =Table_516[[#This Row],[VALOR]]-Table_516[[#This Row],[ CUSTO]] -> 170
B11: 45776 | D11: Laís Duarte | E11: 34 8864-3914 | F11: Instrução - Presencial | H11: 45783 | I11: 0.43055556 | J11: 2ª Vara do Trabalho | K11: Ribeirão Preto - SP | L11: 300 | N11: CUMPRIDO | O11: Mayara Belfort | P11: 16 99138-1367 | Q11: 70 | S11: SIM | T11: CUMPRIDO | U11: =Table_516[[#This Row],[VALOR]]-Table_516[[#This Row],[ CUSTO]] -> 230
B12: 45776 | D12: Andre Oliveira | E12: 19 98127-4386 | F12: UNA Presencial | G12: 1000419-84.2025.5.02.0603 | H12: 45783 | I12: 0.40277778 | J12: 3ª Vara do Trabalho da Zona Leste | K12: São Paulo - SP | L12: 200 | M12: ok | N12: CUMPRIDO | O12: Joao Tomaz da Silva | P12: 11 97377-8980 | Q12: 70 | S12: SIM | T12: CUMPRIDO | U12: =Table_516[[#This Row],[VALOR]]-Table_516[[#This Row],[ CUSTO]] -> 130
B13: 45776 | D13: Andre Oliveira | E13: 19 98127-4386 | F13: UNA Presencial | G13: 1000295-75.2025.5.02.0062 | H13: 45783 | I13: 0.52777778 | J13: 62ª Vara do Trabalho da Barra Funda | K13: São Paulo - SP | L13: 200 | M13: ok | N13: CUMPRIDO | O13: Joao Tomaz da Silva | P13: 11 97377-8980 | Q13: 70 | S13: SIM | T13: CUMPRIDO | U13: =Table_516[[#This Row],[VALOR]]-Table_516[[#This Row],[ CUSTO]] -> 130
B14: 45777 | D14: Vivian Barbosa / Raquel Moreira | E14: 11 94569-1656 / 11 98450-5051 | F14: UNA Presencial | G14: 0011050-86.2024.5.15.0083 | H14: 45783 | I14: 0.375 | J14: 3ª Vara do Trabalho | K14: São José dos Campos - SP | L14: 300 | N14: CUMPRIDO | O14: Helena Do Amaral Simionelli | P14: 12 99108-0694 | Q14: 70 | S14: SIM | T14: CUMPRIDO | U14: =Table_516[[#This Row],[VALOR]]-Table_516[[#This Row],[ CUSTO]] -> 230
B15: 45777 | D15: Gregor / Krämer | E15: 21 99845-9876 / 22 98118-0352 | F15: Andamento | G15: 1001823-83.2025.8.26.0529 | H15: 45783 | J15: SEF Setor das Execuções Fiscais | K15: Santana de Parnaíba - SP | L15: 300 | N15: CUMPRIDO | O15: Jaqueline Machado | P15: 11 97490-9338 | Q15: 100 | S15: SIM | T15: CUMPRIDO | U15: =Table_516[[#This Row],[VALOR]]-Table_516[[#This Row],[ CUSTO]] -> 200
B16: 45779 | D16: Beatriz Aragão & Bernardo | E16: 85 3252-2939 - 85 8405-1478 | F16: Audiência | G16: 0000186-18.2025.5.06.0143 | H16: 45783 | I16: 0.38541667 | J16: 3ª Vara do Trabalho | K16: Jaboatão dos Guararapes - PE | L16: 170 | N16: CUMPRIDO | O16: Clariana Massena Ponciano Dias | P16: 81 9874-9976 | Q16: 70 | S16: SIM | T16: CUMPRIDO | U16: =Table_516[[#This Row],[VALOR]]-Table_516[[#This Row],[ CUSTO]] -> 100
B17: 45779 | D17: Fett Advogados Bruna Ferracini | E17: 51 9184-8885 | F17: Instrução - Presencial | G17: 0021133-76.2024.5.04.0663 | H17: 45783 | I17: 0.57291667 | J17: 3ª Vara do Trabalho | K17: Passo Fundo - RS | L17: 200 | N17: CUMPRIDO | O17: Guilherme Varela Gomes | P17: 54 8101-0410 | Q17: 100 | S17: SIM | T17: CUMPRIDO | U17: =Table_516[[#This Row],[VALOR]]-Table_516[[#This Row],[ CUSTO]] -> 100
B18: 45775 | D18: Josiane - Luan | E18: 45 9979-5193 | F18: Conciliação - Presencial | H18: 45784 | I18: 0.63888889 | J18: ANEXO UNIP | K18: Ribeirão Preto - SP | L18: 120 | N18: CUMPRIDO | O18: Mayara Belfort | P18: 16 99138-1367 | Q18: 60 | S18: SIM | T18: CUMPRIDO | U18: =Table_516[[#This Row],[VALOR]]-Table_516[[#This Row],[ CUSTO]] -> 60
B19: 45776 | D19: Laís Duarte | E19: 34 8864-3914 | F19: Inicial - Presencial | H19: 45784 | I19: 0.36805556 | J19: 2ª Vara do Trabalho | K19: Ribeirão Preto - SP | L19: 200 | N19: CUMPRIDO | O19: Mayara Belfort | P19: 16 99138-1367 | Q19: 60 | S19: SIM | T19: CUMPRIDO | U19: =Table_516[[#This Row],[VALOR]]-Table_516[[#This Row],[ CUSTO]] -> 140
B20: 45776 | D20: Andre Oliveira | E20: 19 98127-4386 | F20: UNA Presencial | G20: 1000163-85.2025.5.02.0072 | H20: 45784 | I20: 0.57291667 | J20: 72ª Vara do Trabalho da Barra Funda | K20: São Paulo - SP | L20: 200 | M20: ok | N20: CUMPRIDO | O20: Joao Tomaz da Silva | P20: 11 97377-8980 | Q20: 70 | S20: SIM | T20: CUMPRIDO | U20: =Table_516[[#This Row],[VALOR]]-Table_516[[#This Row],[ CUSTO]] -> 130
B21: 45776 | D21: Laís Duarte | E21: 34 8864-3914 | F21: Audiência | H21: 45784 | I21: 0.33333333 | J21: Vara do Trabalho | K21: São João dos Patos - MA | N21: CUMPRIDO | O21: Mylenna Sá | P21: 99 8410-9393 | S21: SIM | T21: CUMPRIDO | U21: =Table_516[[#This Row],[VALOR]]-Table_516[[#This Row],[ CUSTO]] -> 0
B22: 45776 | D22: Laís Duarte | E22: 34 8864-3914 | F22: Audiência | H22: 45784 | I22: 0.33333333 | J22: Vara do Trabalho | K22: São João dos Patos - MA | N22: CUMPRIDO | O22: Mylenna Sá | P22: 99 8410-9393 | S22: SIM | T22: CUMPRIDO | U22: =Table_516[[#This Row],[VALOR]]-Table_516[[#This Row],[ CUSTO]] -> 0
B23: 45782 | D23: Andre Oliveira | E23: 19 98127-4386 | F23: UNA Presencial | G23: 1000325-12.2025.5.02.0030 | H23: 45784 | I23: 0.57638889 | J23: 30ª Vara do Trabalho da Barra Funda | K23: São Paulo - SP | L23: 300 | M23: ok | N23: CUMPRIDO | O23: Elisangela ES - SOLUÇÕES JURÍDICAS | P23: 11 93067-5163 | Q23: 150 | S23: SIM | T23: CUMPRIDO | U23: =Table_516[[#This Row],[VALOR]]-Table_516[[#This Row],[ CUSTO]] -> 150
B24: 45782 | D24: LACOSTA ADVOGADOS | E24: 21 95922-4000 / 11 91039-6920 | F24: Audiência | H24: 45784 | I24: 0.41666667 | J24: 1ª Vara do Trabalho | K24: Praia Grande - SP | L24: 350 | N24: CUMPRIDO | O24: Carla Melo | P24: 13 99763-3941 | Q24: 100 | S24: SIM | T24: CUMPRIDO | U24: =Table_516[[#This Row],[VALOR]]-Table_516[[#This Row],[ CUSTO]] -> 250
B25: 45783 | D25: Thiago Coriolano | E25: 11 98775-8123 | F25: Instrução - Presencial | G25: 0001133-71.2024.5.12.0036 | H25: 45784 | I25: 0.45833333 | J25: Virtual | K25: Florianopolis - SC | L25: 250 | N25: CUMPRIDO | O25: Larissa Miliano | P25: 11 97647-0089 | Q25: 50 | S25: SIM | T25: CUMPRIDO | U25: =Table_516[[#This Row],[VALOR]]-Table_516[[#This Row],[ CUSTO]] -> 200
B26: 45776 | D26: Laís Duarte | E26: 34 8864-3914 | F26: Instrução - Presencial | H26: 45785 | I26: 0.375 | J26: 2ª Vara do Trabalho | K26: Ribeirão Preto - SP | L26: 350 | N26: CUMPRIDO | O26: Mayara Belfort | P26: 16 99138-1367 | Q26: 70 | S26: SIM | T26: CUMPRIDO | U26: =Table_516[[#This Row],[VALOR]]-Table_516[[#This Row],[ CUSTO]] -> 280
B27: 45782 | D27: LACOSTA ADVOGADOS | E27: 21 95922-4000 / 11 91039-6920 | F27: Audiência | H27: 45785 | I27: 0.42361111 | J27: 1ª Vara do Trabalho | K27: Jacareí - SP | L27: 250 | N27: CUMPRIDO | O27: Karina Maria | P27: 31 8304-2946 | Q27: 120 | S27: SIM | T27: CUMPRIDO | U27: =Table_516[[#This Row],[VALOR]]-Table_516[[#This Row],[ CUSTO]] -> 130
B28: 45782 | D28: Eliana Ivano | E28: 11 99442-6135 | F28: Inicial - Presencial | G28: 0010083-33.2025.5.15.0139 | H28: 45785 | I28: 0.66666667 | J28: Vara do Trabalho | K28: Ubatuba - SP | L28: 350 | N28: CUMPRIDO | O28: Glaydson Roberto Afonso Soares da Silva | P28: 12 99795-5162 | Q28: 160 | S28: SIM | T28: CUMPRIDO | U28: =Table_516[[#This Row],[VALOR]]-Table_516[[#This Row],[ CUSTO]] -> 190
B29: 45784 | D29: Rodrigo Bezerra | E29: 11 99360-4364 | F29: Instrução - Presencial | G29: 1011691-47.2024.8.26.0068 | H29: 45785 | I29: 0.67708333 | J29: 4ª Vara Cível | K29: Barueri - SP | L29: 200 | N29: CUMPRIDO | O29: Isabel Carolina Butierrez Cartes | P29: 11 97516-8093 | Q29: 80 | S29: SIM | T29: CUMPRIDO | U29: =Table_516[[#This Row],[VALOR]]-Table_516[[#This Row],[ CUSTO]] -> 120
B30: 45785 | D30: Igor Matheus Rezende | E30: 62 8288-5957 | F30: Audiência | G30: 0010214-60.2025.5.03.0165 | H30: 45785 | I30: 0.4375 | J30: 2ª Vara do Trabalho | K30: Nova Lima - MG | L30: 250 | N30: CUMPRIDO | O30: Patrícia do Rosário Liberato Drummond | P30: 31 9108-9766 | Q30: 150 | R30: desv | S30: SIM | T30: CUMPRIDO | U30: =Table_516[[#This Row],[VALOR]]-Table_516[[#This Row],[ CUSTO]] -> 100
B31: 45784 | D31: Thulyo Augustto | E31: 62 9683-9870 | F31: Audiência | G31: 0001228-60.2024.5.10.0003 | H31: 45786 | I31: 0.40277778 | J31: 3ª Vara do Trabalho | K31: Brasília - DF | L31: 250 | N31: CUMPRIDO | O31: Luana Amancio | P31: 61 8542-3080 | Q31: 100 | S31: SIM | T31: CUMPRIDO | U31: =Table_516[[#This Row],[VALOR]]-Table_516[[#This Row],[ CUSTO]] -> 150
B32: 45761 | D32: Marcos Marinho | E32: 41 9647-2038 | F32: UNA Presencial | G32: 1000489-53.2025.5.02.0037 | H32: 45789 | I32: 0.43055556 | J32: 37ª Vara do Trabalho da Barra Funda | K32: São Paulo - SP | L32: 150 | N32: CUMPRIDO | O32: Joao Tomaz da Silva | P32: 11 97377-8980 | Q32: 70 | S32: SIM | T32: CUMPRIDO | U32: =Table_516[[#This Row],[VALOR]]-Table_516[[#This Row],[ CUSTO]] -> 80
B33: 45785 | D33: Jessica | E33: 41 9685-0539 | F33: Coleta de Assinaturas | G33: PAULO CESAR SILVA SANTOS | H33: 45789 | I33: 0.45833333 | J33: Rua Dr. Francisco Guerra (ao lado do novo Forum Senhor do, R. do Bonfim | K33: Penedo - AL | L33: 350 | M33: ok | N33: CUMPRIDO | O33: Hugo Ramires Gomes Oliveira | P33: 82 9357-3470 | Q33: 100 | S33: SIM | T33: CUMPRIDO | U33: =Table_516[[#This Row],[VALOR]]-Table_516[[#This Row],[ CUSTO]] -> 250
B34: 45786 | D34: Sepulveda Advogados Associados | E34: 19 99651-8840 | F34: UNA Presencial | H34: 45789 | I34: 0.40277778 | J34: 16ª Vara do Trabalho da Zona Sul | K34: São Paulo - SP | L34: 150 | N34: CUMPRIDO | O34: Daniela Lima Nogueira | P34: 11 98452-0056 | Q34: 70 | S34: SIM | T34: CUMPRIDO | U34: =Table_516[[#This Row],[VALOR]]-Table_516[[#This Row],[ CUSTO]] -> 80
B35: 45786 | D35: Fett Advogados Bruna Ferracini | E35: 51 9184-8885 | F35: Inicial - Presencial | G35: 0010320-23.2025.5.03.0003 | H35: 45789 | I35: 0.55555556 | J35: 3ª Vara do Trabalho | K35: Belo Horizonte - MG | L35: 200 | N35: CUMPRIDO | O35: Lucas Souza de Siqueira | P35: 31 9641-8682 | Q35: 60 | S35: SIM | T35: CUMPRIDO | U35: =Table_516[[#This Row],[VALOR]]-Table_516[[#This Row],[ CUSTO]] -> 140
B36: 45786 | D36: Rebeca | E36: 19 99416-4309 | F36: Protocolo | H36: 45789 | J36: Foro Cível de Jabaquara | K36: São Paulo - SP | L36: 200 | N36: CUMPRIDO | O36: Joao Tomaz da Silva | P36: 11 97377-8980 | Q36: 50 | S36: SIM | T36: CUMPRIDO | U36: =Table_516[[#This Row],[VALOR]]-Table_516[[#This Row],[ CUSTO]] -> 150
B37: 45785 | D37: Jessica | E37: 41 9685-0539 | F37: Coleta de Assinaturas | G37: ROBERTO GOMES PEREIRA | H37: 45790 | I37: 0.45833333 | J37: Rua Dr Siqueira Campos, nº 172, Bairro: Liberdade | K37: São Paulo - SP | L37: =200+40.4 -> 240.4 | M37: ok | N37: CUMPRIDO | O37: Diligência Própria | Q37: 40.4 | S37: SIM | T37: CUMPRIDO | U37: =Table_516[[#This Row],[VALOR]]-Table_516[[#This Row],[ CUSTO]] -> 200
B38: 45786 | D38: Beatriz Aragão & Bernardo | E38: 85 3252-2939 - 85 8405-1478 | F38: Audiência | G38: 1000437-43.2025.5.02.0074 | H38: 45790 | I38: 0.44444444 | J38: 74ª Vara do Trabalho da Barra Funda | K38: São Paulo - SP | L38: 170 | N38: CUMPRIDO | O38: Amanda Pivott | P38: 11 94857-0549 | Q38: 70 | S38: SIM | T38: CUMPRIDO | U38: =Table_516[[#This Row],[VALOR]]-Table_516[[#This Row],[ CUSTO]] -> 100
B39: 45786 | D39: Leonardo - Advocacia Soller | E39: 11 95657-2522 / 11 95657-2522 | F39: Conciliação - Presencial | H39: 45790 | I39: 0.375 | J39: PROCON | K39: Macaé - RJ | L39: 150 | N39: CUMPRIDO | O39: Larissa Boy | P39: 22 99292-3785 | Q39: 60 | S39: SIM | T39: CUMPRIDO | U39: =Table_516[[#This Row],[VALOR]]-Table_516[[#This Row],[ CUSTO]] -> 90
B40: 45789 | D40: Thulyo Augustto | E40: 62 9683-9870 | F40: UNA Presencial | G40: 0000218-07.2025.5.08.0001 | H40: 45790 | I40: 0.38541667 | J40: 1ª Vara do Trabalho | K40: Belém - PA | L40: 300 | N40: CUMPRIDO | O40: Renata Cardoso | P40: 91 9375-2465 | Q40: 80 | S40: SIM | T40: CUMPRIDO | U40: =Table_516[[#This Row],[VALOR]]-Table_516[[#This Row],[ CUSTO]] -> 220
B41: 45789 | D41: Jessica | E41: 41 9685-0539 | F41: Coleta de Assinaturas | G41: ZITA ALVES VILAR | H41: 45790 | I41: 0.625 | J41: Av Frei Serafim, 2155, sala 05, ed humana, centro | K41: Teresina - PI | L41: =200+108.85-0.36 -> 308.49 | M41: ok | N41: CUMPRIDO | O41: Gabriela Anorato | P41: 99 9649-7638 | Q41: =60+108.85 -> 168.85 | S41: SIM | T41: CUMPRIDO | U41: =Table_516[[#This Row],[VALOR]]-Table_516[[#This Row],[ CUSTO]] -> 139.64
B42: 45782 | D42: LACOSTA ADVOGADOS | E42: 21 95922-4000 / 11 91039-6920 | F42: Audiência | H42: 45791 | I42: 0.40625 | J42: 3ª Vara do Trabalho | K42: Mauá - SP | L42: 300 | N42: CUMPRIDO | O42: Priscila Silva Barbosa Vieira | P42: 11 94918-8364 | Q42: 150 | S42: SIM | T42: CUMPRIDO | U42: =Table_516[[#This Row],[VALOR]]-Table_516[[#This Row],[ CUSTO]] -> 150
B43: 45786 | D43: Beatriz Aragão & Bernardo | E43: 85 3252-2939 - 85 8405-1478 | F43: Audiência | G43: 0000267-21.2025.5.18.0017 | H43: 45791 | I43: 0.34722222 | J43: 17ª Vara do Trabalho | K43: Goiânia - GO | L43: 180 | N43: CUMPRIDO | O43: Lorena Posse | P43: 62 8268-1133 | Q43: 80 | S43: SIM | T43: CUMPRIDO | U43: =Table_516[[#This Row],[VALOR]]-Table_516[[#This Row],[ CUSTO]] -> 100
B44: 45786 | D44: Beatriz Aragão & Bernardo | E44: 85 3252-2939 - 85 8405-1478 | F44: Audiência | G44: 0100431-45.2025.5.01.0541 | H44: 45791 | I44: 0.40277778 | J44: 1ª Vara do Trabalho | K44: Três Rios - RJ | L44: 200 | N44: CUMPRIDO | O44: Anita Kappler | P44: 24 99974-4178 | Q44: 150 | R44: desv | S44: SIM | T44: CUMPRIDO | U44: =Table_516[[#This Row],[VALOR]]-Table_516[[#This Row],[ CUSTO]] -> 50
B45: 45786 | D45: Beatriz Aragão & Bernardo | E45: 85 3252-2939 - 85 8405-1478 | F45: Audiência | G45: 1000293-32.2025.5.02.0054 | H45: 45791 | I45: 0.56944444 | J45: 54ª Vara do Trabalho da Barra Funda | K45: São Paulo - SP | L45: 170 | N45: CUMPRIDO | O45: Amanda Pivott | P45: 11 94857-0549 | Q45: 70 | S45: SIM | T45: CUMPRIDO | U45: =Table_516[[#This Row],[VALOR]]-Table_516[[#This Row],[ CUSTO]] -> 100
B46: 45786 | D46: Beatriz Aragão & Bernardo | E46: 85 3252-2939 - 85 8405-1478 | F46: Audiência | G46: 1000313-07.2025.5.02.0027 | H46: 45791 | I46: 0.60416667 | J46: 27ª Vara do Trabalho da Barra Funda | K46: São Paulo - SP | L46: 170 | N46: CUMPRIDO | O46: Amanda Pivott (Cristiane) | P46: 11 94857-0549 | Q46: 70 | S46: SIM | T46: CUMPRIDO | U46: =Table_516[[#This Row],[VALOR]]-Table_516[[#This Row],[ CUSTO]] -> 100
B47: 45786 | D47: Leonardo - Advocacia Soller | E47: 11 95657-2522 / 11 95657-2522 | F47: Conciliação - Presencial | H47: 45791 | I47: 0.45833333 | J47: Juizado Especial Cível | K47: Varginha - MG | L47: 150 | N47: CUMPRIDO | O47: Mariana Stela | P47: 35 9832-3807 | Q47: 40 | S47: SIM | T47: CUMPRIDO | U47: =Table_516[[#This Row],[VALOR]]-Table_516[[#This Row],[ CUSTO]] -> 110
B48: 45789 | D48: Andre Oliveira | E48: 19 98127-4386 | F48: UNA Presencial | G48: 1000313-84.2025.5.02.0066 | H48: 45791 | I48: 0.625 | J48: 66ª Vara do Trabalho da Barra Funda | K48: São Paulo - SP | L48: 200 | N48: CUMPRIDO | O48: Amanda Pivott (Alexandre) | P48: 11 94857-0549 | Q48: 70 | S48: SIM | T48: CUMPRIDO | U48: =Table_516[[#This Row],[VALOR]]-Table_516[[#This Row],[ CUSTO]] -> 130
B49: 45789 | D49: Andre Oliveira | E49: 19 98127-4386 | F49: UNA Presencial | G49: 1000332-65.2025.5.02.0042 | H49: 45791 | I49: 0.55555556 | J49: 42ª Vara do Trabalho da Barra Funda | K49: São Paulo - SP | L49: 200 | N49: CUMPRIDO | O49: Amanda Pivott (Cristiane) | P49: 11 94857-0549 | Q49: 70 | S49: SIM | T49: CUMPRIDO | U49: =Table_516[[#This Row],[VALOR]]-Table_516[[#This Row],[ CUSTO]] -> 130
B50: 45790 | D50: Igor Matheus Rezende | E50: 62 8288-5957 | F50: Audiência | G50: 0020361-44.2024.5.04.0201 | H50: 45791 | I50: 0.35416667 | J50: 1ª Vara do Trabalho | K50: Canoas - RS | L50: 250 | N50: CUMPRIDO | O50: Karina Rosa Kessler | P50: 51 8578-0750 | Q50: 100 | S50: SIM | T50: CUMPRIDO | U50: =Table_516[[#This Row],[VALOR]]-Table_516[[#This Row],[ CUSTO]] -> 150
B51: 45790 | D51: Jessica | E51: 41 9685-0539 | F51: Coleta de Assinaturas | G51: LUIZ CARLOS MEDEIROS VIEIRA | H51: 45791 | I51: 0.66666667 | J51: Av. Praia de Belas, nº 1212, Sala 424, Edificio Home Office, Praia de Belas | K51: Porto Alegre - RS | L51: 300 | M51: ok | N51: CUMPRIDO | O51: Josie Lopes | P51: 51 9182-9085 | Q51: 58 | S51: SIM | T51: CUMPRIDO | U51: =Table_516[[#This Row],[VALOR]]-Table_516[[#This Row],[ CUSTO]] -> 242
B52: 45790 | D52: Andressa Cruz | E52: 11 96829-3317 | F52: Instrução - Presencial | H52: 45791 | I52: 0.46527778 | J52: 1ª Vara do Trabalho | K52: Nova Iguaçu - RJ | L52: 150 | N52: CUMPRIDO | O52: Luciana Silva | P52: 21 97993-7053 | Q52: 70 | S52: SIM | T52: CUMPRIDO | U52: =Table_516[[#This Row],[VALOR]]-Table_516[[#This Row],[ CUSTO]] -> 80
B53: 45791 | D53: Thiago Coriolano | E53: 11 98775-8123 | F53: UNA Presencial | G53: 1000417-87.2025.5.02.0709 | H53: 45791 | I53: 0.66666667 | J53: 1ª Vara do Trabalho da Zona Sul | K53: São Paulo - SP | L53: 180 | N53: CUMPRIDO | O53: Amanda Solanich | P53: 11 97951-9771 | Q53: 60 | S53: SIM | T53: CUMPRIDO | U53: =Table_516[[#This Row],[VALOR]]-Table_516[[#This Row],[ CUSTO]] -> 120
B54: 45791 | D54: Thiago Coriolano | E54: 11 98775-8123 | F54: UNA Presencial | G54: 1000332-89.2025.5.02.0713 | H54: 45791 | I54: 0.55208333 | J54: 17ª Vara do Trabalho da Zona Sul | K54: São Paulo - SP | L54: 180 | N54: CUMPRIDO | O54: Luiza Yasuko Mio | P54: 11 99861-0460 | Q54: 80 | S54: SIM | T54: CUMPRIDO | U54: =Table_516[[#This Row],[VALOR]]-Table_516[[#This Row],[ CUSTO]] -> 100
B55: 45791 | D55: Joarfferson Rosendo | E55: 83 8646-7514 | F55: Protocolo | H55: 45791 | J55: Virtual | K55: São Paulo - SP | L55: 1000 | N55: CUMPRIDO | O55: Arlen Mota | P55: 11 99543-2449 | Q55: 150 | S55: SIM | T55: CUMPRIDO | U55: =Table_516[[#This Row],[VALOR]]-Table_516[[#This Row],[ CUSTO]] -> 850
B56: 45786 | D56: Beatriz Aragão & Bernardo | E56: 85 3252-2939 - 85 8405-1478 | F56: Audiência | G56: 0101470-69.2024.5.01.0070 | H56: 45792 | I56: 0.38194444 | J56: 70ª Vara do Trabalho | K56: Rio de Janeiro - RJ | L56: 180 | N56: CUMPRIDO | O56: Mayara Lahas | P56: 21 99474-4417 | Q56: 80 | S56: SIM | T56: CUMPRIDO | U56: =Table_516[[#This Row],[VALOR]]-Table_516[[#This Row],[ CUSTO]] -> 100
B57: 45786 | D57: Fett Advogados Bruna Ferracini | E57: 51 9184-8885 | F57: Instrução - Presencial | G57: 0020664-62.2024.5.04.0523 | H57: 45792 | I57: 0.39583333 | J57: 3ª Vara do Trabalho | K57: Erechim - RS | L57: 200 | N57: CUMPRIDO | O57: Cariza Beal Toigo | P57: 54 8428-0506 | Q57: 100 | S57: SIM | T57: CUMPRIDO | U57: =Table_516[[#This Row],[VALOR]]-Table_516[[#This Row],[ CUSTO]] -> 100
B58: 45786 | D58: Fett Advogados Bruna Ferracini | E58: 51 9184-8885 | F58: Instrução - Presencial | G58: 0011212-45.2024.5.03.0009 | H58: 45792 | I58: 0.42708333 | J58: 9ª Vara do Trabalho | K58: Belo Horizonte - MG | L58: 200 | N58: CUMPRIDO | O58: Fernando Santos | P58: 11 98307-2224 | Q58: 100 | S58: SIM | T58: CUMPRIDO | U58: =Table_516[[#This Row],[VALOR]]-Table_516[[#This Row],[ CUSTO]] -> 100
B59: 45790 | D59: LACOSTA ADVOGADOS | E59: 21 95922-4000 / 11 91039-6920 | F59: Audiência | H59: 45792 | I59: 0.44791667 | J59: 1ª Vara do Trabalho | K59: Osasco - SP | L59: 150 | N59: CUMPRIDO | O59: Joao Tomaz da Silva | P59: 11 97377-8980 | Q59: 70 | S59: SIM | T59: CUMPRIDO | U59: =Table_516[[#This Row],[VALOR]]-Table_516[[#This Row],[ CUSTO]] -> 80
B60: 45792 | D60: Jessica | E60: 41 9685-0539 | F60: Coleta de Assinaturas | G60: Edelsio Parise | H60: 45792 | I60: 0.79166667 | J60: Rua Deputado Asterio de Mello, 589, AP 402 | K60: Veranópolis - RS | L60: =200+28.8 -> 228.8 | M60: ok | N60: CUMPRIDO | O60: Sabrina Censi Fiorio | P60: 54 9908-2696 | Q60: =100+28.8 -> 128.8 | S60: SIM | T60: CUMPRIDO | U60: =Table_516[[#This Row],[VALOR]]-Table_516[[#This Row],[ CUSTO]] -> 100
B61: 45776 | D61: Laís Duarte | E61: 34 8864-3914 | F61: Inicial - Presencial | H61: 45793 | I61: 0.5 | J61: 1ª Vara do Trabalho | K61: Ribeirão Preto - SP | L61: 200 | N61: CUMPRIDO | O61: Mayara Belfort | P61: 16 99138-1367 | Q61: 60 | S61: SIM | T61: CUMPRIDO | U61: =Table_516[[#This Row],[VALOR]]-Table_516[[#This Row],[ CUSTO]] -> 140
B62: 45789 | D62: Andre Oliveira | E62: 19 98127-4386 | F62: UNA Presencial | G62: 1000386-79.2025.5.02.0511 | H62: 45793 | I62: 0.48611111 | J62: Vara do Trabalho | K62: Itapevi - SP | L62: 300 | M62: ok | N62: CUMPRIDO | O62: Isabel Carolina Butierrez Cartes | P62: 11 97516-8093 | Q62: 140 | S62: SIM | T62: CUMPRIDO | U62: =Table_516[[#This Row],[VALOR]]-Table_516[[#This Row],[ CUSTO]] -> 160
B63: 45792 | D63: Danielle Peruzzo | E63: 11 99584-7776 | F63: Conciliação - Presencial | H63: 45793 | I63: 0.625 | J63: PROCON | K63: Araçatuba - SP | L63: 180 | N63: CUMPRIDO | O63: Karla Handressa Castro de Oliveira | P63: 18 99715-9573 | Q63: 50 | S63: SIM | T63: CUMPRIDO | U63: =Table_516[[#This Row],[VALOR]]-Table_516[[#This Row],[ CUSTO]] -> 130
B64: 45793 | D64: Jessica | E64: 41 9685-0539 | F64: Coleta de Assinaturas | G64: Marlon Mariano | H64: 45793 | I64: 0.625 | J64: Rua dr. João Gonçalves Foz, Bairro: Jardim Marupiara (Sede da OAB) | K64: Presidente Prudente - SP | L64: 200 | M64: ok | N64: CUMPRIDO | O64: Bruno Cortez | P64: 18 99610-1364 | Q64: 100 | S64: SIM | T64: CUMPRIDO | U64: =Table_516[[#This Row],[VALOR]]-Table_516[[#This Row],[ CUSTO]] -> 100
B65: 45793 | D65: Thiago Coriolano | E65: 11 98775-8123 | F65: Entrega | H65: 45793 | K65: São Paulo - SP | L65: 120 | N65: CUMPRIDO | O65: Joao Tomaz da Silva | P65: 11 97377-8980 | Q65: 50 | S65: SIM | T65: CUMPRIDO | U65: =Table_516[[#This Row],[VALOR]]-Table_516[[#This Row],[ CUSTO]] -> 70
B66: 45792 | D66: Patricia Detlinger | E66: 11 99707-7808 | F66: Acompanhamento | H66: 45796 | J66: 7ª Vara Empresarial | K66: Rio de Janeiro - RJ | L66: 150 | N66: CUMPRIDO | O66: Mayara Lahas | P66: 21 99474-4417 | Q66: 50 | S66: SIM | T66: CUMPRIDO | U66: =Table_516[[#This Row],[VALOR]]-Table_516[[#This Row],[ CUSTO]] -> 100
B67: 45793 | D67: Beatriz Aragão & Bernardo | E67: 85 3252-2939 - 85 8405-1478 | F67: UNA Presencial | G67: 0100134-65.2025.5.01.0047 | H67: 45796 | I67: 0.5625 | J67: 47ª Vara do Trabalho | K67: Rio de Janeiro - RJ | L67: 180 | N67: CUMPRIDO | O67: Mayara Lahas | P67: 21 99474-4417 | Q67: 70 | S67: SIM | T67: CUMPRIDO | U67: =Table_516[[#This Row],[VALOR]]-Table_516[[#This Row],[ CUSTO]] -> 110
B68: 45793 | D68: Fett Advogados Bruna Ferracini | E68: 51 9184-8885 | F68: Inicial - Presencial | G68: 0010339-11.2025.5.03.0009 | H68: 45796 | I68: 0.34027778 | J68: 9ª Vara do Trabalho | K68: Belo Horizonte - MG | L68: 200 | N68: CUMPRIDO | O68: Lucas Souza de Siqueira | P68: 31 9641-8682 | Q68: 60 | S68: SIM | T68: CUMPRIDO | U68: =Table_516[[#This Row],[VALOR]]-Table_516[[#This Row],[ CUSTO]] -> 140
B69: 45792 | D69: Andre Oliveira | E69: 19 98127-4386 | F69: UNA Presencial | G69: 1000438-30.2025.5.02.0041 | H69: 45797 | I69: 0.66666667 | J69: 41ª Vara do Trabalho da Barra Funda | K69: São Paulo - SP | L69: 200 | M69: ok | N69: CUMPRIDO | O69: Joao Tomaz da Silva | P69: 11 97377-8980 | Q69: 70 | S69: SIM | T69: CUMPRIDO | U69: =Table_516[[#This Row],[VALOR]]-Table_516[[#This Row],[ CUSTO]] -> 130
B70: 45793 | D70: Beatriz Aragão & Bernardo | E70: 85 3252-2939 - 85 8405-1478 | F70: UNA Presencial | G70: 0000127.56.2025.5.06.0102 | H70: 45797 | I70: 0.36805556 | J70: 2ª Vara do Trabalho | K70: Olinda - PE | L70: 160 | N70: CUMPRIDO | O70: João Victor Pessôa Silva | P70: 81 9979-6869 | Q70: 60 | S70: SIM | T70: CUMPRIDO | U70: =Table_516[[#This Row],[VALOR]]-Table_516[[#This Row],[ CUSTO]] -> 100
B71: 45793 | D71: Beatriz Aragão & Bernardo | E71: 85 3252-2939 - 85 8405-1478 | F71: UNA Presencial | G71: 0000351-91.2025.5.06.0102 | H71: 45797 | I71: 0.37152778 | J71: 2ª Vara do Trabalho | K71: Olinda - PE | L71: 160 | N71: CUMPRIDO | O71: João Victor Pessôa Silva | P71: 81 9979-6869 | Q71: 60 | S71: SIM | T71: CUMPRIDO | U71: =Table_516[[#This Row],[VALOR]]-Table_516[[#This Row],[ CUSTO]] -> 100
B72: 45793 | D72: Leonardo - Advocacia Soller | E72: 11 95657-2522 / 11 95657-2522 | F72: Audiência | H72: 45797 | I72: 0.38194444 | J72: 3º Juizado Especial Cível e das Relações de Consumo | K72: Recife - PE | L72: 150 | N72: CUMPRIDO | O72: Priscila Souza | P72: 81 8971-6844 | Q72: 40 | S72: SIM | T72: CUMPRIDO | U72: =Table_516[[#This Row],[VALOR]]-Table_516[[#This Row],[ CUSTO]] -> 110
B73: 45793 | D73: Fett Advogados Bruna Ferracini | E73: 51 9184-8885 | F73: Instrução - Presencial | G73: 0000244-94.2025.5.09.0124 | H73: 45797 | I73: 0.40277778 | J73: 2ª Vara do Trabalho | K73: Ponta Grossa - PR | L73: 200 | N73: CUMPRIDO | O73: Geiciele Paula da Rosa | P73: 42 9945-0178 | Q73: 100 | S73: SIM | T73: CUMPRIDO | U73: =Table_516[[#This Row],[VALOR]]-Table_516[[#This Row],[ CUSTO]] -> 100
B74: 45796 | D74: LACOSTA ADVOGADOS | E74: 21 95922-4000 / 11 91039-6920 | F74: Audiência | H74: 45797 | I74: 0.64583333 | J74: 2ª Vara do Trabalho da Zona Sul | K74: São Paulo - SP | L74: 150 | N74: CUMPRIDO | O74: Amanda Solanich | P74: 11 97951-9771 | Q74: 60 | S74: SIM | T74: CUMPRIDO | U74: =Table_516[[#This Row],[VALOR]]-Table_516[[#This Row],[ CUSTO]] -> 90
B75: 45792 | D75: Andre Oliveira | E75: 19 98127-4386 | F75: UNA Presencial | G75: 1001856-14.2024.5.02.0081 | H75: 45798 | I75: 0.56944444 | J75: 81ª Vara do Trabalho da Barra Funda | K75: São Paulo - SP | L75: 200 | N75: CUMPRIDO | O75: Amanda Pivott | P75: 11 94857-0549 | Q75: 70 | S75: SIM | T75: CUMPRIDO | U75: =Table_516[[#This Row],[VALOR]]-Table_516[[#This Row],[ CUSTO]] -> 130
B76: 45793 | D76: Beatriz Aragão & Bernardo | E76: 85 3252-2939 - 85 8405-1478 | F76: Inicial - Presencial | G76: 0001158-14.2024.5.10.0821 | H76: 45798 | I76: 0.38541667 | J76: 1ª Vara do Trabalho | K76: Palmas - TO | L76: 200 | N76: CUMPRIDO | O76: Amanda Alcantara | P76: 63 9202-3026 | Q76: 70 | S76: SIM | T76: CUMPRIDO | U76: =Table_516[[#This Row],[VALOR]]-Table_516[[#This Row],[ CUSTO]] -> 130
B77: 45793 | D77: Jessica | E77: 41 9685-0539 | F77: Coleta de Assinaturas | G77: LOURENCO TEODORO RODRIGUES | H77: 45798 | I77: 0.58333333 | J77: Rua Antônio de Albuquerque, n°330, Sala 901, Ed. Comercial Canopus Corporate, Savassi | K77: Belo Horizonte - MG | L77: =300+56.4 -> 356.4 | M77: ok | N77: CUMPRIDO | O77: Camila Simao | P77: 31 9474-0937 | Q77: =90+56.4 -> 146.4 | S77: SIM | T77: CUMPRIDO | U77: =Table_516[[#This Row],[VALOR]]-Table_516[[#This Row],[ CUSTO]] -> 210
B78: 45793 | D78: Fett Advogados Bruna Ferracini | E78: 51 9184-8885 | F78: UNA Presencial | G78: 1000476-63.2025.5.02.0422 | H78: 45798 | I78: 0.44791667 | J78: 2ª Vara do Trabalho | K78: Santana de Parnaíba - SP | L78: 200 | N78: CUMPRIDO | O78: Priscila Felisberto Coelho | P78: 11 97337-1172 | Q78: 80 | S78: SIM | T78: CUMPRIDO | U78: =Table_516[[#This Row],[VALOR]]-Table_516[[#This Row],[ CUSTO]] -> 120
B79: 45797 | D79: Jessica | E79: 41 9685-0539 | F79: Coleta de Assinaturas | G79: ANTONIO DE DEUS DA COSTA | H79: 45798 | I79: 0.53125 | J79: OAB Trabalhista | K79: Capanema - PA | L79: =400+141.05+25 -> 566.05 | M79: ok | N79: CUMPRIDO | O79: Yasmym Oliveira | P79: 91 8083-0820 | Q79: =200+141.05+25 -> 366.05 | S79: SIM | T79: CUMPRIDO | U79: =Table_516[[#This Row],[VALOR]]-Table_516[[#This Row],[ CUSTO]] -> 200
B80: 45797 | D80: Leonardo - Advocacia Soller | E80: 11 95657-2522 / 11 95657-2522 | F80: Audiência | H80: 45798 | I80: 0.41666667 | J80: Juizado Especial Cível Anexo UNISANTOS | K80: Santos - SP | L80: 150 | N80: CUMPRIDO | O80: IRB - Isabelle | P80: 13 98804-4390 | Q80: 70 | S80: SIM | T80: CUMPRIDO | U80: =Table_516[[#This Row],[VALOR]]-Table_516[[#This Row],[ CUSTO]] -> 80
B81: 45797 | D81: Thiago Coriolano | E81: 11 98775-8123 | F81: Pericia | H81: 45798 | I81: 0.58333333 | J81: Rua Major Dantas Cortez, 844, Vila Cortez | K81: São Paulo - SP | L81: 200 | N81: CUMPRIDO | O81: Eduardo Molina Vieira | Q81: 120 | S81: SIM | T81: CUMPRIDO | U81: =Table_516[[#This Row],[VALOR]]-Table_516[[#This Row],[ CUSTO]] -> 80
B82: 45782 | D82: LACOSTA ADVOGADOS | E82: 21 95922-4000 / 11 91039-6920 | F82: Audiência | H82: 45799 | I82: 0.54166667 | J82: 7ª Vara do Trabalho da Barra Funda | K82: São Paulo - SP | L82: 150 | N82: CUMPRIDO | O82: Joao Tomaz da Silva | P82: 11 97377-8980 | Q82: 70 | S82: SIM | T82: CUMPRIDO | U82: =Table_516[[#This Row],[VALOR]]-Table_516[[#This Row],[ CUSTO]] -> 80
B83: 45782 | D83: LACOSTA ADVOGADOS | E83: 21 95922-4000 / 11 91039-6920 | F83: Audiência | H83: 45799 | I83: 0.57638889 | J83: 17ª Vara do Trabalho da Barra Funda | K83: São Paulo - SP | L83: 150 | N83: CUMPRIDO | O83: Amanda Pivott (Neila de Souza Miranda) | P83: 11 94857-0549 | Q83: 70 | S83: SIM | T83: CUMPRIDO | U83: =Table_516[[#This Row],[VALOR]]-Table_516[[#This Row],[ CUSTO]] -> 80
B84: 45791 | D84: CAMPANA ADVOGADOS | E84: 16 99788-7824 | F84: Instrução - Presencial | G84: 1001668-40.2024.5.02.0301 | H84: 45799 | I84: 0.58333333 | J84: 3ª Vara do Trabalho | K84: Guarulhos - SP | L84: 150 | N84: CUMPRIDO | O84: Arlen Mota | P84: 11 99543-2449 | Q84: 80 | S84: SIM | T84: CUMPRIDO | U84: =Table_516[[#This Row],[VALOR]]-Table_516[[#This Row],[ CUSTO]] -> 70
B85: 45798 | D85: Andre Oliveira | E85: 19 98127-4386 | F85: UNA Presencial | G85: 1000370-32.2025.5.02.0445 | H85: 45799 | I85: 0.62847222 | J85: 5ª Vara do Trabalho | K85: Santos - SP | L85: 150 | M85: ok | N85: CUMPRIDO | O85: IRB - Isabelle | P85: 13 98804-4390 | Q85: 70 | S85: SIM | T85: CUMPRIDO | U85: =Table_516[[#This Row],[VALOR]]-Table_516[[#This Row],[ CUSTO]] -> 80
B86: 45798 | D86: Leonardo - Advocacia Soller | E86: 11 95657-2522 / 11 95657-2522 | F86: Audiência AIJ | G86: 0000235-20.2025.8.17.8221 | H86: 45799 | I86: 0.42361111 | J86: Juizado Especial Cível | K86: Cabo de Santo Agostinho - PE | L86: 170 | N86: CUMPRIDO | O86: Camilla Almeida | P86: 81 9939-8323 | Q86: 70 | S86: SIM | T86: CUMPRIDO | U86: =Table_516[[#This Row],[VALOR]]-Table_516[[#This Row],[ CUSTO]] -> 100
B87: 45799 | D87: Jessica | E87: 41 9685-0539 | F87: Coleta de Assinaturas | G87: Heron Sérgio da Silva Soares | H87: 45799 | I87: 0.45833333 | J87: Rua México n° 31 Sala 703, centro | K87: Rio de Janeiro - RJ | L87: =300+40.4 -> 340.4 | M87: ok | N87: CUMPRIDO | O87: Oswaldo Assumpção Jr | P87: 21 99672-1599 | Q87: =60+40.4 -> 100.4 | S87: SIM | T87: CUMPRIDO | U87: =Table_516[[#This Row],[VALOR]]-Table_516[[#This Row],[ CUSTO]] -> 240
B88: 45798 | D88: Leonardo - Advocacia Soller | E88: 11 95657-2522 / 11 95657-2522 | F88: Audiência AIJ | G88: 0001164-38.2025.8.17.8226 | H88: 45800 | I88: 0.48611111 | J88: 1º Juizado Especial Cível | K88: Petrolina - PE | L88: =180+200 -> 380 | N88: CUMPRIDO | O88: Camilla Almeida | P88: 81 9939-8323 | Q88: =80+200 -> 280 | S88: SIM | T88: CUMPRIDO | U88: =Table_516[[#This Row],[VALOR]]-Table_516[[#This Row],[ CUSTO]] -> 100
B89: 45799 | D89: Rodrigo Bezerra | E89: 11 99360-4364 | F89: Audiência | H89: 45800 | I89: 0.33333333 | J89: Virtual | K89: Arujá - SP | L89: 150 | N89: CUMPRIDO | O89: Geiciele Paula da Rosa | P89: 42 9945-0178 | Q89: 40 | S89: SIM | T89: CUMPRIDO | U89: =Table_516[[#This Row],[VALOR]]-Table_516[[#This Row],[ CUSTO]] -> 110
B90: 45797 | D90: Danielle Peruzzo | E90: 11 99584-7776 | F90: Audiência | H90: 45803 | I90: 0.375 | J90: 5ª Vara do Trabalho | K90: Maringá - PR | L90: 450 | N90: CUMPRIDO | O90: Ana Marconato | P90: 44 9950-8350 | Q90: 150 | S90: SIM | T90: CUMPRIDO | U90: =Table_516[[#This Row],[VALOR]]-Table_516[[#This Row],[ CUSTO]] -> 300
B91: 45799 | D91: Leonardo - Advocacia Soller | E91: 11 95657-2522 / 11 96606-8260 | F91: Instrução - Presencial | G91: 1001730-70.2024.5.02.0466 | H91: 45803 | I91: 0.36111111 | J91: 6ª Vara do Trabalho | K91: São Bernardo do Campo - SP | L91: 270 | N91: CUMPRIDO | O91: Natacha Caskanlian Aloi | P91: 11 99359-5566 | Q91: 70 | S91: SIM | T91: CUMPRIDO | U91: =Table_516[[#This Row],[VALOR]]-Table_516[[#This Row],[ CUSTO]] -> 200
B92: 45799 | D92: Mara - Sid Fontes | E92: 11 96608-6802 | F92: UNA Presencial | H92: 45803 | I92: 0.64583333 | J92: 3ª Vara do Trabalho | K92: Mogi das Cruzes - SP | L92: 250 | N92: CUMPRIDO | O92: Fernando Santos | P92: 11 98307-2224 | Q92: 100 | S92: SIM | T92: CUMPRIDO | U92: =Table_516[[#This Row],[VALOR]]-Table_516[[#This Row],[ CUSTO]] -> 150
B93: 45798 | D93: Rebeca - Prolicred e Prescred | E93: 11 96538-1745 | F93: Conciliação - Presencial | G93: 1050570-43.2024.8.26.0224 | H93: 45804 | I93: 0.58333333 | J93: CEJUSC/FIG - Av. São Luiz, 315, Vl.Rosália | K93: Guarulhos - SP | L93: 270 | N93: CUMPRIDO | O93: Arlen Mota | P93: 11 99543-2449 | Q93: 130 | S93: SIM | T93: CUMPRIDO | U93: =Table_516[[#This Row],[VALOR]]-Table_516[[#This Row],[ CUSTO]] -> 140
B94: 45784 | D94: Jessica Nunes | E94: 351 936 331 691 | F94: Certidão de Cartório | G94: Camila Marques Freitas Ferreira da Silva | H94: 45804 | J94: Cartório de Registro Civil 1º Subdistrito | K94: Santos - SP | L94: =300+161.88 -> 461.88 | N94: CUMPRIDO | O94: Nelson Hidalgo (cartório) | Q94: 161.88 | S94: SIM | T94: CUMPRIDO | U94: =Table_516[[#This Row],[VALOR]]-Table_516[[#This Row],[ CUSTO]] -> 300
B95: 45776 | D95: Laís Duarte | E95: 34 8864-3914 | F95: Inicial - Presencial | H95: 45805 | I95: 0.52777778 | J95: 1ª Vara do Trabalho | K95: Ribeirão Preto - SP | L95: 200 | N95: CUMPRIDO | O95: Mayara Belfort | P95: 16 99138-1367 | Q95: 60 | S95: SIM | T95: CUMPRIDO | U95: =Table_516[[#This Row],[VALOR]]-Table_516[[#This Row],[ CUSTO]] -> 140
B96: 45797 | D96: Bruno Magalhães | E96: 62 9166-2415 | F96: Inicial - Presencial | G96: RAFAEL VIEIRA ROSA | H96: 45805 | I96: 0.51041667 | J96: 2ª Vara do Trabalho | K96: Cascavel - PR | L96: 300 | N96: CUMPRIDO | O96: Nayara dos santos Gaspar de Jesus | P96: 45 9902-6902 | Q96: 80 | S96: SIM | T96: CUMPRIDO | U96: =Table_516[[#This Row],[VALOR]]-Table_516[[#This Row],[ CUSTO]] -> 220
B97: 45800 | D97: LACOSTA ADVOGADOS | E97: 21 95922-4000 / 11 91039-6920 | F97: Audiência | H97: 45805 | I97: 0.45833333 | J97: 1ª Vara do Trabalho | K97: Praia Grande - SP | L97: =150+100 -> 250 | N97: CUMPRIDO | O97: IRB - Isabelle | P97: 13 98804-4390 | Q97: =80+50 -> 130 | S97: SIM | T97: CUMPRIDO | U97: =Table_516[[#This Row],[VALOR]]-Table_516[[#This Row],[ CUSTO]] -> 120
B98: 45800 | D98: Fett Advogados Bruna Ferracini | E98: 51 9184-8885 | F98: Instrução - Presencial | G98: 1001822-27.2024.5.02.0473 | H98: 45805 | I98: 0.39583333 | J98: 3ª Vara do Trabalho | K98: São Caetano do Sul - SP | L98: 200 | N98: CUMPRIDO | O98: Natacha Caskanlian Aloi | P98: 11 99359-5566 | Q98: 70 | S98: SIM | T98: CUMPRIDO | U98: =Table_516[[#This Row],[VALOR]]-Table_516[[#This Row],[ CUSTO]] -> 130
B99: 45800 | D99: Fett Advogados Bruna Ferracini | E99: 51 9184-8885 | F99: Instrução - Presencial | G99: 0020029-29.2025.5.04.0141 | H99: 45805 | I99: 0.40625 | J99: Posto da Justiça do Trabalho | K99: São Lourenço do Sul - RS | L99: 200 | N99: CUMPRIDO | O99: Braian dos Santos Rios | P99: 53 8121-0860 | Q99: 160 | S99: SIM | T99: CUMPRIDO | U99: =Table_516[[#This Row],[VALOR]]-Table_516[[#This Row],[ CUSTO]] -> 40
B100: 45803 | D100: Jessica | E100: 41 9685-0539 | F100: Coleta de Assinaturas | G100: OSVALDO LIMA OLIVEIRA | H100: 45805 | I100: 0.625 | J100: OAB da cidade | K100: Itaberaba - BA | L100: 350 | N100: CUMPRIDO | O100: Arlete do Nascimento Rocha | P100: 75 9164-2459 | Q100: 100 | S100: SIM | T100: CUMPRIDO | U100: =Table_516[[#This Row],[VALOR]]-Table_516[[#This Row],[ CUSTO]] -> 250
B101: 45803 | D101: Andre Oliveira | E101: 19 98127-4386 | F101: UNA Presencial | G101: 1000438-30.2025.5.02.0041 | H101: 45805 | I101: 0.69444444 | J101: 41ª Vara do Trabalho da Barra Funda | K101: São Paulo - SP | L101: 200 | M101: ok | N101: CUMPRIDO | O101: Joao Tomaz da Silva | P101: 11 97377-8980 | Q101: 70 | S101: SIM | T101: CUMPRIDO | U101: =Table_516[[#This Row],[VALOR]]-Table_516[[#This Row],[ CUSTO]] -> 130
B102: 45805 | D102: Jessica | E102: 41 9685-0539 | F102: Coleta de Assinaturas | H102: 45806 | J102: 5ª Vara Federal | K102: Aracaju - SE | L102: 150 | N102: CUMPRIDO | O102: Andrezza da Silva Bezerra | P102: 79 9920-5269 | Q102: 70 | S102: SIM | T102: CUMPRIDO | U102: =Table_516[[#This Row],[VALOR]]-Table_516[[#This Row],[ CUSTO]] -> 80
...

Sheet JUNHO
B2: CONTROLE DE DILIGÊNCIAS
B4: SOLICITAÇÃO | C4: Nº. DOC9 | D4: SOLICITANTE | E4: TEL. | F4: TIPO DE DILIGÊNCIA | G4: Processo | H4: DATA | I4: HORA | J4: LOCAL | K4: Cidade - UF | L4: VALOR | M4: DATA PAG | N4: PAGAM. | O4: CONTRATADO | P4: TEL. 2 | Q4: CUSTO | R4: PRAZO | S4: PAGO | T4: STATUS | U4: LUCRO
B5: 45831 | D5: Thiago Coriolano | E5: 11 98775-8123 | F5: Audiência | H5: 45831 | I5: 0.41666667 | J5: 85ª Vara do Trabalho da Barra Funda | K5: São Paulo - SP | N5: CUMPRIDO | O5: Thatyane Veiga da Hora Lisboa | P5: 11 94792-7729 | Q5: 50 | S5: SIM | T5: CUMPRIDO | U5: =Table_518[[#This Row],[VALOR]]-Table_518[[#This Row],[ CUSTO]] -> -50
B6: 45807 | D6: Leonardo - Advocacia Soller | E6: 11 95657-2522 / 11 96606-8260 | F6: Audiência | H6: 45810 | I6: 0.52777778 | J6: JEC | K6: Limoeiro - PE | L6: 200 | N6: CUMPRIDO | O6: Elmano Filho | P6: 81 9723-2740 | Q6: 200 | S6: SIM | T6: CUMPRIDO | U6: =Table_518[[#This Row],[VALOR]]-Table_518[[#This Row],[ CUSTO]] -> 0
B7: 45814 | D7: Gabriel Luna | E7: 11 99323-0874 | F7: Instrução - Presencial | G7: 0010790-41.2023.5.15.0116 | H7: 45820 | I7: 0.63194444 | J7: Vara do Trabalho | K7: Tatuí - SP | N7: CUMPRIDO | O7: Sandra Lenhate dos Santos | P7: 11 99795-1181 | S7: SIM | T7: CUMPRIDO | U7: =Table_518[[#This Row],[VALOR]]-Table_518[[#This Row],[ CUSTO]] -> 0
D8: Ana Mirela | E8: 82 9903-7220 | F8: Conciliação - Presencial | U8: =Table_518[[#This Row],[VALOR]]-Table_518[[#This Row],[ CUSTO]] -> 0
U9: =Table_518[[#This Row],[VALOR]]-Table_518[[#This Row],[ CUSTO]] -> 0
B10: 45810 | D10: Vinicius Andrade | E10: 11 91078-8746 | F10: Inicial - Presencial | H10: 45811 | I10: 0.35416667 | J10: 2ª | K10: Coronel Fabriciano - MG | L10: 70 | N10: CUMPRIDO | O10: Geiciele Paula da Rosa | P10: 42 9945-0178 | Q10: 40 | R10: ok | S10: SIM | T10: CUMPRIDO | U10: =Table_518[[#This Row],[VALOR]]-Table_518[[#This Row],[ CUSTO]] -> 30
B11: 45810 | D11: Vinicius Andrade | E11: 11 91078-8746 | F11: Inicial - Presencial | H11: 45811 | I11: 0.36111111 | J11: 7ª | K11: Belo Horizonte - MG | L11: 70 | N11: CUMPRIDO | O11: Geiciele Paula da Rosa | P11: 42 9945-0178 | Q11: 40 | R11: ok | S11: SIM | T11: CUMPRIDO | U11: =Table_518[[#This Row],[VALOR]]-Table_518[[#This Row],[ CUSTO]] -> 30
B12: 45810 | D12: Vinicius Andrade | E12: 11 91078-8746 | F12: Inicial - Presencial | H12: 45811 | I12: 0.39583333 | J12: 2ª | K12: Assis - SP | L12: 70 | N12: CUMPRIDO | O12: Geiciele Paula da Rosa | P12: 42 9945-0178 | Q12: 40 | R12: ok | S12: SIM | T12: CUMPRIDO | U12: =Table_518[[#This Row],[VALOR]]-Table_518[[#This Row],[ CUSTO]] -> 30
B13: 45810 | D13: Vinicius Andrade | E13: 11 91078-8746 | F13: Inicial - Presencial | H13: 45812 | I13: 0.45833333 | J13: 1ª | K13: Umuarama - PR | L13: 70 | N13: CUMPRIDO | O13: Geiciele Paula da Rosa | P13: 42 9945-0178 | Q13: 40 | S13: SIM | T13: CUMPRIDO | U13: =Table_518[[#This Row],[VALOR]]-Table_518[[#This Row],[ CUSTO]] -> 30
B14: 45810 | D14: Vinicius Andrade | E14: 11 91078-8746 | F14: Inicial - Presencial | H14: 45812 | I14: 0.65277778 | J14: 2ª | K14: Anápolis - GO | L14: 70 | N14: CUMPRIDO | O14: Geiciele Paula da Rosa | P14: 42 9945-0178 | Q14: 40 | S14: SIM | T14: CUMPRIDO | U14: =Table_518[[#This Row],[VALOR]]-Table_518[[#This Row],[ CUSTO]] -> 30
B15: 45810 | D15: Vinicius Andrade | E15: 11 91078-8746 | F15: Conciliação - Presencial | H15: 45813 | I15: 0.39236111 | J15: CEJUSC | K15: Barueri - SP | L15: 70 | N15: CUMPRIDO | O15: Geiciele Paula da Rosa | P15: 42 9945-0178 | Q15: 40 | S15: SIM | T15: CUMPRIDO | U15: =Table_518[[#This Row],[VALOR]]-Table_518[[#This Row],[ CUSTO]] -> 30
B16: 45810 | D16: Vinicius Andrade | E16: 11 91078-8746 | F16: Inicial - Presencial | H16: 45813 | I16: 0.44791667 | J16: 1ª | K16: Franca - SP | L16: 70 | N16: CUMPRIDO | O16: Geiciele Paula da Rosa | P16: 42 9945-0178 | Q16: 40 | S16: SIM | T16: CUMPRIDO | U16: =Table_518[[#This Row],[VALOR]]-Table_518[[#This Row],[ CUSTO]] -> 30
B17: 45810 | D17: Vinicius Andrade | E17: 11 91078-8746 | F17: Inicial - Presencial | H17: 45813 | I17: 0.54861111 | J17: ÚNICA | K17: Tatuí - SP | L17: 70 | N17: CUMPRIDO | O17: Geiciele Paula da Rosa | P17: 42 9945-0178 | Q17: 40 | S17: SIM | T17: CUMPRIDO | U17: =Table_518[[#This Row],[VALOR]]-Table_518[[#This Row],[ CUSTO]] -> 30
B18: 45810 | D18: Vinicius Andrade | E18: 11 91078-8746 | F18: Inicial - Presencial | H18: 45813 | I18: 0.5625 | J18: 4ª | K18: Campo Grande - MT | L18: 70 | N18: CUMPRIDO | O18: Geiciele Paula da Rosa | P18: 42 9945-0178 | Q18: 40 | S18: SIM | T18: CUMPRIDO | U18: =Table_518[[#This Row],[VALOR]]-Table_518[[#This Row],[ CUSTO]] -> 30
B19: 45810 | D19: Vinicius Andrade | E19: 11 91078-8746 | F19: Inicial - Presencial | H19: 45813 | I19: 0.60416667 | J19: ÚNICA | K19: Itapeva - SP | L19: 70 | N19: CUMPRIDO | O19: Geiciele Paula da Rosa | P19: 42 9945-0178 | Q19: 40 | S19: SIM | T19: CUMPRIDO | U19: =Table_518[[#This Row],[VALOR]]-Table_518[[#This Row],[ CUSTO]] -> 30
B20: 45810 | D20: Vinicius Andrade | E20: 11 91078-8746 | F20: Inicial - Presencial | H20: 45814 | I20: 0.38194444 | J20: 2ª | K20: Taubaté - SP | L20: 70 | N20: CUMPRIDO | O20: Geiciele Paula da Rosa | P20: 42 9945-0178 | Q20: 40 | S20: SIM | T20: CUMPRIDO | U20: =Table_518[[#This Row],[VALOR]]-Table_518[[#This Row],[ CUSTO]] -> 30
B21: 45821 | D21: Vinicius Andrade | E21: 11 91078-8746 | F21: CONCILIAÇÃO | G21: 0024838-36.2025.5.24.0002 | H21: 45824 | I21: 0.56944444 | J21: 2ª | K21: Campo Grande | L21: 70 | N21: CUMPRIDO | O21: Geiciele Paula da Rosa | P21: 42 9945-0178 | Q21: 40 | S21: SIM | T21: CUMPRIDO | U21: =Table_518[[#This Row],[VALOR]]-Table_518[[#This Row],[ CUSTO]] -> 30
B22: 45821 | D22: Vinicius Andrade | E22: 11 91078-8746 | F22: CONCILIAÇÃO | G22: 0100686-72.2025.5.01.0033 | H22: 45825 | I22: 0.37152778 | J22: 33ª | K22: Rio De Janeiro | L22: 70 | N22: CUMPRIDO | O22: Geiciele Paula da Rosa | P22: 42 9945-0178 | Q22: 40 | S22: SIM | T22: CUMPRIDO | U22: =Table_518[[#This Row],[VALOR]]-Table_518[[#This Row],[ CUSTO]] -> 30
B23: 45821 | D23: Vinicius Andrade | E23: 11 91078-8746 | F23: CONCILIAÇÃO | G23: 0000358-13.2025.5.12.0039 | H23: 45825 | I23: 0.41319444 | J23: 3ª | K23: Blumenau | L23: 70 | N23: CUMPRIDO | O23: Geiciele Paula da Rosa | P23: 42 9945-0178 | Q23: 40 | S23: SIM | T23: CUMPRIDO | U23: =Table_518[[#This Row],[VALOR]]-Table_518[[#This Row],[ CUSTO]] -> 30
B24: 45821 | D24: Vinicius Andrade | E24: 11 91078-8746 | F24: INICIAL | G24: 0000013-79.2025.5.09.0411 | H24: 45825 | I24: 0.55902778 | J24: 3ª | K24: Paranaguá | L24: 70 | N24: CUMPRIDO | O24: Geiciele Paula da Rosa | P24: 42 9945-0178 | Q24: 40 | S24: SIM | T24: CUMPRIDO | U24: =Table_518[[#This Row],[VALOR]]-Table_518[[#This Row],[ CUSTO]] -> 30
B25: 45821 | D25: Vinicius Andrade | E25: 11 91078-8746 | F25: INICIAL | G25: 0020577-68.2025.5.04.0104 | H25: 45825 | I25: 0.65972222 | J25: 4ª | K25: Pelotas | L25: 70 | N25: CUMPRIDO | O25: Geiciele Paula da Rosa | P25: 42 9945-0178 | Q25: 40 | S25: SIM | T25: CUMPRIDO | U25: =Table_518[[#This Row],[VALOR]]-Table_518[[#This Row],[ CUSTO]] -> 30
B26: 45821 | D26: Vinicius Andrade | E26: 11 91078-8746 | F26: INICIAL | G26: 0010594-20.2025.5.03.0089 | H26: 45826 | I26: 0.34583333 | J26: 3ª | K26: Coronel Fabriciano | L26: 70 | N26: CUMPRIDO | O26: Geiciele Paula da Rosa | P26: 42 9945-0178 | Q26: 40 | S26: SIM | T26: CUMPRIDO | U26: =Table_518[[#This Row],[VALOR]]-Table_518[[#This Row],[ CUSTO]] -> 30
B27: 45821 | D27: Vinicius Andrade | E27: 11 91078-8746 | F27: INICIAL | G27: 0010388-73.2025.5.03.0002 | H27: 45826 | I27: 0.36111111 | J27: 2ª | K27: Belo Horizonte | L27: 70 | N27: CUMPRIDO | O27: Geiciele Paula da Rosa | P27: 42 9945-0178 | Q27: 40 | S27: SIM | T27: CUMPRIDO | U27: =Table_518[[#This Row],[VALOR]]-Table_518[[#This Row],[ CUSTO]] -> 30
B28: 45821 | D28: Vinicius Andrade | E28: 11 91078-8746 | F28: INICIAL | G28: 0000249-88.2025.5.09.0004 | H28: 45826 | I28: 0.57638889 | J28: 4ª | K28: Curitiba | L28: 70 | N28: CUMPRIDO | O28: Geiciele Paula da Rosa | P28: 42 9945-0178 | Q28: 40 | S28: SIM | T28: CUMPRIDO | U28: =Table_518[[#This Row],[VALOR]]-Table_518[[#This Row],[ CUSTO]] -> 30
B29: 45826 | D29: Vinicius Andrade | E29: 11 91078-8746 | F29: INICIAL | G29: 0000481-05.2025.5.12.0041 | H29: 45831 | I29: 0.56944444 | J29: 2ª | K29: Tubarão | L29: 70 | N29: CUMPRIDO | O29: Geiciele Paula da Rosa | P29: 42 9945-0178 | Q29: 40 | S29: SIM | T29: CUMPRIDO | U29: =Table_518[[#This Row],[VALOR]]-Table_518[[#This Row],[ CUSTO]] -> 30
B30: 45826 | D30: Vinicius Andrade | E30: 11 91078-8746 | F30: INICIAL | G30: 0000689-90.2025.5.09.0002 | H30: 45831 | I30: 0.57638889 | J30: 2ª | K30: Curitiba | L30: 70 | N30: CUMPRIDO | O30: Geiciele Paula da Rosa | P30: 42 9945-0178 | Q30: 40 | S30: SIM | T30: CUMPRIDO | U30: =Table_518[[#This Row],[VALOR]]-Table_518[[#This Row],[ CUSTO]] -> 30
B31: 45826 | D31: Vinicius Andrade | E31: 11 91078-8746 | F31: INICIAL | G31: 0000783-30.2025.5.18.0053 | H31: 45832 | I31: 0.4375 | J31: 3ª | K31: Anápolis | L31: 70 | N31: CUMPRIDO | O31: Geiciele Paula da Rosa | P31: 42 9945-0178 | Q31: 40 | S31: SIM | T31: CUMPRIDO | U31: =Table_518[[#This Row],[VALOR]]-Table_518[[#This Row],[ CUSTO]] -> 30
B32: 45826 | D32: Vinicius Andrade | E32: 11 91078-8746 | F32: CONCILIAÇÃO | G32: 0000663-62.2025.5.09.0012 | H32: 45832 | I32: 0.54166667 | J32: 1ª | K32: Curitiba | L32: 70 | N32: CUMPRIDO | O32: Geiciele Paula da Rosa | P32: 42 9945-0178 | Q32: 40 | S32: SIM | T32: CUMPRIDO | U32: =Table_518[[#This Row],[VALOR]]-Table_518[[#This Row],[ CUSTO]] -> 30
... B36: 45826 | D36: Vinicius Andrade | E36: 11 91078-8746 | F36: CONCILIAÇÃO | G36: 1001253-26.2021.5.02.0313 | H36: 45834 | I36: 0.41666667 | J36: CEJUSC | K36: Guarulhos | L36: 70 | N36: CUMPRIDO | O36: Geiciele Paula da Rosa | P36: 42 9945-0178 | Q36: 40 | S36: SIM | T36: CUMPRIDO | U36: =Table_518[[#This Row],[VALOR]]-Table_518[[#This Row],[ CUSTO]] -> 30
B37: 45835 | D37: Vinicius Andrade | E37: 11 91078-8746 | F37: INICIAL | G37: 0016606-18.2025.5.16.0015 | H37: 45838 | I37: 0.375 | J37: 5ª | K37: São Luís | L37: 70 | M37: ok | N37: CUMPRIDO | O37: Geiciele Paula da Rosa | P37: 42 9945-0178 | Q37: 40 | S37: SIM | T37: CUMPRIDO | U37: =Table_518[[#This Row],[VALOR]]-Table_518[[#This Row],[ CUSTO]] -> 30
B38: 45814 | D38: Vinicius Andrade | E38: 11 91078-8746 | F38: INICIAL | G38: 0000327-14.2025.5.05.0192 | H38: 45817 | I38: 0.40277778 | L38: 70 | N38: CUMPRIDO | O38: Amanda Trindade | P38: 11 96931-8379 | Q38: 30 | S38: SIM | T38: CUMPRIDO | U38: =Table_518[[#This Row],[VALOR]]-Table_518[[#This Row],[ CUSTO]] -> 40
B39: 45814 | D39: Vinicius Andrade | E39: 11 91078-8746 | F39: INICIAL | G39: 0000327-14.2025.5.05.0192 | H39: 45818 | I39: 0.35763889 | L39: 70 | N39: CUMPRIDO | O39: Amanda Trindade | P39: 11 96931-8379 | Q39: 30 | S39: SIM | T39: CUMPRIDO | U39: =Table_518[[#This Row],[VALOR]]-Table_518[[#This Row],[ CUSTO]] -> 40
B40: 45814 | D40: Vinicius Andrade | E40: 11 91078-8746 | F40: INICIAL | G40: 0010436-39.2025.5.15.0021 | H40: 45818 | I40: 0.41805556 | L40: 70 | N40: CUMPRIDO | O40: Amanda Trindade | P40: 11 96931-8379 | Q40: 30 | S40: SIM | T40: CUMPRIDO | U40: =Table_518[[#This Row],[VALOR]]-Table_518[[#This Row],[ CUSTO]] -> 40
B41: 45814 | D41: Vinicius Andrade | E41: 11 91078-8746 | F41: INICIAL | G41: 0013294-10.2024.5.15.0011 | H41: 45818 | I41: 0.57777778 | L41: 70 | N41: CUMPRIDO | O41: Amanda Trindade | P41: 11 96931-8379 | Q41: 30 | S41: SIM | T41: CUMPRIDO | U41: =Table_518[[#This Row],[VALOR]]-Table_518[[#This Row],[ CUSTO]] -> 40
B42: 45814 | D42: Vinicius Andrade | E42: 11 91078-8746 | F42: CONCILIAÇÃO | G42: 0000373-72.2025.5.09.0133 | H42: 45818 | I42: 0.67708333 | L42: 70 | N42: CUMPRIDO | O42: Gabriela Amélia Alfano | P42: 11 98075-5145 | Q42: 30 | S42: SIM | T42: CUMPRIDO | U42: =Table_518[[#This Row],[VALOR]]-Table_518[[#This Row],[ CUSTO]] -> 40
B43: 45814 | D43: Vinicius Andrade | E43: 11 91078-8746 | F43: CONCILIAÇÃO | G43: 0000388-41.2025.5.09.0133 | H43: 45818 | I43: 0.69791667 | L43: 70 | N43: CUMPRIDO | O43: Gabriela Amélia Alfano | P43: 11 98075-5145 | Q43: 30 | S43: SIM | T43: CUMPRIDO | U43: =Table_518[[#This Row],[VALOR]]-Table_518[[#This Row],[ CUSTO]] -> 40
B44: 45814 | D44: Vinicius Andrade | E44: 11 91078-8746 | F44: INICIAL | G44: 0012261-54.2024.5.15.0085 | H44: 45819 | I44: 0.57291667 | L44: 70 | N44: CUMPRIDO | O44: Amanda Trindade | P44: 11 96931-8379 | Q44: 30 | S44: SIM | T44: CUMPRIDO | U44: =Table_518[[#This Row],[VALOR]]-Table_518[[#This Row],[ CUSTO]] -> 40
B45: 45814 | D45: Vinicius Andrade | E45: 11 91078-8746 | F45: INICIAL | G45: 0010633-97.2025.5.03.0030 | H45: 45820 | I45: 0.35763889 | L45: 70 | N45: CUMPRIDO | O45: Amanda Trindade | P45: 11 96931-8379 | Q45: 30 | S45: SIM | T45: CUMPRIDO | U45: =Table_518[[#This Row],[VALOR]]-Table_518[[#This Row],[ CUSTO]] -> 40
B46: 45814 | D46: Vinicius Andrade | E46: 11 91078-8746 | F46: INICIAL | G46: 0024271-96.2025.5.24.0004 | H46: 45820 | I46: 0.67361111 | L46: 70 | N46: CUMPRIDO | O46: Amanda Trindade | P46: 11 96931-8379 | Q46: 30 | S46: SIM | T46: CUMPRIDO | U46: =Table_518[[#This Row],[VALOR]]-Table_518[[#This Row],[ CUSTO]] -> 40
B47: 45814 | D47: Vinicius Andrade | E47: 11 91078-8746 | F47: INICIAL | G47: 0000899-59.2025.5.18.0013 | H47: 45821 | I47: 0.375 | L47: 70 | N47: CUMPRIDO | O47: Amanda Trindade | P47: 11 96931-8379 | Q47: 30 | S47: SIM | T47: CUMPRIDO | U47: =Table_518[[#This Row],[VALOR]]-Table_518[[#This Row],[ CUSTO]] -> 40
B48: 45814 | D48: Vinicius Andrade | E48: 11 91078-8746 | F48: INICIAL | G48: 0000470-11.2025.5.09.0024 | H48: 45821 | I48: 0.45138889 | L48: 70 | N48: CUMPRIDO | O48: Amanda Trindade | P48: 11 96931-8379 | Q48: 30 | S48: SIM | T48: CUMPRIDO | U48: =Table_518[[#This Row],[VALOR]]-Table_518[[#This Row],[ CUSTO]] -> 40
B49: 45814 | D49: Vinicius Andrade | E49: 11 91078-8746 | F49: CONCILIAÇÃO | G49: 1000164-06.2025.5.02.0255 | H49: 45821 | I49: 0.54166667 | L49: 70 | N49: CUMPRIDO | O49: Amanda Trindade | P49: 11 96931-8379 | Q49: 30 | S49: SIM | T49: CUMPRIDO | U49: =Table_518[[#This Row],[VALOR]]-Table_518[[#This Row],[ CUSTO]] -> 40
B50: 45814 | D50: LACOSTA ADVOGADOS | E50: 21 95922-4000 / 11 91039-6920 | F50: Despacho | G50: 1000394-81.2024.5.02.0029 | H50: 45814 | J50: 29ª Vara do Trabalho da Barra Funda | K50: São Paulo - SP | L50: 100 | N50: CUMPRIDO | O50: Rafael Fernandes | P50: 11 99939-8419 | Q50: 60 | S50: SIM | T50: CUMPRIDO | U50: =Table_518[[#This Row],[VALOR]]-Table_518[[#This Row],[ CUSTO]] -> 40
B51: 45811 | D51: Jessica | E51: 41 9685-0539 | F51: Extração de fotos | G51: HERMES MEDINA COELI | H51: 45812 | I51: 0.41666667 | J51: Rua Padre Zeferino, n°1413, Bairro: Fabricio | K51: Uberaba - MG | L51: 100 | M51: ok | N51: CUMPRIDO | O51: Júlya Dias | P51: 34 9255-7010 / 34 9285-7115 | Q51: 50 | S51: SIM | T51: CUMPRIDO | U51: =Table_518[[#This Row],[VALOR]]-Table_518[[#This Row],[ CUSTO]] -> 50
B52: 45817 | D52: Adriana Arruda | E52: 19 3303-1135 | F52: Cópias | G52: 0034205-21.2017.4.03.6182 | H52: 45821 | J52: Justiça Federal | K52: São Paulo - SP | L52: 100 | N52: CUMPRIDO | O52: Joao Tomaz da Silva | P52: 11 97377-8980 | Q52: 50 | S52: SIM | T52: CUMPRIDO | U52: =Table_518[[#This Row],[VALOR]]-Table_518[[#This Row],[ CUSTO]] -> 50
B53: 45824 | D53: David Angelo Barros Figueiroa | E53: 81 8788-5448 | F53: Cópia | H53: 45824 | J53: 15º DP | K53: São Paulo - SP | L53: 100 | N53: CUMPRIDO | O53: Francisco Bruno | P53: 11 95466-5684 | Q53: 50 | R53: desv | S53: SIM | T53: CUMPRIDO | U53: =Table_518[[#This Row],[VALOR]]-Table_518[[#This Row],[ CUSTO]] -> 50
B54: 45808 | D54: Igor Matheus Rezende | E54: 62 8288-5957 | F54: Conciliação - Presencial | H54: 45810 | I54: 0.47916667 | J54: 6ª Vara do Trabalho | K54: Teresina - PI | L54: 150 | N54: CUMPRIDO | O54: Aimêe Portela Pereira | P54: 86 8806-7898 | Q54: 100 | S54: SIM | T54: CUMPRIDO | U54: =Table_518[[#This Row],[VALOR]]-Table_518[[#This Row],[ CUSTO]] -> 50
B55: 45817 | D55: Rodrigo Bezerra | E55: 11 99360-4364 | F55: Acompanhamento | G55: Esse acompanhamento será para o advogado contratante ele irá se reuinir com a empresa cliente dele e quer q a dra esteja junto para entender as necessidades da empresa para melhor poder atuar na audiência de instrução do dia 11 | H55: 45818 | I55: 0.45138889 | J55: Rua Goiás, 110, Chácara do Solar I | K55: Santana de Parnaíba - SP | L55: 150 | N55: CUMPRIDO | O55: Josimeire de Jesus Rocha | P55: 11 99553-6099 | Q55: 100 | S55: SIM | T55: CUMPRIDO | U55: =Table_518[[#This Row],[VALOR]]-Table_518[[#This Row],[ CUSTO]] -> 50
B56: 45814 | D56: Beatriz Aragão & Bernardo | E56: 85 3252-2939 - 85 8405-1478 | F56: UNA - Presencial | G56: 0000173-24.2025.5.05.0021 | H56: 45820 | I56: 0.37152778 | J56: 21ª Vara do Trabalho | K56: Salvador - BA | L56: 150 | N56: CUMPRIDO | O56: Rodrigo Daniel | P56: 71 9914-4147 | Q56: 100 | S56: SIM | T56: CUMPRIDO | U56: =Table_518[[#This Row],[VALOR]]-Table_518[[#This Row],[ CUSTO]] -> 50
B57: 45814 | D57: Beatriz Aragão & Bernardo | E57: 85 3252-2939 - 85 8405-1478 | F57: UNA - Presencial | G57: 0000491-76.2025.5.13.0023 | H57: 45820 | I57: 0.4375 | J57: 4ª Vara do Trabalho | K57: Campina Grande - PB | L57: 150 | N57: CUMPRIDO | O57: Thalyta Nóbrega | P57: 83 9620-9976 | Q57: 100 | S57: SIM | T57: CUMPRIDO | U57: =Table_518[[#This Row],[VALOR]]-Table_518[[#This Row],[ CUSTO]] -> 50
B58: 45828 | D58: Beatriz Aragão & Bernardo | E58: 85 3252-2939 - 85 8405-1478 | F58: UNA - Presencial | G58: 0000529-86.2025.5.09.0092 | H58: 45834 | I58: 0.38888889 | J58: Vara do Trabalho | K58: Cianorte - PR | L58: 150 | N58: CUMPRIDO | O58: Karen Beltrame | P58: 44 9937-9842 | Q58: 100 | R58: desv | S58: SIM | T58: CUMPRIDO | U58: =Table_518[[#This Row],[VALOR]]-Table_518[[#This Row],[ CUSTO]] -> 50
B59: 45820 | D59: Beatriz Aragão & Bernardo | E59: 85 3252-2939 - 85 8405-1478 | F59: Inicial - Presencial | G59: 0000417-13.2025.5.05.0195 | H59: 45824 | I59: 0.375 | J59: 5ª Vara do Trabalho | K59: Feira de Santana - BA | L59: 170 | N59: CUMPRIDO | O59: Tiago Micheli | P59: 75 8198-6682 | Q59: 120 | S59: SIM | T59: CUMPRIDO | U59: =Table_518[[#This Row],[VALOR]]-Table_518[[#This Row],[ CUSTO]] -> 50
B60: 45827 | D60: David Angelo Barros Figueiroa | E60: 81 8788-5448 | F60: Conciliação - Presencial | G60: 5001870-82.2025.8.21.0058 | H60: 45834 | I60: 0.85416667 | J60: JEC | K60: Nova Prata - RS | L60: 50 | N60: CUMPRIDO | O60: Sabrina Censi Fiorio | P60: 54 9908-2696 | S60: SIM | T60: CUMPRIDO | U60: =Table_518[[#This Row],[VALOR]]-Table_518[[#This Row],[ CUSTO]] -> 50
B61: 45813 | D61: Mirlla - BCC Advocacia | E61: 61 9831-3480 | F61: Conciliação - Presencial | G61: 1004001-89.2025.8.26.0016 | H61: 45818 | I61: 0.66666667 | J61: Rua Boa vista, nº 76- 3º andar- Centro Histórico | K61: São Paulo - SP | L61: 120 | N61: CUMPRIDO | O61: Yasmin Girotto | P61: 11 91343-8650 | Q61: 60 | R61: desv | S61: SIM | T61: CUMPRIDO | U61: =Table_518[[#This Row],[VALOR]]-Table_518[[#This Row],[ CUSTO]] -> 60
B62: 45829 | D62: Murilo Leal | E62: 38 9111-9227 | F62: Conciliação - Presencial | H62: 45833 | I62: 0.5625 | J62: Rua Vergueiro, 835, sala 04 - 5º andar - Paraíso | K62: São Paulo - SP | L62: 120 | N62: CUMPRIDO | O62: Joao Tomaz da Silva | P62: 11 97377-8980 | Q62: 60 | S62: SIM | T62: CUMPRIDO | U62: =Table_518[[#This Row],[VALOR]]-Table_518[[#This Row],[ CUSTO]] -> 60
B63: 45817 | D63: Renan | E63: 44 9863-0627 | F63: Audiência | G63: 1002403-59.2024.5.02.0241 | H63: 45818 | I63: 0.54166667 | J63: 1ª Vara do Trabalho | K63: Cotia - SP | L63: 150 | N63: CUMPRIDO | O63: Luciana Iamamura Gonzalez | P63: 11 97990-8181 | Q63: 90 | S63: SIM | T63: CUMPRIDO | U63: =Table_518[[#This Row],[VALOR]]-Table_518[[#This Row],[ CUSTO]] -> 60
B64: 45817 | D64: Gabriel Luna | E64: 11 99323-0874 | F64: UNA - Presencial | G64: 0011708-45.2023.5.15.0116 | H64: 45819 | I64: 0.375 | L64: =150+120 -> 270 | N64: CUMPRIDO | O64: Sandra Lenhate dos Santos | P64: 11 99795-1181 | Q64: =130+80 -> 210 | S64: SIM | T64: CUMPRIDO | U64: =Table_518[[#This Row],[VALOR]]-Table_518[[#This Row],[ CUSTO]] -> 60
B65: 45806 | D65: Sepulveda Advogados | E65: 19 99651-8840 | F65: UNA - Presencial | H65: 45810 | I65: 0.64583333 | J65: 53ª Vara do Trabalho da Barra Funda | K65: São Paulo - SP | L65: 150 | N65: CUMPRIDO | O65: Amanda Pivott | P65: 11 94857-0549 | Q65: 70 | S65: SIM | T65: CUMPRIDO | U65: =Table_518[[#This Row],[VALOR]]-Table_518[[#This Row],[ CUSTO]] -> 80
B66: 45810 | D66: David Angelo Barros Figueiroa | E66: 81 8788-5448 | F66: Conciliação - Presencial | G66: 0814358-50.2025.8.12.0001 | H66: 45810 | I66: 0.54166667 | J66: CEJUSC | K66: Campo Grande - MT | L66: 150 | N66: CUMPRIDO | O66: Anna Cláudia Santana | P66: 67 8424-4131 | Q66: 70 | S66: SIM | T66: CUMPRIDO | U66: =Table_518[[#This Row],[VALOR]]-Table_518[[#This Row],[ CUSTO]] -> 80
B67: 45814 | D67: Beatriz Aragão & Bernardo | E67: 85 3252-2939 - 85 8405-1478 | F67: UNA - Presencial | G67: 1000810-33.2025.5.02.0702 | H67: 45818 | I67: 0.57291667 | J67: 2ª Vara do Trabalho da Zona Sul | K67: São Paulo - SP | L67: 150 | N67: CUMPRIDO | O67: Mayara Costa | P67: 11 99318-5707 | Q67: 70 | S67: SIM | T67: CUMPRIDO | U67: =Table_518[[#This Row],[VALOR]]-Table_518[[#This Row],[ CUSTO]] -> 80
B68: 45814 | D68: Beatriz Aragão & Bernardo | E68: 85 3252-2939 - 85 8405-1478 | F68: Instrução - Presencial | G68: 0000127-56.2025.5.06.0102 | H68: 45820 | I68: 0.36805556 | J68: 2ª Vara do Trabalho | K68: Olinda - PE | L68: 150 | N68: CUMPRIDO | O68: João Victor Pessôa | P68: 81 9979-6869 | Q68: 70 | S68: SIM | T68: CUMPRIDO | U68: =Table_518[[#This Row],[VALOR]]-Table_518[[#This Row],[ CUSTO]] -> 80
B69: 45821 | D69: Beatriz Aragão & Bernardo | E69: 85 3252-2939 - 85 8405-1478 | F69: UNA - Presencial | G69: 0010487-98.2025.5.03.0016 | H69: 45824 | I69: 0.37152778 | J69: 16ª Vara do Trabalho | K69: Belo Horizonte - MG | L69: 150 | N69: CUMPRIDO | O69: Diogo Ribeiro Cassini | P69: 31 8722-3837 | Q69: 70 | S69: SIM | T69: CUMPRIDO | U69: =Table_518[[#This Row],[VALOR]]-Table_518[[#This Row],[ CUSTO]] -> 80
B70: 45823 | D70: Caio Casemiro | E70: 62 9226-9798 | F70: Conciliação - Presencial | G70: 1004282-69.2025.8.26.0008 | H70: 45824 | I70: 0.5625 | J70: 1ª JEC de Tatuapé | K70: São Paulo - SP | L70: 150 | N70: CUMPRIDO | O70: Marcelo Gurczynska | P70: 11 95798-0936 | Q70: 70 | S70: SIM | T70: CUMPRIDO | U70: =Table_518[[#This Row],[VALOR]]-Table_518[[#This Row],[ CUSTO]] -> 80
B71: 45824 | D71: Sepulveda Advogados | E71: 19 99651-8840 | F71: UNA - Presencial | H71: 45832 | I71: 0.375 | J71: 11ª Vara do Trabalho da Zona Sul | K71: São Paulo - SP | L71: 150 | N71: CUMPRIDO | O71: Amanda Solanich | P71: 11 97951-9771 | Q71: 60 | S71: SIM | T71: CUMPRIDO | U71: =Table_518[[#This Row],[VALOR]]-Table_518[[#This Row],[ CUSTO]] -> 90
B72: 45831 | D72: Sepulveda Advogados | E72: 19 99651-8840 | F72: UNA - Presencial | H72: 45838 | I72: 0.53125 | J72: 3ª Vara do Trabalho da Zona Sul | K72: São Paulo - SP | L72: 150 | N72: CUMPRIDO | O72: Amanda Solanich | P72: 11 97951-9771 | Q72: 60 | S72: SIM | T72: CUMPRIDO | U72: =Table_518[[#This Row],[VALOR]]-Table_518[[#This Row],[ CUSTO]] -> 90
B73: 45821 | D73: Mirlla - BCC Advocacia | E73: 61 9831-3480 | F73: AIJ | H73: 45826 | I73: 0.57291667 | J73: Unidade Avançada de Atendimento das Microempresas e Empresas de Pequeno Porte | K73: São Paulo - SP | L73: 180 | N73: CUMPRIDO | O73: Yasmin Girotto | P73: 11 91343-8650 | Q73: 90 | S73: SIM | T73: CUMPRIDO | U73: =Table_518[[#This Row],[VALOR]]-Table_518[[#This Row],[ CUSTO]] -> 90
B74: 45834 | D74: David Angelo Barros Figueiroa | E74: 81 8788-5448 | F74: Conciliação - Presencial | G74: 0002206-64.2025.8.12.0110 | H74: 45838 | I74: 0.72916667 | J74: 3ª JEC | K74: Campo Grande - MS | L74: 130 | M74: 45840 | N74: CUMPRIDO | O74: Rafael Vicentim Fernandes | P74: 67 9205-3643 | Q74: 30 | S74: SIM | T74: CUMPRIDO | U74: =Table_518[[#This Row],[VALOR]]-Table_518[[#This Row],[ CUSTO]] -> 100
B75: 45811 | D75: Marcia Graças | E75: 11 95190-2626 | F75: Conciliação - Presencial | G75: 0826687-02.2025.8.19.0001 | H75: 45811 | I75: 0.5 | J75: 1ª Vara de Família de Madureira | K75: Rio de Janeiro - RJ | L75: 150 | N75: CUMPRIDO | O75: Murilo Vieira da Costa | P75: 21 96865-2819 | Q75: 50 | S75: SIM | T75: CUMPRIDO | U75: =Table_518[[#This Row],[VALOR]]-Table_518[[#This Row],[ CUSTO]] -> 100
B76: 45810 | D76: Lucas | E76: 31 98271-0829 | F76: Conciliação - Presencial | H76: 45812 | I76: 0.64583333 | J76: João Mendes | K76: São Paulo - SP | L76: 150 | N76: CUMPRIDO | O76: Isabelly Leão | P76: 81 9936-5104 | Q76: 50 | S76: SIM | T76: CUMPRIDO | U76: =Table_518[[#This Row],[VALOR]]-Table_518[[#This Row],[ CUSTO]] -> 100
B77: 45812 | D77: David Angelo Barros Figueiroa | E77: 81 8788-5448 | F77: Cópia | G77: 2146510/25 361/25 | H77: 45813 | J77: 1º DP da Liberdade | K77: São Paulo - SP | L77: 150 | N77: CUMPRIDO | O77: Raiane Antunes | P77: 11 97846-7431 | Q77: 50 | S77: SIM | T77: CUMPRIDO | U77: =Table_518[[#This Row],[VALOR]]-Table_518[[#This Row],[ CUSTO]] -> 100
B78: 45812 | D78: Rodrigo Bezerra | E78: 11 99360-4364 | F78: UNA - Presencial | G78: 1000195-13.2025.5.02.0421 | H78: 45813 | I78: 0.58333333 | J78: 1ª Vara do Trabalho | K78: Santana de Parnaíba - SP | L78: 150 | N78: CUMPRIDO | O78: Joao Tomaz da Silva | P78: 11 97377-8980 | Q78: 50 | S78: SIM | T78: CUMPRIDO | U78: =Table_518[[#This Row],[VALOR]]-Table_518[[#This Row],[ CUSTO]] -> 100
B79: 45833 | D79: Jessica | E79: 41 9685-0539 | F79: Coleta de Assinaturas | G79: Moacir Lima de Brito | H79: 45835 | I79: 0.58333333 | J79: Rua dos Artistas, n. 19, Bairro: Centro | K79: Cachoeira - BA | L79: 150 | M79: ok | N79: CUMPRIDO | O79: Priscilla Felicio Da Silva Matos | P79: 75 9853-2449 | Q79: 50 | S79: SIM | T79: CUMPRIDO | U79: =Table_518[[#This Row],[VALOR]]-Table_518[[#This Row],[ CUSTO]] -> 100
B80: 45807 | D80: Fett Advogados Bruna Ferracini | E80: 51 9184-8885 | F80: Instrução - Presencial | G80: 0020272-59.2025.5.04.0662 | H80: 45811 | I80: 0.40625 | J80: 2ª Vara do Trabalho | K80: Passo Fundo - RS | L80: 200 | N80: CUMPRIDO | O80: Guilherme Varela Gomes | P80: 54 8101-0410 | Q80: 100 | R80: ok | S80: SIM | T80: CUMPRIDO | U80: =Table_518[[#This Row],[VALOR]]-Table_518[[#This Row],[ CUSTO]] -> 100
B81: 45810 | D81: LACOSTA ADVOGADOS | E81: 21 95922-4000 / 11 91039-6920 | F81: Audiência | H81: 45811 | I81: 0.41666667 | J81: Vara do Trabalho | K81: Atibaia - SP | L81: 200 | N81: CUMPRIDO | O81: Anna Paula Almeida de Jesus | P81: 11 98528-5583 | Q81: 100 | R81: ok | S81: SIM | T81: CUMPRIDO | U81: =Table_518[[#This Row],[VALOR]]-Table_518[[#This Row],[ CUSTO]] -> 100
B82: 45812 | D82: David Angelo Barros Figueiroa | E82: 81 8788-5448 | F82: Audiência | H82: 45817 | I82: 0.41666667 | J82: JEC | K82: Chapadão do Sul - MS | L82: 200 | N82: CUMPRIDO | O82: Marla Débora Silva dos Santos | P82: 67 9818-4089 | Q82: 100 | S82: SIM | T82: CUMPRIDO | U82: =Table_518[[#This Row],[VALOR]]-Table_518[[#This Row],[ CUSTO]] -> 100
B83: 45814 | D83: Fett Advogados Bruna Ferracini | E83: 51 9184-8885 | F83: Instrução - Presencial | G83: 0011838-76.2024.5.18.0161 | H83: 45820 | I83: 0.41666667 | J83: Vara do Trabalho | K83: Caldas Novas - GO | L83: 200 | N83: CUMPRIDO | O83: Brenda Calgaroto Santana | P83: 64 9327-1843 | Q83: 100 | R83: desv | S83: SIM | T83: CUMPRIDO | U83: =Table_518[[#This Row],[VALOR]]-Table_518[[#This Row],[ CUSTO]] -> 100
B84: 45829 | D84: Fett Advogados Bruna Ferracini | E84: 51 9184-8885 | F84: Instrução - Presencial | G84: 1003048-47.2024.5.02.0221 | H84: 45831 | I84: 0.56944444 | J84: Vara do Trabalho | K84: Cajamar - SP | L84: 200 | N84: CUMPRIDO | O84: Simone Amaral Rocha da Silva | P84: 11 94771-4082 | Q84: 100 | S84: SIM | T84: CUMPRIDO | U84: =Table_518[[#This Row],[VALOR]]-Table_518[[#This Row],[ CUSTO]] -> 100
B85: 45827 | D85: David Angelo Barros Figueiroa | E85: 81 8788-5448 | F85: Conciliação - Presencial | G85: 5001931-43.2025.8.21.0057 | H85: 45832 | I85: 0.8125 | J85: JEC | K85: Lagoa Vermelha - RS | L85: 200 | N85: CUMPRIDO | O85: Manuella Piardi | P85: 54 9936-5935 | Q85: 100 | S85: SIM | T85: CUMPRIDO | U85: =Table_518[[#This Row],[VALOR]]-Table_518[[#This Row],[ CUSTO]] -> 100
B86: 45829 | D86: Fett Advogados Bruna Ferracini | E86: 51 9184-8885 | F86: UNA - Presencial | G86: 0010553-48.2025.5.03.0026 | H86: 45833 | I86: 0.55208333 | J86: 1ª Vara do Trabalho | K86: Betim - MG | L86: 200 | N86: CUMPRIDO | O86: Marcos Vinicius de Oliveira | P86: 31 9905-1028 | Q86: 100 | S86: SIM | T86: CUMPRIDO | U86: =Table_518[[#This Row],[VALOR]]-Table_518[[#This Row],[ CUSTO]] -> 100
B87: 45834 | D87: Gregor / Krämer | E87: 21 99845-9876 / 22 98118-0352 | F87: Acompanhamento | G87: 1001823-83.2025.8.26.0529 | H87: 45835 | I87: 0.41666667 | J87: Precatória | K87: São Paulo - SP | L87: 200 | N87: CUMPRIDO | O87: Jaqueline Machado | P87: 11 97490-9338 | Q87: 100 | S87: SIM | T87: CUMPRIDO | U87: =Table_518[[#This Row],[VALOR]]-Table_518[[#This Row],[ CUSTO]] -> 100
B88: 45821 | D88: Jessica | E88: 41 9685-0539 | F88: Visita In Loco | G88: Deoclecio Lima Barbosa | H88: 45821 | I88: 0.66666667 | J88: R SETE DE SETEMBRO, 49, CASA CENTRO - DUQUE DE CAXIAS / RJ - 25020190 R BOM JARDIM, 592, FDS VILA LEOPOLDINA - DUQUE DE CAXIAS / RJ - 25035060 | K88: Duque de Caxias - RJ | L88: 220 | M88: ok | N88: CUMPRIDO | O88: Danielle Rodrigues | P88: 21 96555-4385 | Q88: 120 | S88: SIM | T88: CUMPRIDO | U88: =Table_518[[#This Row],[VALOR]]-Table_518[[#This Row],[ CUSTO]] -> 100
B89: 45819 | D89: Jessica | E89: 41 9685-0539 | F89: Coleta de documentos | G89: FRANCISCO SOUZA | H89: 45820 | I89: 0.72916667 | J89: Rua Alvaro Alvim, n°27 13° andar Sala 133, Centro/ Cinelandia | K89: Rio de Janeiro - RJ | L89: =200+40.4 -> 240.4 | M89: ok | N89: CUMPRIDO | O89: Ana Paula Mota | P89: 21 96483-0161 | Q89: =100+40.4 -> 140.4 | S89: SIM | T89: CUMPRIDO | U89: =Table_518[[#This Row],[VALOR]]-Table_518[[#This Row],[ CUSTO]] -> 100
B90: 45810 | D90: Mara - Sid Fontes | E90: 11 96608-6802 | F90: UNA - Presencial | G90: 1000293-42.2025.5.02.0374 | H90: 45817 | I90: 0.65625 | J90: 4ª Vara do Trabalho | K90: Mogi das Cruzes - SP | L90: 250 | N90: CUMPRIDO | O90: Gabriela Maria Aparecida Carneiro | P90: 11 98237-3627 | Q90: 150 | S90: SIM | T90: CUMPRIDO | U90: =Table_518[[#This Row],[VALOR]]-Table_518[[#This Row],[ CUSTO]] -> 100
B91: 45821 | D91: Gabriel Luna | E91: 11 99323-0874 | F91: Instrução - Presencial | G91: 0010756-66.2023.5.15.0116 | H91: 45825 | I91: 0.63888889 | J91: Vara do Trabalho | K91: Tatuí - SP | L91: 270 | M91: 45842 | N91: CUMPRIDO | O91: Sandra Lenhate dos Santos | P91: 11 99795-1181 | Q91: 170 | S91: SIM | T91: CUMPRIDO | U91: =Table_518[[#This Row],[VALOR]]-Table_518[[#This Row],[ CUSTO]] -> 100
B92: 45819 | D92: LACOSTA ADVOGADOS | E92: 21 95922-4000 | F92: Audiência | H92: 45820 | I92: 0.45486111 | J92: Vara do Trabalho | K92: Caçapava - SP | L92: 350 | N92: CUMPRIDO | O92: Keroleyni Rabello | P92: 12 99687-7381 | Q92: 250 | S92: SIM | T92: CUMPRIDO | U92: =Table_518[[#This Row],[VALOR]]-Table_518[[#This Row],[ CUSTO]] -> 100
B93: 45820 | D93: Jessica | E93: 41 9685-0539 | F93: Atendimento e Coleta de Assinaturas | G93: Edmea Benta de Souza | H93: 45821 | I93: 0.625 | J93: Rua México, nº 31 Sala 703, centro | K93: Rio de Janeiro - RJ | L93: =500+48.16 -> 548.16 | M93: ok | N93: CUMPRIDO | O93: Consuelo de Abreu Camargo | P93: 21 96887-3163 | Q93: =400+48.16 -> 448.16 | S93: SIM | T93: CUMPRIDO | U93: =Table_518[[#This Row],[VALOR]]-Table_518[[#This Row],[ CUSTO]] -> 100
B94: 45820 | D94: Camila Goes de Carvalho | E94: 71 9337-4601 | F94: Acompanhamento | H94: 45825 | I94: 0.35416667 | J94: R. Vinte e Seis de Março, 326 - Centro | K94: Poá - SP | L94: 100 | N94: CUMPRIDO | O94: Diligência Própria | S94: SIM | T94: CUMPRIDO | U94: =Table_518[[#This Row],[VALOR]]-Table_518[[#This Row],[ CUSTO]] -> 100
B95: 45817 | D95: Jessica | E95: 41 9685-0539 | F95: Coleta de Assinaturas | G95: Maurício Rodrigues Coelho | H95: 45818 | I95: 0.45833333 | J95: Rua Tomaz Gonzaga, Bairro: Lourdes | K95: Belo Horizonte - MG | L95: =200+56.4 -> 256.4 | M95: ok | N95: CUMPRIDO | O95: Camila Simao | P95: 31 9474-0937 | Q95: =90+56.4 -> 146.4 | S95: SIM | T95: CUMPRIDO | U95: =Table_518[[#This Row],[VALOR]]-Table_518[[#This Row],[ CUSTO]] -> 110
B96: 45817 | D96: Leonardo - Advocacia Soller | E96: 11 95657-2522 / 11 96606-8260 | F96: Conciliação - Presencial | G96: 0013796-74.2025.8.17.8201 | H96: 45821 | I96: 0.42361111 | J96: 16º Juizado Especial Cível e das Relações de Consumo da Capital | K96: Recife - PE | L96: 150 | N96: CUMPRIDO | O96: Priscila Souza | P96: 81 8971-6844 | Q96: 40 | S96: SIM | T96: CUMPRIDO | U96: =Table_518[[#This Row],[VALOR]]-Table_518[[#This Row],[ CUSTO]] -> 110
